Workbook

Sheet UserChat
A1: id | B1: managedAt | C1: 법인명 | D1: 사업자번호 | E1: name | F1: title | G1: description | H1: summarizedMessage | I1: tags | J1: priority | K1: direction | L1: sync | M1: page | N1: userId | O1: assigneeId | P1: firstAssigneeId | Q1: assigneeIdAtFirstClose | R1: managerIds | S1: teamId | T1: mediumType | U1: mediumName | V1: mediumSenderName | W1: state | X1: missedReason | Y1: goalState | Z1: goalCheckedAt | AA1: everOpened | AB1: reopened | AC1: reassigned | AD1: workflowTriggered | AE1: alfTriggered | AF1: replyCount | AG1: replyCountInOperation | AH1: reopenCount | AI1: reassignmentCount | AJ1: createdAt | AK1: updatedAt | AL1: firstWorkflowStartedAt | AM1: firstAskedAt | AN1: firstAlfStartedAt | AO1: firstAlfEndedAt | AP1: firstWorkflowEndedAt | AQ1: firstQueueInAt | AR1: queuedAt | AS1: firstQueueOutAt | AT1: firstOpenedAt | AU1: openedAt | AV1: firstMissedAt | AW1: missedAt | AX1: firstAssignedAt | AY1: firstActiveAt | AZ1: firstAnsweredAt | BA1: repliedAt | BB1: snoozedAt | BC1: firstClosedAt | BD1: closedAt | BE1: totalReplyTime | BF1: totalReplyTimeInOperation | BG1: avgReplyTime | BH1: avgReplyTimeInOperation | BI1: totalSnoozedTime | BJ1: totalSnoozedTimeInOperation | BK1: firstQueueTime | BL1: firstQueueTimeInOperation | BM1: timeToFirstAssignment | BN1: timeToFirstAssignmentInOperation | BO1: timeToFirstAnswer | BP1: timeToFirstAnswerInOperation | BQ1: timeFromFirstAskToFirstAnswer | BR1: timeFromFirstAskToFirstAnswerInOperation | BS1: timeFromFirstAssignmentToFirstAnswer | BT1: timeFromFirstAssignmentToFirstAnswerInOperation | BU1: timeFromFirstActiveToFirstAnswer | BV1: timeFromFirstActiveToFirstAnswerInOperation | BW1: timeFromFirstOpenToFirstAnswer | BX1: timeFromFirstOpenToFirstAnswerInOperation | BY1: timeToFirstClose | BZ1: timeToFirstCloseInOperation | CA1: timeToClose | CB1: timeToCloseInOperation | CC1: timeFromFirstAskToFirstClose | CD1: timeFromFirstAskToFirstCloseInOperation | CE1: timeFromFirstAssignmentToFirstClose | CF1: timeFromFirstAssignmentToFirstCloseInOperation | CG1: timeFromFirstActiveToFirstClose | CH1: timeFromFirstActiveToFirstCloseInOperation | CI1: timeFromFirstOpenToFirstClose | CJ1: timeFromFirstOpenToFirstCloseInOperation | CK1: memberHandlingTime | CL1: memberHandlingTimeInOperation | CM1: firstMemberHandlingTime | CN1: firstMemberHandlingTimeInOperation | CO1: workflowHandlingTime | CP1: alfHandlingTime | CQ1: alfCxScore | CR1: url | CS1: profile.csat | CT1: profile.csatComment
A2: 6996f5f607c5323d04fc | B2: 46072.859 | C2: {=INDEX('User data'!E:E, MATCH(E2, 'User data'!B:B, 0))} -> 주식회사 나우고 (NOWGO) | D2: {=INDEX('User data'!F:F, MATCH(C2, 'User data'!E:E, 0))} -> 753-87-03437 | E2: 김지원 | J2: medium | K2: INBOUND | L2: FALSE | M2: https://www.gowid.com | N2: 69965e75e7898f2d426e | T2: native | W2: initial | Y2: waiting | AA2: FALSE | AB2: FALSE | AC2: FALSE | AD2: FALSE | AE2: TRUE | AJ2: 46072.859 | AK2: 46072.86 | AM2: 46072.859 | AN2: 46072.859 | CR2: https://desk.channel.io/gowid/user-chats/6996f5f607c5323d04fc
A3: 6996e18029ec011e9717 | B3: 46072.799 | C3: {=INDEX('User data'!E:E, MATCH(E3, 'User data'!B:B, 0))} | D3: {=INDEX('User data'!F:F, MATCH(C3, 'User data'!E:E, 0))} -> #N/A | E3: 베이글 219 | J3: medium | K3: INBOUND | L3: FALSE | M3: https://www.gowid.com | N3: 6996e0e650385b354543 | T3: native | W3: initial | Y3: waiting | AA3: FALSE | AB3: FALSE | AC3: FALSE | AD3: FALSE | AE3: TRUE | AJ3: 46072.799 | AK3: 46072.799 | AM3: 46072.799 | AN3: 46072.799 | CR3: https://desk.channel.io/gowid/user-chats/6996e18029ec011e9717
A4: 6996e105f22aec26e769 | B4: 46072.797 | C4: {=INDEX('User data'!E:E, MATCH(E4, 'User data'!B:B, 0))} -> 주식회사 제이엔케이글로벌 (JNK GLOBAL Inc) | D4: {=INDEX('User data'!F:F, MATCH(C4, 'User data'!E:E, 0))} -> 393-87-02181 | E4: 최진주 | H4: [상담요약] - 고객사: 고위드 - 문의요약: 고위드 탈퇴 요청 - 문의유형: 해지 - impact: L2 - 처리내용: 고객 탈퇴 절차 안내, 의견 수렴 - 결과: 상담 종료 - 후속조치: 유선 연락 예정, 탈퇴 절차 진행 | I4: 탈회·탈퇴 | J4: medium | K4: INBOUND | L4: FALSE | M4: https://www.gowid.com | N4: 6996e0ba1115cac5d834 | O4: 607950 | P4: 607950 | Q4: 607950 | R4: 594863, 607950 | T4: native | W4: closed | Y4: none | AA4: TRUE | AB4: FALSE | AC4: FALSE | AD4: TRUE | AE4: TRUE | AF4: 6 | AG4: 5 | AJ4: 46072.797 | AK4: 46073.576 | AL4: 46072.797 | AM4: 46072.797 | AN4: 46072.797 | AO4: 46072.797 | AP4: 46072.797 | AT4: 46072.797 | AU4: 46072.797 | AX4: 46073.42 | AY4: 46072.797 | AZ4: 46073.42 | BA4: 46073.473 | BC4: 46073.576 | BD4: 46073.576 | BE4: 56782 | BF4: 3043 | BG4: 9463 | BH4: 608 | BM4: 53750 | BN4: 246 | BO4: 53754 | BP4: 251 | BQ4: 53755 | BR4: 251 | BS4: 4 | BT4: 4 | BU4: 53752 | BV4: 251 | BW4: 53752 | BX4: 251 | BY4: 67259 | BZ4: 10156 | CA4: 67259 | CB4: 10156 | CC4: 67259 | CD4: 10156 | CE4: 13509 | CF4: 9909 | CG4: 67256 | CH4: 10156 | CI4: 67256 | CJ4: 10156 | CK4: 67256 | CL4: 10156 | CM4: 67256 | CN4: 10156 | CO4: 2 | CP4: 2 | CR4: https://desk.channel.io/gowid/user-chats/6996e105f22aec26e769
A5: 6996de144eda6fa56870 | B5: 46072.789 | C5: {=INDEX('User data'!E:E, MATCH(E5, 'User data'!B:B, 0))} -> 주식회사 로이드케이 | D5: {=INDEX('User data'!F:F, MATCH(C5, 'User data'!E:E, 0))} -> 120-87-67951 | E5: 권대화 | J5: medium | K5: INBOUND | L5: FALSE | M5: https://www.gowid.com | N5: 68db916bd8428156f1aa | T5: native | W5: initial | Y5: waiting | AA5: FALSE | AB5: FALSE | AC5: FALSE | AD5: FALSE | AE5: TRUE | AJ5: 46072.789 | AK5: 46072.789 | AM5: 46072.789 | AN5: 46072.789 | CR5: https://desk.channel.io/gowid/user-chats/6996de144eda6fa56870
A6: 6996d57bbaa55f0e7c31 | B6: 46072.763 | C6: {=INDEX('User data'!E:E, MATCH(E6, 'User data'!B:B, 0))} -> 주식회사 보살핌 | D6: {=INDEX('User data'!F:F, MATCH(C6, 'User data'!E:E, 0))} -> 440-88-02179 | E6: 장한솔 | H6: [상담요약] - 고객사: 고위드 - 문의요약: 법인 카드 결제 문제 - 문의유형: 결제 관련 - impact: L1 - 처리내용: 카드 결제가 되지 않음, 한도 심사 완료 - 결과: 담당자 안내 후 문제 해결 여부 확인 - 후속조치: 추가 문의는 새 창에서 요청 | I6: 카드/한도상하향/오류 | J6: medium | K6: INBOUND | L6: FALSE | M6: https://www.gowid.com | N6: 67049b48d2f96f870032 | O6: 574085 | P6: 574085 | Q6: 574085 | R6: 540030, 574085, 607950 | S6: 13285 | T6: native | W6: closed | Y6: none | AA6: TRUE | AB6: FALSE | AC6: FALSE | AD6: TRUE | AE6: TRUE | AF6: 1 | AJ6: 46072.763 | AK6: 46073.492 | AL6: 46072.764 | AM6: 46072.763 | AN6: 46072.763 | AO6: 46072.764 | AP6: 46072.764 | AQ6: 46072.764 | AS6: 46072.764 | AT6: 46072.764 | AU6: 46072.764 | AX6: 46072.764 | AY6: 46072.764 | AZ6: 46072.827 | BA6: 46072.827 | BC6: 46073.45 | BD6: 46073.45 | BE6: 5454 | BG6: 5454 | BK6: 1 | BL6: 0 | BM6: 37 | BN6: 0 | BO6: 5490 | BP6: 0 | BQ6: 5490 | BR6: 0 | BS6: 5453 | BT6: 0 | BU6: 5453 | BV6: 0 | BW6: 5454 | BX6: 0 | BY6: 59359 | BZ6: 2908 | CA6: 59359 | CB6: 2908 | CC6: 59359 | CD6: 2908 | CE6: 59321 | CF6: 2908 | CG6: 59321 | CH6: 2908 | CI6: 59322 | CJ6: 2908 | CK6: 59321 | CL6: 2908 | CM6: 59321 | CN6: 2908 | CO6: 3 | CP6: 35 | CR6: https://desk.channel.io/gowid/user-chats/6996d57bbaa55f0e7c31
A7: 6996ce7029650198cbd4 | B7: 46072.742 | C7: {=INDEX('User data'!E:E, MATCH(E7, 'User data'!B:B, 0))} -> 주식회사 스티커스코퍼레이션 | D7: {=INDEX('User data'!F:F, MATCH(C7, 'User data'!E:E, 0))} -> 737-81-01527 | E7: 신혜서 | J7: medium | K7: INBOUND | L7: FALSE | M7: https://www.gowid.com | N7: 686b52afe94e86d525a9 | T7: native | W7: initial | Y7: waiting | AA7: FALSE | AB7: FALSE | AC7: FALSE | AD7: FALSE | AE7: TRUE | AJ7: 46072.742 | AK7: 46072.742 | AM7: 46072.742 | AN7: 46072.742 | CR7: https://desk.channel.io/gowid/user-chats/6996ce7029650198cbd4
A8: 6996cd3338319030d407 | B8: 46072.739 | C8: {=INDEX('User data'!E:E, MATCH(E8, 'User data'!B:B, 0))} -> 주식회사 파인우드리빙 | D8: {=INDEX('User data'!F:F, MATCH(C8, 'User data'!E:E, 0))} -> 819-86-01256 | E8: 박지민 | J8: medium | K8: INBOUND | L8: FALSE | M8: https://www.gowid.com | N8: 67f4efbd2d771506b220 | T8: native | W8: initial | Y8: waiting | AA8: FALSE | AB8: FALSE | AC8: FALSE | AD8: FALSE | AE8: TRUE | AJ8: 46072.739 | AK8: 46072.739 | AM8: 46072.739 | AN8: 46072.739 | CR8: https://desk.channel.io/gowid/user-chats/6996cd3338319030d407
A9: 697c672b52de5a403c86 | B9: 46072.733 | C9: {=INDEX('User data'!E:E, MATCH(E9, 'User data'!B:B, 0))} -> 주식회사 커들리스튜디오 | D9: {=INDEX('User data'!F:F, MATCH(C9, 'User data'!E:E, 0))} -> 636-88-02713 | E9: 유화연 | H9: [상담요약] - 고객사: 고위드 - 문의요약: 회사 사무실 관리비 카드 자동 납부 가능 여부 - 문의유형: 카드 이용 관련 - impact: L2 - 처리내용: 자동 납부 기능 신청 불가 안내, 신한카드 고객센터 번호 제공 - 결과: 문제 해결 방법 안내 - 후속조치: 추가 문의 가능 안내 | I9: 지출관리/카드관리 | J9: medium | K9: INBOUND | L9: FALSE | M9: https://www.gowid.com | N9: 681b3720f177b6c20783 | O9: 574085 | P9: 574085 | Q9: 574085 | R9: 574085, 607950 | S9: 13285 | T9: native | W9: closed | Y9: none | AA9: TRUE | AB9: FALSE | AC9: FALSE | AD9: TRUE | AE9: TRUE | AF9: 1 | AJ9: 46052.715 | AK9: 46073.499 | AL9: 46052.715 | AM9: 46052.715 | AN9: 46072.733 | AO9: 46072.734 | AP9: 46072.734 | AQ9: 46072.734 | AS9: 46072.734 | AT9: 46072.734 | AU9: 46072.734 | AX9: 46072.734 | AY9: 46072.734 | AZ9: 46073.421 | BA9: 46073.421 | BC9: 46073.458 | BD9: 46073.458 | BE9: 59351 | BG9: 59351 | BK9: 0 | BL9: 0 | BM9: 115 | BN9: 0 | BO9: 59466 | BP9: 385 | BQ9: 1789028 | BR9: 302785 | BS9: 59350 | BT9: 385 | BU9: 59350 | BV9: 385 | BW9: 59351 | BX9: 385 | BY9: 62613 | BZ9: 3533 | CA9: 62613 | CB9: 3533 | CC9: 1792176 | CD9: 305933 | CE9: 62497 | CF9: 3533 | CG9: 62497 | CH9: 3533 | CI9: 62498 | CJ9: 3533 | CK9: 62497 | CL9: 3533 | CM9: 62497 | CN9: 3533 | CO9: 1729678 | CP9: 114 | CR9: https://desk.channel.io/gowid/user-chats/697c672b52de5a403c86
A10: 6996cb0be0a6e6c19f53 | B10: 46072.732 | C10: {=INDEX('User data'!E:E, MATCH(E10, 'User data'!B:B, 0))} | D10: {=INDEX('User data'!F:F, MATCH(C10, 'User data'!E:E, 0))} -> #N/A | E10: 풋볼 754 | I10: 신규발급(오류) | J10: medium | K10: INBOUND | L10: FALSE | M10: https://www.gowid.com | N10: 6996c313ed0bfe931579 | O10: 607950 | P10: 607950 | R10: 607950 | T10: native | W10: opened | Y10: none | AA10: TRUE | AB10: FALSE | AC10: FALSE | AD10: FALSE | AE10: TRUE | AF10: 1 | AJ10: 46072.732 | AK10: 46073.571 | AM10: 46072.732 | AN10: 46072.732 | AO10: 46072.733 | AT10: 46072.733 | AU10: 46072.733 | AX10: 46072.732 | AY10: 46072.733 | AZ10: 46072.733 | BA10: 46073.421 | BE10: 59458 | BG10: 59458 | BM10: 7 | BN10: 0 | BO10: 17 | BP10: 0 | BQ10: 17 | BR10: 0 | BS10: 10 | BT10: 0 | BW10: 0 | CP10: 17 | CR10: https://desk.channel.io/gowid/user-chats/6996cb0be0a6e6c19f53
A11: 6996c38339acf66f73db | B11: 46072.71 | C11: {=INDEX('User data'!E:E, MATCH(E11, 'User data'!B:B, 0))} | D11: {=INDEX('User data'!F:F, MATCH(C11, 'User data'!E:E, 0))} -> #N/A | E11: 우산 411 | J11: medium | K11: INBOUND | L11: FALSE | M11: https://www.gowid.com | N11: 6996a9d33aac31bd8158 | T11: native | W11: initial | Y11: waiting | AA11: FALSE | AB11: FALSE | AC11: FALSE | AD11: FALSE | AE11: TRUE | AJ11: 46072.71 | AK11: 46072.712 | AM11: 46072.71 | AN11: 46072.71 | CR11: https://desk.channel.io/gowid/user-chats/6996c38339acf66f73db
A12: 6996b9fb528495ca8c69 | B12: 46072.682 | C12: {=INDEX('User data'!E:E, MATCH(E12, 'User data'!B:B, 0))} -> 주식회사 앳홈 | D12: {=INDEX('User data'!F:F, MATCH(C12, 'User data'!E:E, 0))} -> 136-81-34676 | E12: 이상희 | H12: 문의 내용이 15글자 이하이므로 요약할 내용이 없습니다. | J12: medium | K12: INBOUND | L12: FALSE | M12: https://www.gowid.com | N12: 698c0ad19c6b7bb05487 | T12: native | W12: closed | Y12: waiting | AA12: FALSE | AB12: FALSE | AC12: FALSE | AD12: FALSE | AE12: TRUE | AJ12: 46072.682 | AK12: 46072.682 | AM12: 46072.682 | AN12: 46072.682 | BC12: 46072.682 | BD12: 46072.682 | BY12: 29 | BZ12: 29 | CA12: 29 | CB12: 29 | CC12: 29 | CD12: 29 | CR12: https://desk.channel.io/gowid/user-chats/6996b9fb528495ca8c69
A13: 6996b8ff711dff23d7ae | B13: 46072.679 | C13: {=INDEX('User data'!E:E, MATCH(E13, 'User data'!B:B, 0))} -> (주)쿨스쿨 | D13: {=INDEX('User data'!F:F, MATCH(C13, 'User data'!E:E, 0))} -> 314-86-66749 | E13: 오진연 | J13: medium | K13: INBOUND | L13: FALSE | M13: https://www.gowid.com | N13: 698e6abe35dc2af1bcf2 | T13: native | W13: initial | Y13: waiting | AA13: FALSE | AB13: FALSE | AC13: FALSE | AD13: FALSE | AE13: TRUE | AJ13: 46072.679 | AK13: 46072.687 | AM13: 46072.679 | AN13: 46072.679 | CR13: https://desk.channel.io/gowid/user-chats/6996b8ff711dff23d7ae
A14: 6996b2968cf1975c3cb5 | B14: 46072.66 | C14: {=INDEX('User data'!E:E, MATCH(E14, 'User data'!B:B, 0))} | D14: {=INDEX('User data'!F:F, MATCH(C14, 'User data'!E:E, 0))} -> #N/A | E14: 팔레트 582 | J14: medium | K14: INBOUND | L14: FALSE | M14: https://www.gowid.com | N14: 6996a69cd3ca03317e6e | T14: native | W14: initial | Y14: waiting | AA14: FALSE | AB14: FALSE | AC14: FALSE | AD14: FALSE | AE14: TRUE | AJ14: 46072.66 | AK14: 46072.661 | AM14: 46072.66 | AN14: 46072.66 | CR14: https://desk.channel.io/gowid/user-chats/6996b2968cf1975c3cb5
A15: 6996b047df5bc0d1ba53 | B15: 46072.656 | C15: {=INDEX('User data'!E:E, MATCH(E15, 'User data'!B:B, 0))} -> 주식회사 트위넬 | D15: {=INDEX('User data'!F:F, MATCH(C15, 'User data'!E:E, 0))} -> 8388103911 | E15: 주식회사 트위넬 | H15: [상담요약] - 고객사: 고위드 - 문의요약: 멤버 정보 변경 요청 - 문의유형: 정보 수정 - impact: L2 - 처리내용: 회원가입 미완료 확인 - 결과: 정보 수정 불가 - 후속조치: 회원가입 완료 후 이메일로 변경 지원 | J15: medium | K15: OUTBOUND | L15: FALSE | N15: 6996af79a1277aaaf40a | O15: 607950 | P15: 607950 | R15: 607950 | T15: email | U15: email | W15: snoozed | Y15: waiting | AA15: TRUE | AB15: FALSE | AC15: FALSE | AD15: TRUE | AE15: FALSE | AF15: 1 | AG15: 1 | AJ15: 46072.653 | AK15: 46073.521 | AL15: 46072.657 | AM15: 46072.656 | AP15: 46072.657 | AT15: 46072.656 | AU15: 46073.518 | AX15: 46072.653 | AY15: 46072.656 | AZ15: 46072.661 | BA15: 46072.661 | BB15: 46073.521 | BE15: 377 | BF15: 377 | BG15: 377 | BH15: 377 | BI15: 14400 | BJ15: 8717 | BO15: 377 | BP15: 377 | BQ15: 377 | BR15: 377 | BS15: 670 | BT15: 670 | BU15: 377 | BV15: 377 | BW15: 377 | BX15: 377 | CO15: 3 | CR15: https://desk.channel.io/gowid/user-chats/6996b047df5bc0d1ba53
A16: 6996af7c373f0a18ddaf | B16: 46072.651 | C16: {=INDEX('User data'!E:E, MATCH(E16, 'User data'!B:B, 0))} -> 주식회사 트위넬 | D16: {=INDEX('User data'!F:F, MATCH(C16, 'User data'!E:E, 0))} -> 8388103911 | E16: 주식회사 트위넬 | H16: [상담요약] - 고객사: - 문의요약: 메일 주소 오류 - 문의유형: 정보 수정 요청 - impact: L1 - 처리내용: 고객의 메일 주소 확인, 멤버 정보 변경 요청 - 결과: 법인명과 사업자 번호 요청 - 후속조치: 고객의 추가 정보 대기 | J16: medium | K16: INBOUND | L16: FALSE | M16: https://gowid.channel.io | N16: 6996af79a1277aaaf40a | O16: 607950 | P16: 607950 | R16: 607950 | T16: native | W16: snoozed | Y16: waiting | AA16: TRUE | AB16: FALSE | AC16: FALSE | AD16: TRUE | AE16: TRUE | AF16: 1 | AG16: 1 | AJ16: 46072.651 | AK16: 46073.521 | AL16: 46072.652 | AM16: 46072.651 | AN16: 46072.651 | AO16: 46072.651 | AP16: 46072.652 | AT16: 46072.651 | AU16: 46073.518 | AX16: 46072.652 | AY16: 46072.651 | AZ16: 46072.652 | BA16: 46072.652 | BB16: 46073.521 | BE16: 69 | BF16: 69 | BG16: 69 | BH16: 69 | BI16: 14399 | BJ16: 8716 | BM16: 113 | BN16: 113 | BO16: 115 | BP16: 115 | BQ16: 115 | BR16: 115 | BS16: 1 | BT16: 1 | BU16: 69 | BV16: 69 | BW16: 69 | BX16: 69 | CO16: 3 | CP16: 2 | CR16: https://desk.channel.io/gowid/user-chats/6996af7c373f0a18ddaf
A17: 6996ac71bcd572c171f4 | B17: 46072.642 | C17: {=INDEX('User data'!E:E, MATCH(E17, 'User data'!B:B, 0))} -> 주식회사 오픈아이오티 | D17: {=INDEX('User data'!F:F, MATCH(C17, 'User data'!E:E, 0))} -> 175-88-03861 | E17: 김동은 | J17: medium | K17: INBOUND | L17: FALSE | M17: https://www.gowid.com | N17: 69857160abf7ab10bf7b | T17: native | W17: initial | Y17: waiting | AA17: FALSE | AB17: FALSE | AC17: FALSE | AD17: FALSE | AE17: TRUE | AJ17: 46072.641 | AK17: 46072.642 | AM17: 46072.642 | AN17: 46072.642 | CR17: https://desk.channel.io/gowid/user-chats/6996ac71bcd572c171f4
A18: 6996ac37bdf4850a6fb0 | B18: 46072.641 | C18: {=INDEX('User data'!E:E, MATCH(E18, 'User data'!B:B, 0))} -> 주식회사 아토즈소프트 | D18: {=INDEX('User data'!F:F, MATCH(C18, 'User data'!E:E, 0))} -> 117-81-81687 | E18: 서호진 | J18: medium | K18: INBOUND | L18: FALSE | M18: https://www.gowid.com | N18: 686c7842bdfc6fd158a6 | T18: native | W18: initial | Y18: waiting | AA18: FALSE | AB18: FALSE | AC18: FALSE | AD18: FALSE | AE18: TRUE | AJ18: 46072.641 | AK18: 46072.644 | AM18: 46072.641 | AN18: 46072.641 | CR18: https://desk.channel.io/gowid/user-chats/6996ac37bdf4850a6fb0
A19: 6996a8437d5b72bf1640 | B19: 46072.629 | C19: {=INDEX('User data'!E:E, MATCH(E19, 'User data'!B:B, 0))} -> 주식회사 아일로 | D19: {=INDEX('User data'!F:F, MATCH(C19, 'User data'!E:E, 0))} -> 322-88-02342 | E19: 류지현 | J19: medium | K19: INBOUND | L19: FALSE | M19: https://www.gowid.com | N19: 65d6a61a8181fd32e65c | T19: native | W19: initial | Y19: waiting | AA19: FALSE | AB19: FALSE | AC19: FALSE | AD19: FALSE | AE19: TRUE | AJ19: 46072.629 | AK19: 46072.629 | AM19: 46072.629 | AN19: 46072.629 | CR19: https://desk.channel.io/gowid/user-chats/6996a8437d5b72bf1640
A20: 6996a5d9e42382cabfa6 | B20: 46072.622 | C20: {=INDEX('User data'!E:E, MATCH(E20, 'User data'!B:B, 0))} -> (주)튜링 | D20: {=INDEX('User data'!F:F, MATCH(C20, 'User data'!E:E, 0))} -> 254-87-01382 | E20: 신지은 | J20: medium | K20: INBOUND | L20: FALSE | M20: https://gowid.channel.io | N20: 6711e6d10bd2776ab6b3 | T20: native | W20: initial | Y20: waiting | AA20: FALSE | AB20: FALSE | AC20: FALSE | AD20: FALSE | AE20: TRUE | AJ20: 46072.622 | AK20: 46072.622 | AM20: 46072.622 | AN20: 46072.622 | CR20: https://desk.channel.io/gowid/user-chats/6996a5d9e42382cabfa6
A21: 6996a5c85da03308cb7d | B21: 46072.622 | C21: {=INDEX('User data'!E:E, MATCH(E21, 'User data'!B:B, 0))} -> 주식회사 플루토 (PLUTO) | D21: {=INDEX('User data'!F:F, MATCH(C21, 'User data'!E:E, 0))} -> 444-87-02140 | E21: 양해민 | J21: medium | K21: INBOUND | L21: FALSE | M21: https://www.gowid.com | N21: 65d2e377ef7151c31c25 | T21: native | W21: initial | Y21: waiting | AA21: FALSE | AB21: FALSE | AC21: FALSE | AD21: FALSE | AE21: TRUE | AJ21: 46072.622 | AK21: 46072.622 | AM21: 46072.622 | AN21: 46072.622 | CR21: https://desk.channel.io/gowid/user-chats/6996a5c85da03308cb7d
A22: 6996a5821c6300cff115 | B22: 46072.621 | C22: {=INDEX('User data'!E:E, MATCH(E22, 'User data'!B:B, 0))} -> 주식회사 플루비(PLUVI Co.,Ltd) | D22: {=INDEX('User data'!F:F, MATCH(C22, 'User data'!E:E, 0))} -> 830-86-03552 | E22: 박준성 | J22: medium | K22: INBOUND | L22: FALSE | M22: https://www.gowid.com | N22: 696f31eeae4409bc6c96 | T22: native | W22: initial | Y22: waiting | AA22: FALSE | AB22: FALSE | AC22: FALSE | AD22: FALSE | AE22: TRUE | AJ22: 46072.621 | AK22: 46072.622 | AM22: 46072.621 | AN22: 46072.621 | CR22: https://desk.channel.io/gowid/user-chats/6996a5821c6300cff115
A23: 6996a3f63e6dfd8a17ef | B23: 46072.616 | C23: {=INDEX('User data'!E:E, MATCH(E23, 'User data'!B:B, 0))} -> (주)온차 | D23: {=INDEX('User data'!F:F, MATCH(C23, 'User data'!E:E, 0))} -> 799-81-02937 | E23: 정진미 | J23: medium | K23: INBOUND | L23: FALSE | M23: https://www.gowid.com | N23: 69967cd2267eb0097db1 | T23: native | W23: initial | Y23: waiting | AA23: FALSE | AB23: FALSE | AC23: FALSE | AD23: FALSE | AE23: TRUE | AJ23: 46072.616 | AK23: 46072.617 | AM23: 46072.616 | AN23: 46072.616 | CR23: https://desk.channel.io/gowid/user-chats/6996a3f63e6dfd8a17ef
A24: 6996a1db5dfe1fb7581c | B24: 46072.61 | C24: {=INDEX('User data'!E:E, MATCH(E24, 'User data'!B:B, 0))} -> 주식회사 솔로몬랩스(Solomon Labs Co., Ltd.) | D24: {=INDEX('User data'!F:F, MATCH(C24, 'User data'!E:E, 0))} -> 249-87-03675 | E24: 박다솜 | J24: medium | K24: INBOUND | L24: FALSE | M24: https://www.gowid.com | N24: 6909a9ef55643f86a4d0 | T24: native | W24: initial | Y24: waiting | AA24: FALSE | AB24: FALSE | AC24: FALSE | AD24: FALSE | AE24: TRUE | AJ24: 46072.61 | AK24: 46072.779 | AM24: 46072.61 | AN24: 46072.61 | CR24: https://desk.channel.io/gowid/user-chats/6996a1db5dfe1fb7581c
A25: 69969b9781793e8a72d7 | B25: 46072.592 | C25: {=INDEX('User data'!E:E, MATCH(E25, 'User data'!B:B, 0))} -> 주식회사 이터녹스 | D25: {=INDEX('User data'!F:F, MATCH(C25, 'User data'!E:E, 0))} -> 839-86-03001 | E25: 정한길 | J25: medium | K25: INBOUND | L25: FALSE | M25: https://www.gowid.com | N25: 6954cdaf9c0ee46a027b | T25: native | W25: initial | Y25: waiting | AA25: FALSE | AB25: FALSE | AC25: FALSE | AD25: FALSE | AE25: TRUE | AJ25: 46072.592 | AK25: 46072.593 | AM25: 46072.592 | AN25: 46072.592 | CR25: https://desk.channel.io/gowid/user-chats/69969b9781793e8a72d7
A26: 69969a5fe1fc17b96564 | B26: 46072.588 | C26: {=INDEX('User data'!E:E, MATCH(E26, 'User data'!B:B, 0))} -> 주식회사 스튜디오크립티드 | D26: {=INDEX('User data'!F:F, MATCH(C26, 'User data'!E:E, 0))} -> 329-86-02368 | E26: 백한열 | J26: medium | K26: INBOUND | L26: FALSE | M26: https://www.gowid.com | N26: 69969a3eada6ff84cc1d | T26: native | W26: initial | Y26: waiting | AA26: FALSE | AB26: FALSE | AC26: FALSE | AD26: FALSE | AE26: TRUE | AJ26: 46072.588 | AK26: 46072.588 | AM26: 46072.588 | AN26: 46072.588 | CR26: https://desk.channel.io/gowid/user-chats/69969a5fe1fc17b96564
A27: 6996945158bb08e6d581 | B27: 46072.57 | C27: {=INDEX('User data'!E:E, MATCH(E27, 'User data'!B:B, 0))} -> 주식회사 리훈 (RIHOON CO., LTD.) | D27: {=INDEX('User data'!F:F, MATCH(C27, 'User data'!E:E, 0))} -> 489-88-01777 | E27: 박이훈 | J27: medium | K27: INBOUND | L27: FALSE | M27: https://www.gowid.com | N27: 660b9ca16bc23e2402b8 | T27: native | W27: initial | Y27: waiting | AA27: FALSE | AB27: FALSE | AC27: FALSE | AD27: FALSE | AE27: TRUE | AJ27: 46072.57 | AK27: 46073.57 | AM27: 46072.57 | AN27: 46072.57 | CR27: https://desk.channel.io/gowid/user-chats/6996945158bb08e6d581
A28: 6996900cec4cc2ff1764 | B28: 46072.557 | C28: {=INDEX('User data'!E:E, MATCH(E28, 'User data'!B:B, 0))} -> 주식회사 브랜뉴에이전시 (Brand New Agency Inc.) | D28: {=INDEX('User data'!F:F, MATCH(C28, 'User data'!E:E, 0))} -> 639-87-02302 | E28: 서강민 | J28: medium | K28: INBOUND | L28: FALSE | M28: https://www.gowid.com | N28: 6684d193243ee7c2e826 | T28: native | W28: initial | Y28: waiting | AA28: FALSE | AB28: FALSE | AC28: FALSE | AD28: FALSE | AE28: TRUE | AJ28: 46072.557 | AK28: 46073.558 | AM28: 46072.557 | AN28: 46072.557 | CR28: https://desk.channel.io/gowid/user-chats/6996900cec4cc2ff1764
A29: 6996900132e6ee07c769 | B29: 46072.557 | C29: {=INDEX('User data'!E:E, MATCH(E29, 'User data'!B:B, 0))} -> 주식회사 브랜뉴에이전시 (Brand New Agency Inc.) | D29: {=INDEX('User data'!F:F, MATCH(C29, 'User data'!E:E, 0))} -> 639-87-02302 | E29: 서강민 | J29: medium | K29: INBOUND | L29: FALSE | M29: https://www.gowid.com | N29: 6684d193243ee7c2e826 | T29: native | W29: initial | Y29: waiting | AA29: FALSE | AB29: FALSE | AC29: FALSE | AD29: FALSE | AE29: TRUE | AJ29: 46072.557 | AK29: 46073.557 | AM29: 46072.557 | AN29: 46072.557 | CR29: https://desk.channel.io/gowid/user-chats/6996900132e6ee07c769
A30: 69968b6fc41146c130e6 | B30: 46072.544 | C30: {=INDEX('User data'!E:E, MATCH(E30, 'User data'!B:B, 0))} -> 주식회사 오가시스 (ORGASIS Corp.) | D30: {=INDEX('User data'!F:F, MATCH(C30, 'User data'!E:E, 0))} -> 531-87-02594 | E30: 황중식 | H30: 요약할 내용이 없습니다. | I30: 멤버관리(단순문의) | J30: medium | K30: INBOUND | L30: FALSE | M30: https://www.gowid.com | N30: 698d2dc165342e2d8c0e | O30: 574085 | P30: 574085 | Q30: 574085 | R30: 574085, 607950 | S30: 13285 | T30: native | W30: closed | Y30: waiting | AA30: TRUE | AB30: TRUE | AC30: FALSE | AD30: TRUE | AE30: TRUE | AF30: 5 | AG30: 4 | AH30: 1 | AJ30: 46072.544 | AK30: 46072.65 | AL30: 46072.544 | AM30: 46072.544 | AN30: 46072.544 | AO30: 46072.544 | AP30: 46072.544 | AQ30: 46072.544 | AS30: 46072.544 | AT30: 46072.544 | AU30: 46072.607 | AX30: 46072.544 | AY30: 46072.544 | AZ30: 46072.567 | BA30: 46072.58 | BB30: 46072.567 | BC30: 46072.599 | BD30: 46072.608 | BE30: 2462 | BF30: 484 | BG30: 492 | BH30: 121 | BI30: 7 | BJ30: 7 | BK30: 2 | BL30: 0 | BM30: 6 | BN30: 0 | BO30: 1983 | BP30: 387 | BQ30: 1983 | BR30: 387 | BS30: 1977 | BT30: 387 | BU30: 1977 | BV30: 387 | BW30: 1979 | BX30: 387 | BY30: 4755 | BZ30: 3159 | CA30: 5531 | CB30: 3935 | CC30: 4755 | CD30: 3159 | CE30: 4749 | CF30: 3159 | CG30: 4749 | CH30: 3159 | CI30: 4751 | CJ30: 3159 | CK30: 4809 | CL30: 3219 | CM30: 4741 | CN30: 3151 | CO30: 2 | CP30: 3 | CR30: https://desk.channel.io/gowid/user-chats/69968b6fc41146c130e6 | CS30: 5
A31: 6996812c771869e2e69b | B31: 46072.513 | C31: {=INDEX('User data'!E:E, MATCH(E31, 'User data'!B:B, 0))} | D31: {=INDEX('User data'!F:F, MATCH(C31, 'User data'!E:E, 0))} -> #N/A | E31: 팅커벨 026 | J31: medium | K31: INBOUND | L31: FALSE | M31: https://www.gowid.com | N31: 6996811f9fe00a4391fb | T31: native | W31: initial | Y31: waiting | AA31: FALSE | AB31: FALSE | AC31: FALSE | AD31: FALSE | AE31: TRUE | AJ31: 46072.513 | AK31: 46073.514 | AM31: 46072.513 | AN31: 46072.513 | CR31: https://desk.channel.io/gowid/user-chats/6996812c771869e2e69b
A32: 699680185446fb920981 | B32: 46072.51 | C32: {=INDEX('User data'!E:E, MATCH(E32, 'User data'!B:B, 0))} | D32: {=INDEX('User data'!F:F, MATCH(C32, 'User data'!E:E, 0))} -> #N/A | E32: 스타 325 | J32: medium | K32: INBOUND | L32: FALSE | M32: https://docs.channel.io/gowid-guide/ko/articles/고위드-법인카드-스펙-안내-a97b7c3f | N32: 698ed7de08d3482713fe | T32: native | W32: initial | Y32: waiting | AA32: FALSE | AB32: FALSE | AC32: FALSE | AD32: FALSE | AE32: TRUE | AJ32: 46072.51 | AK32: 46072.752 | AM32: 46072.51 | AN32: 46072.51 | CR32: https://desk.channel.io/gowid/user-chats/699680185446fb920981
A33: 69967bcfa966a7cf3c4d | B33: 46072.498 | C33: {=INDEX('User data'!E:E, MATCH(E33, 'User data'!B:B, 0))} -> 주식회사 디에프코퍼레이션 | D33: {=INDEX('User data'!F:F, MATCH(C33, 'User data'!E:E, 0))} -> 808-86-00446 | E33: 퍼스트캔버스 | J33: medium | K33: INBOUND | L33: FALSE | M33: https://www.gowid.com | N33: 67217a30884027249f64 | T33: native | W33: initial | Y33: waiting | AA33: FALSE | AB33: FALSE | AC33: FALSE | AD33: FALSE | AE33: TRUE | AJ33: 46072.497 | AK33: 46073.498 | AM33: 46072.498 | AN33: 46072.498 | CR33: https://desk.channel.io/gowid/user-chats/69967bcfa966a7cf3c4d
A34: 698d979a04d5b1245178 | B34: 46072.497 | C34: {=INDEX('User data'!E:E, MATCH(E34, 'User data'!B:B, 0))} -> 주식회사 플루토 (PLUTO) | D34: {=INDEX('User data'!F:F, MATCH(C34, 'User data'!E:E, 0))} -> 444-87-02140 | E34: 양해민 | H34: 상담 내용이 15글자 이하이므로 요약할 내용이 없습니다. | I34: 카드/한도상하향 | J34: medium | K34: OUTBOUND | L34: FALSE | N34: 65d2e377ef7151c31c25 | O34: 574085 | P34: 574085 | Q34: 574085 | R34: 574085, 607950 | T34: email | U34: email | W34: closed | Y34: none | AA34: TRUE | AB34: FALSE | AC34: FALSE | AD34: TRUE | AE34: FALSE | AF34: 2 | AG34: 2 | AJ34: 46065.753 | AK34: 46072.616 | AL34: 46072.498 | AM34: 46072.497 | AP34: 46072.498 | AT34: 46072.497 | AU34: 46072.567 | AX34: 46065.753 | AY34: 46072.497 | AZ34: 46072.504 | BA34: 46072.574 | BB34: 46072.507 | BC34: 46072.574 | BD34: 46072.574 | BE34: 1196 | BF34: 1196 | BG34: 598 | BH34: 598 | BI34: 5206 | BJ34: 1606 | BO34: 600 | BP34: 600 | BQ34: 601 | BR34: 601 | BS34: 583286 | BT34: 93952 | BU34: 600 | BV34: 600 | BW34: 600 | BX34: 600 | BY34: 6657 | BZ34: 3057 | CA34: 6657 | CB34: 3057 | CC34: 6657 | CD34: 3057 | CE34: 589342 | CF34: 96408 | CG34: 6657 | CH34: 3057 | CI34: 6657 | CJ34: 3057 | CK34: 1451 | CL34: 1451 | CM34: 1451 | CN34: 1451 | CO34: 3 | CR34: https://desk.channel.io/gowid/user-chats/698d979a04d5b1245178
A35: 69967b01ae8debaaf0de | B35: 46072.495 | C35: {=INDEX('User data'!E:E, MATCH(E35, 'User data'!B:B, 0))} -> 주식회사 스케일업스쿼드(SCALEUPSQUAD Corp.) | D35: {=INDEX('User data'!F:F, MATCH(C35, 'User data'!E:E, 0))} -> 413-86-02907 | E35: 박승표 | H35: - 고객사: 고위드 - 문의요약: 상담원 연결 요청 및 탄력 조정 적용 시기 문의 - 문의유형: 상담 요청 - impact: L2 - 처리내용: 상담원과 연결 요청 - 결과: 대기 중 - 후속조치: 추가 확인 필요 | I35: 구독/GWS | J35: medium | K35: INBOUND | L35: FALSE | M35: https://www.gowid.com | N35: 6728a0d15d906aa40765 | O35: 594863 | P35: 574085 | R35: 533671, 574085, 594863 | S35: 13285 | T35: native | W35: opened | Y35: waiting | AA35: TRUE | AB35: FALSE | AC35: TRUE | AD35: TRUE | AE35: TRUE | AF35: 1 | AG35: 1 | AI35: 1 | AJ35: 46072.495 | AK35: 46073.542 | AL35: 46072.497 | AM35: 46072.495 | AN35: 46072.495 | AO35: 46072.496 | AP35: 46072.497 | AQ35: 46072.496 | AS35: 46072.496 | AT35: 46072.496 | AU35: 46073.542 | AX35: 46072.496 | AY35: 46072.496 | AZ35: 46072.506 | BA35: 46072.506 | BB35: 46072.567 | BE35: 824 | BF35: 824 | BG35: 824 | BH35: 824 | BI35: 84229 | BJ35: 21219 | BK35: 0 | BL35: 0 | BM35: 94 | BN35: 94 | BO35: 918 | BP35: 918 | BQ35: 918 | BR35: 918 | BS35: 823 | BT35: 823 | BU35: 823 | BV35: 823 | BW35: 824 | BX35: 824 | CO35: 3 | CP35: 93 | CR35: https://desk.channel.io/gowid/user-chats/69967b01ae8debaaf0de
A36: 69967a4c2b07490a20c4 | B36: 46072.493 | C36: {=INDEX('User data'!E:E, MATCH(E36, 'User data'!B:B, 0))} -> 주식회사 스케일업스쿼드(SCALEUPSQUAD Corp.) | D36: {=INDEX('User data'!F:F, MATCH(C36, 'User data'!E:E, 0))} -> 413-86-02907 | E36: 박승표 | J36: medium | K36: INBOUND | L36: FALSE | M36: https://www.gowid.com | N36: 6728a0d15d906aa40765 | T36: native | W36: initial | Y36: waiting | AA36: FALSE | AB36: FALSE | AC36: FALSE | AD36: FALSE | AE36: TRUE | AJ36: 46072.493 | AK36: 46073.493 | AM36: 46072.493 | AN36: 46072.493 | CR36: https://desk.channel.io/gowid/user-chats/69967a4c2b07490a20c4
A37: 69967989eaefdf6b94b4 | B37: 46072.491 | C37: {=INDEX('User data'!E:E, MATCH(E37, 'User data'!B:B, 0))} -> 주식회사 코네이스 | D37: {=INDEX('User data'!F:F, MATCH(C37, 'User data'!E:E, 0))} -> 857-81-02868 | E37: 조명광 | H37: [상담요약] - 고객사: 롯데카드 - 문의요약: 카드 한도 상향 신청 진행 상황 - 문의유형: 승인 상태 문의 - impact: L2 - 처리내용: 신청 중인 카드 한도 상향 심사 확인 - 결과: 심사 차주 초 완료 예정, 메일 안내 예정 - 후속조치: 추가 문의 필요 시 새 창에서 문의 | I37: 카드/한도상하향 | J37: medium | K37: INBOUND | L37: FALSE | M37: https://www.gowid.com | N37: 695c9837cb14ff9fd3b6 | O37: 574085 | P37: 574085 | Q37: 574085 | R37: 574085, 607950 | S37: 13285 | T37: native | W37: closed | Y37: none | AA37: TRUE | AB37: FALSE | AC37: FALSE | AD37: TRUE | AE37: TRUE | AF37: 3 | AG37: 3 | AJ37: 46072.491 | AK37: 46072.548 | AL37: 46072.507 | AM37: 46072.491 | AN37: 46072.491 | AO37: 46072.504 | AQ37: 46072.504 | AS37: 46072.504 | AT37: 46072.504 | AU37: 46072.504 | AX37: 46072.504 | AY37: 46072.504 | AZ37: 46072.504 | BA37: 46072.506 | BC37: 46072.507 | BD37: 46072.507 | BE37: 67 | BF37: 67 | BG37: 22 | BH37: 22 | BK37: 1 | BL37: 1 | BM37: 1105 | BN37: 1105 | BO37: 1139 | BP37: 1139 | BQ37: 1139 | BR37: 1139 | BS37: 33 | BT37: 33 | BU37: 33 | BV37: 33 | BW37: 34 | BX37: 34 | BY37: 1340 | BZ37: 1340 | CA37: 1340 | CB37: 1340 | CC37: 1341 | CD37: 1341 | CE37: 235 | CF37: 235 | CG37: 235 | CH37: 235 | CI37: 236 | CJ37: 236 | CK37: 235 | CL37: 235 | CM37: 235 | CN37: 235 | CP37: 1104 | CR37: https://desk.channel.io/gowid/user-chats/69967989eaefdf6b94b4
A38: 699675ec3808cb178591 | B38: 46072.48 | C38: {=INDEX('User data'!E:E, MATCH(E38, 'User data'!B:B, 0))} -> 가제트코리아 주식회사 | D38: {=INDEX('User data'!F:F, MATCH(C38, 'User data'!E:E, 0))} -> 786-87-01837 | E38: 이현주 | H38: [상담요약] - 고객사: - 문의요약: 날짜 변경 및 라이선스 추가 요청 - 문의유형: 라이선스 변경 - impact: L2 - 처리내용: 3월 2일에서 3월 3일로 변경, 라이선스 3개 추가 요청 - 결과: 3월 3일 자정 3개 라이선스 추가 확정 - 후속조치: 세팅 진행 예정 | I38: 구독/GWS | J38: medium | K38: INBOUND | L38: FALSE | M38: https://www.gowid.com | N38: 691681b63ec1d5a14061 | O38: 594863 | P38: 607950 | Q38: 594863 | R38: 533671, 594863, 607950 | S38: 13288 | T38: native | W38: closed | Y38: none | AA38: TRUE | AB38: FALSE | AC38: TRUE | AD38: TRUE | AE38: TRUE | AF38: 7 | AG38: 6 | AI38: 1 | AJ38: 46072.48 | AK38: 46072.726 | AL38: 46072.572 | AM38: 46072.48 | AN38: 46072.48 | AO38: 46072.481 | AP38: 46072.572 | AT38: 46072.481 | AU38: 46072.571 | AX38: 46072.481 | AY38: 46072.481 | AZ38: 46072.481 | BA38: 46072.681 | BB38: 46072.567 | BC38: 46072.684 | BD38: 46072.684 | BE38: 14386 | BF38: 7602 | BG38: 2055 | BH38: 1267 | BI38: 355 | BJ38: 355 | BM38: 67 | BN38: 67 | BO38: 68 | BP38: 68 | BQ38: 68 | BR38: 68 | BS38: 0 | BT38: 0 | BU38: 20 | BV38: 20 | BW38: 20 | BX38: 20 | BY38: 17614 | BZ38: 14014 | CA38: 17614 | CB38: 14014 | CC38: 17614 | CD38: 14014 | CE38: 17547 | CF38: 13947 | CG38: 17567 | CH38: 13967 | CI38: 17567 | CJ38: 13967 | CK38: 17211 | CL38: 13611 | CM38: 17211 | CN38: 13611 | CO38: 3 | CP38: 47 | CR38: https://desk.channel.io/gowid/user-chats/699675ec3808cb178591
A39: 699675f5aa3871542499 | B39: 46072.48 | C39: {=INDEX('User data'!E:E, MATCH(E39, 'User data'!B:B, 0))} -> 주식회사 프롬프트타운 | D39: {=INDEX('User data'!F:F, MATCH(C39, 'User data'!E:E, 0))} -> 526-81-03003 | E39: 서진희 | J39: medium | K39: INBOUND | L39: FALSE | M39: https://www.gowid.com | N39: 685a5613b7d1c5e11ae5 | T39: native | W39: initial | Y39: waiting | AA39: FALSE | AB39: FALSE | AC39: FALSE | AD39: FALSE | AE39: TRUE | AJ39: 46072.48 | AK39: 46073.48 | AM39: 46072.48 | AN39: 46072.48 | CR39: https://desk.channel.io/gowid/user-chats/699675f5aa3871542499
A40: 699675b48a63d6b03ed4 | B40: 46072.479 | C40: {=INDEX('User data'!E:E, MATCH(E40, 'User data'!B:B, 0))} -> 헬로스킨 주식회사(HELLO SKIN Co.,Ltd.) | D40: {=INDEX('User data'!F:F, MATCH(C40, 'User data'!E:E, 0))} -> 888-88-00596 | E40: 지소영 | H40: 요약할 내용이 없습니다. | I40: 카드/한도상하향 | J40: medium | K40: INBOUND | L40: FALSE | M40: https://www.gowid.com | N40: 696db3205e96892e8e31 | O40: 574085 | P40: 574085 | Q40: 574085 | R40: 574085, 607950 | S40: 13285 | T40: native | W40: closed | Y40: none | AA40: TRUE | AB40: FALSE | AC40: FALSE | AD40: TRUE | AE40: TRUE | AF40: 2 | AG40: 2 | AJ40: 46072.479 | AK40: 46072.616 | AL40: 46072.574 | AM40: 46072.479 | AN40: 46072.479 | AO40: 46072.48 | AQ40: 46072.48 | AS40: 46072.48 | AT40: 46072.48 | AU40: 46072.567 | AX40: 46072.48 | AY40: 46072.48 | AZ40: 46072.481 | BA40: 46072.574 | BB40: 46072.567 | BC40: 46072.574 | BD40: 46072.574 | BE40: 656 | BF40: 656 | BG40: 328 | BH40: 328 | BI40: 20 | BJ40: 20 | BK40: 0 | BL40: 0 | BM40: 87 | BN40: 87 | BO40: 131 | BP40: 131 | BQ40: 131 | BR40: 131 | BS40: 44 | BT40: 44 | BU40: 43 | BV40: 43 | BW40: 44 | BX40: 44 | BY40: 8202 | BZ40: 4602 | CA40: 8202 | CB40: 4602 | CC40: 8202 | CD40: 4602 | CE40: 8115 | CF40: 4515 | CG40: 8115 | CH40: 4515 | CI40: 8115 | CJ40: 4515 | CK40: 8095 | CL40: 4495 | CM40: 8095 | CN40: 4495 | CP40: 87 | CR40: https://desk.channel.io/gowid/user-chats/699675b48a63d6b03ed4
A41: 69967557ccb0490826ab | B41: 46072.478 | C41: {=INDEX('User data'!E:E, MATCH(E41, 'User data'!B:B, 0))} -> 닥터블릿헬스케어 주식회사 | D41: {=INDEX('User data'!F:F, MATCH(C41, 'User data'!E:E, 0))} -> 382-88-01869 | E41: 관리자 | J41: medium | K41: INBOUND | L41: FALSE | M41: https://www.gowid.com | N41: 67bc054f2965018319ee | T41: native | W41: initial | Y41: waiting | AA41: FALSE | AB41: FALSE | AC41: FALSE | AD41: FALSE | AE41: TRUE | AJ41: 46072.478 | AK41: 46073.528 | AM41: 46072.478 | AN41: 46072.478 | CR41: https://desk.channel.io/gowid/user-chats/69967557ccb0490826ab
A42: 6996725aede844f38879 | B42: 46072.47 | C42: {=INDEX('User data'!E:E, MATCH(E42, 'User data'!B:B, 0))} -> 주식회사 카닥 | D42: {=INDEX('User data'!F:F, MATCH(C42, 'User data'!E:E, 0))} -> 144-81-21245 | E42: 김송아 | J42: medium | K42: INBOUND | L42: FALSE | M42: https://www.gowid.com | N42: 6847c819273b8e1e2e08 | T42: native | W42: initial | Y42: waiting | AA42: FALSE | AB42: FALSE | AC42: FALSE | AD42: FALSE | AE42: TRUE | AJ42: 46072.469 | AK42: 46073.473 | AM42: 46072.47 | AN42: 46072.47 | CR42: https://desk.channel.io/gowid/user-chats/6996725aede844f38879
A43: 69966ed04b12a996b578 | B43: 46072.459 | C43: {=INDEX('User data'!E:E, MATCH(E43, 'User data'!B:B, 0))} -> 팀키토 주식회사 | D43: {=INDEX('User data'!F:F, MATCH(C43, 'User data'!E:E, 0))} -> 513-81-92058 | E43: 박혜수 | J43: medium | K43: INBOUND | L43: FALSE | M43: https://www.gowid.com | N43: 695c7fb517780ca87db9 | T43: native | W43: initial | Y43: waiting | AA43: FALSE | AB43: FALSE | AC43: FALSE | AD43: FALSE | AE43: TRUE | AJ43: 46072.459 | AK43: 46073.46 | AM43: 46072.459 | AN43: 46072.459 | CR43: https://desk.channel.io/gowid/user-chats/69966ed04b12a996b578
A44: 69966d7cde84a3ed71c9 | B44: 46072.455 | C44: {=INDEX('User data'!E:E, MATCH(E44, 'User data'!B:B, 0))} -> 주식회사 라로제코리아 | D44: {=INDEX('User data'!F:F, MATCH(C44, 'User data'!E:E, 0))} -> 433-87-03789 | E44: 라로제 어드민 | J44: medium | K44: INBOUND | L44: FALSE | M44: https://www.gowid.com | N44: 679b26c501256631a6b2 | T44: native | W44: initial | Y44: waiting | AA44: FALSE | AB44: FALSE | AC44: FALSE | AD44: FALSE | AE44: TRUE | AJ44: 46072.455 | AK44: 46073.455 | AM44: 46072.455 | AN44: 46072.455 | CR44: https://desk.channel.io/gowid/user-chats/69966d7cde84a3ed71c9
A45: 69966b03377bbcd30756 | B45: 46072.448 | C45: {=INDEX('User data'!E:E, MATCH(E45, 'User data'!B:B, 0))} -> 뉴타입인더스트리즈 주식회사 | D45: {=INDEX('User data'!F:F, MATCH(C45, 'User data'!E:E, 0))} -> 589-86-03426 | E45: 조성원 | J45: medium | K45: INBOUND | L45: FALSE | M45: https://www.gowid.com | N45: 69892b9420897bfe4de5 | T45: native | W45: initial | Y45: waiting | AA45: FALSE | AB45: FALSE | AC45: FALSE | AD45: FALSE | AE45: TRUE | AJ45: 46072.448 | AK45: 46073.448 | AM45: 46072.448 | AN45: 46072.448 | CR45: https://desk.channel.io/gowid/user-chats/69966b03377bbcd30756
A46: 69966ad0db252b7e9f9c | B46: 46072.447 | C46: {=INDEX('User data'!E:E, MATCH(E46, 'User data'!B:B, 0))} -> 주식회사 힐링페이퍼 | D46: {=INDEX('User data'!F:F, MATCH(C46, 'User data'!E:E, 0))} -> 117-81-81256 | E46: Oudi 김현주 | H46: [상담요약] - 고객사: 멤버관리 - 문의요약: 퇴직자와 신규등록멤버 이메일 주소 겹침 문제 - 문의유형: 이메일 중복 등록 문제 - impact: L2 - 처리내용: 퇴직자의 이메일 주소 변경 진행 - 결과: 신규 멤버 등록 가능 확인 - 후속조치: 추가 문의 시 지원 가능 | I46: 멤버관리(정보변경) | J46: medium | K46: INBOUND | L46: FALSE | M46: https://www.gowid.com | N46: 68fed84e4e23b37f7bcb | O46: 574085 | P46: 574085 | Q46: 574085 | R46: 574085, 607950 | S46: 13285 | T46: native | W46: closed | Y46: none | AA46: TRUE | AB46: FALSE | AC46: FALSE | AD46: TRUE | AE46: TRUE | AF46: 5 | AG46: 5 | AJ46: 46072.447 | AK46: 46072.548 | AL46: 46072.449 | AM46: 46072.447 | AN46: 46072.447 | AO46: 46072.448 | AP46: 46072.449 | AQ46: 46072.448 | AS46: 46072.448 | AT46: 46072.448 | AU46: 46072.448 | AX46: 46072.448 | AY46: 46072.448 | AZ46: 46072.451 | BA46: 46072.506 | BC46: 46072.506 | BD46: 46072.506 | BE46: 4480 | BF46: 4480 | BG46: 896 | BH46: 896 | BK46: 1 | BL46: 1 | BM46: 44 | BN46: 44 | BO46: 341 | BP46: 341 | BQ46: 341 | BR46: 341 | BS46: 297 | BT46: 297 | BU46: 297 | BV46: 297 | BW46: 298 | BX46: 298 | BY46: 5101 | BZ46: 5101 | CA46: 5101 | CB46: 5101 | CC46: 5101 | CD46: 5101 | CE46: 5057 | CF46: 5057 | CG46: 5057 | CH46: 5057 | CI46: 5058 | CJ46: 5058 | CK46: 5057 | CL46: 5057 | CM46: 5057 | CN46: 5057 | CO46: 3 | CP46: 42 | CR46: https://desk.channel.io/gowid/user-chats/69966ad0db252b7e9f9c
A47: 699669909e77937c8ba7 | B47: 46072.443 | C47: {=INDEX('User data'!E:E, MATCH(E47, 'User data'!B:B, 0))} | D47: {=INDEX('User data'!F:F, MATCH(C47, 'User data'!E:E, 0))} -> #N/A | E47: 구름 376 | J47: medium | K47: INBOUND | L47: FALSE | M47: https://gowid.channel.io | N47: 6996698f265d153e4901 | T47: native | W47: initial | Y47: waiting | AA47: FALSE | AB47: FALSE | AC47: FALSE | AD47: FALSE | AE47: TRUE | AJ47: 46072.443 | AK47: 46073.445 | AM47: 46072.443 | AN47: 46072.443 | CR47: https://desk.channel.io/gowid/user-chats/699669909e77937c8ba7
A48: 69966475af0d81faea0b | B48: 46072.428 | C48: {=INDEX('User data'!E:E, MATCH(E48, 'User data'!B:B, 0))} -> 주식회사 스위트스팟 | D48: {=INDEX('User data'!F:F, MATCH(C48, 'User data'!E:E, 0))} -> 846-86-00225 | E48: 도우법 | H48: [상담요약] - 고객사: 해당 고객사 - 문의요약: 계정 생성 시 오류 발생 - 문의유형: 기술 지원 - impact: L2 - 처리내용: 오류 스크린샷 요청, 구글 확인, 시크릿 모드 안내 - 결과: 고객에게 시크릿 모드 이용 권장, 라이선스 확인 - 후속조치: 시크릿 모드 진행 후 결과 보고 요청 | I48: 구독/GWS | J48: medium | K48: INBOUND | L48: FALSE | M48: https://www.gowid.com | N48: 69966098193ab38358d7 | O48: 594863 | P48: 574085 | Q48: 594863 | R48: 533671, 574085, 594863, 607950 | S48: 13288 | T48: native | W48: closed | Y48: none | AA48: TRUE | AB48: FALSE | AC48: TRUE | AD48: TRUE | AE48: TRUE | AF48: 5 | AG48: 3 | AI48: 1 | AJ48: 46072.428 | AK48: 46073.583 | AL48: 46072.432 | AM48: 46072.428 | AN48: 46072.428 | AO48: 46072.431 | AP48: 46072.432 | AQ48: 46072.431 | AS48: 46072.431 | AT48: 46072.431 | AU48: 46072.611 | AX48: 46072.431 | AY48: 46072.431 | AZ48: 46072.434 | BA48: 46073.485 | BB48: 46072.567 | BC48: 46073.583 | BD48: 46073.583 | BE48: 15218 | BF48: 5245 | BG48: 3043 | BH48: 1748 | BI48: 3786 | BJ48: 3786 | BK48: 1 | BL48: 1 | BM48: 257 | BN48: 257 | BO48: 514 | BP48: 514 | BQ48: 514 | BR48: 514 | BS48: 256 | BT48: 256 | BU48: 256 | BV48: 256 | BW48: 257 | BX48: 257 | BY48: 99762 | BZ48: 31362 | CA48: 99762 | CB48: 31362 | CC48: 99762 | CD48: 31362 | CE48: 99504 | CF48: 31104 | CG48: 99504 | CH48: 31104 | CI48: 99505 | CJ48: 31105 | CK48: 95717 | CL48: 27317 | CM48: 95717 | CN48: 27317 | CO48: 3 | CP48: 229 | CR48: https://desk.channel.io/gowid/user-chats/69966475af0d81faea0b
A49: 699660087ecb2d6affe6 | B49: 46072.415 | C49: {=INDEX('User data'!E:E, MATCH(E49, 'User data'!B:B, 0))} -> 주식회사 이오스튜디오 | D49: {=INDEX('User data'!F:F, MATCH(C49, 'User data'!E:E, 0))} -> 501-87-01653 | E49: 안서현 | J49: medium | K49: INBOUND | L49: FALSE | M49: https://www.gowid.com | N49: 66f53171f11755c05d8c | T49: native | W49: initial | Y49: waiting | AA49: FALSE | AB49: FALSE | AC49: FALSE | AD49: FALSE | AE49: TRUE | AJ49: 46072.415 | AK49: 46073.557 | AM49: 46072.415 | AN49: 46072.415 | CQ49: 1.8 | CR49: https://desk.channel.io/gowid/user-chats/699660087ecb2d6affe6
A50: 69965cb527628d271556 | B50: 46072.406 | C50: {=INDEX('User data'!E:E, MATCH(E50, 'User data'!B:B, 0))} | D50: {=INDEX('User data'!F:F, MATCH(C50, 'User data'!E:E, 0))} -> #N/A | E50: 요트 040 | J50: medium | K50: INBOUND | L50: FALSE | M50: https://gowidsub.com/ | N50: 694113472a214463489e | T50: native | W50: initial | Y50: waiting | AA50: FALSE | AB50: FALSE | AC50: FALSE | AD50: FALSE | AE50: TRUE | AJ50: 46072.405 | AK50: 46073.535 | AM50: 46072.406 | AN50: 46072.406 | CQ50: 2 | CR50: https://desk.channel.io/gowid/user-chats/69965cb527628d271556
A51: 699656fc95e5363522d9 | B51: 46072.388 | C51: {=INDEX('User data'!E:E, MATCH(E51, 'User data'!B:B, 0))} -> 주식회사 마진맥스 | D51: {=INDEX('User data'!F:F, MATCH(C51, 'User data'!E:E, 0))} -> 826-86-02651 | E51: 빈태찬 | H51: [상담요약] - 고객사: 고위드 - 문의요약: 카드 한도 상향 승인 소요 시간 문의 - 문의유형: 카드 한도 및 정산 방식 - impact: L1 - 처리내용: 한도 신청 완료 확인 및 카드사 심사 상황 안내 - 결과: 영업일 기준 1~2일 소요 예상 - 후속조치: 추가 자료 제출 시 지연 가능성 안내 | I51: 카드/한도상하향 | J51: medium | K51: INBOUND | L51: FALSE | M51: https://www.gowid.com | N51: 65f9019ee74976e27fa4 | O51: 574085 | P51: 574085 | Q51: 574085 | R51: 574085, 607950 | S51: 13285 | T51: native | W51: closed | Y51: none | AA51: TRUE | AB51: FALSE | AC51: FALSE | AD51: TRUE | AE51: TRUE | AF51: 4 | AG51: 2 | AJ51: 46072.388 | AK51: 46072.477 | AL51: 46072.389 | AM51: 46072.388 | AN51: 46072.388 | AO51: 46072.389 | AP51: 46072.389 | AQ51: 46072.389 | AS51: 46072.389 | AT51: 46072.389 | AU51: 46072.389 | AX51: 46072.389 | AY51: 46072.389 | AZ51: 46072.404 | BA51: 46072.435 | BC51: 46072.435 | BD51: 46072.435 | BE51: 3005 | BF51: 90 | BG51: 751 | BH51: 45 | BK51: 0 | BL51: 0 | BM51: 78 | BN51: 0 | BO51: 1314 | BP51: 0 | BQ51: 1314 | BR51: 0 | BS51: 1236 | BT51: 0 | BU51: 1236 | BV51: 0 | BW51: 1237 | BX51: 0 | BY51: 4071 | BZ51: 1623 | CA51: 4071 | CB51: 1623 | CC51: 4071 | CD51: 1623 | CE51: 3993 | CF51: 1623 | CG51: 3993 | CH51: 1623 | CI51: 3994 | CJ51: 1623 | CK51: 3993 | CL51: 1623 | CM51: 3993 | CN51: 1623 | CO51: 2 | CP51: 77 | CR51: https://desk.channel.io/gowid/user-chats/699656fc95e5363522d9 | CS51: 5
A52: 6996516cc92726048c8e | B52: 46072.372 | C52: {=INDEX('User data'!E:E, MATCH(E52, 'User data'!B:B, 0))} -> 캔디드 유한회사 | D52: {=INDEX('User data'!F:F, MATCH(C52, 'User data'!E:E, 0))} -> 717-87-02844 | E52: 조성률 | J52: medium | K52: INBOUND | L52: FALSE | M52: https://www.gowid.com | N52: 697718155ce787a56670 | T52: native | W52: initial | Y52: waiting | AA52: FALSE | AB52: FALSE | AC52: FALSE | AD52: FALSE | AE52: TRUE | AJ52: 46072.372 | AK52: 46072.689 | AM52: 46072.372 | AN52: 46072.372 | CR52: https://desk.channel.io/gowid/user-chats/6996516cc92726048c8e
A53: 6996514f0ecc58d9ec12 | B53: 46072.372 | C53: {=INDEX('User data'!E:E, MATCH(E53, 'User data'!B:B, 0))} -> 주식회사 마이프랜차이즈 | D53: {=INDEX('User data'!F:F, MATCH(C53, 'User data'!E:E, 0))} -> 584-87-01610 | E53: young | H53: [상담요약] - 고객사: 협력사 - 문의요약: 기기 판매 신청 페이지 안내 - 문의유형: 정보 제공 - impact: L1 - 처리내용: 기기 판매 신청 페이지 안내 - 결과: 안내 완료 - 후속조치: 없음 | I53: 구독/GWS | J53: medium | K53: INBOUND | L53: FALSE | M53: https://www.gowid.com | N53: 67809d4aa7314954c090 | O53: 594863 | P53: 574085 | Q53: 594863 | R53: 533671, 574085, 594863 | S53: 13288 | T53: native | W53: closed | Y53: waiting | AA53: TRUE | AB53: FALSE | AC53: TRUE | AD53: TRUE | AE53: TRUE | AF53: 1 | AI53: 1 | AJ53: 46072.371 | AK53: 46072.726 | AL53: 46072.374 | AM53: 46072.372 | AN53: 46072.372 | AO53: 46072.374 | AP53: 46072.374 | AQ53: 46072.374 | AS53: 46072.374 | AT53: 46072.374 | AU53: 46072.607 | AX53: 46072.374 | AY53: 46072.374 | AZ53: 46072.549 | BA53: 46072.549 | BB53: 46072.567 | BC53: 46072.684 | BD53: 46072.684 | BE53: 15166 | BG53: 15166 | BI53: 3501 | BJ53: 3501 | BK53: 0 | BL53: 0 | BM53: 188 | BN53: 0 | BO53: 15353 | BP53: 9000 | BQ53: 15353 | BR53: 9000 | BS53: 15165 | BT53: 9000 | BU53: 15165 | BV53: 9000 | BW53: 15166 | BX53: 9000 | BY53: 26992 | BZ53: 19507 | CA53: 26992 | CB53: 19507 | CC53: 26992 | CD53: 19507 | CE53: 26804 | CF53: 19507 | CG53: 26804 | CH53: 19507 | CI53: 26805 | CJ53: 19507 | CK53: 23302 | CL53: 16005 | CM53: 23302 | CN53: 16005 | CO53: 2 | CP53: 187 | CR53: https://desk.channel.io/gowid/user-chats/6996514f0ecc58d9ec12
A54: 6996485a380dd38bc9f0 | B54: 46072.345 | C54: {=INDEX('User data'!E:E, MATCH(E54, 'User data'!B:B, 0))} -> 주식회사 프라이스잇(priceit. Co.,Ltd.) | D54: {=INDEX('User data'!F:F, MATCH(C54, 'User data'!E:E, 0))} -> 431-86-03466 | E54: 송현규 | J54: medium | K54: INBOUND | L54: FALSE | M54: https://www.gowid.com | N54: 698adac9d13b25e3a10b | T54: native | W54: initial | Y54: waiting | AA54: FALSE | AB54: FALSE | AC54: FALSE | AD54: FALSE | AE54: TRUE | AJ54: 46072.345 | AK54: 46073.449 | AM54: 46072.345 | AN54: 46072.345 | CR54: https://desk.channel.io/gowid/user-chats/6996485a380dd38bc9f0
A55: 6996016789d5f7b91f1d | B55: 46072.135 | C55: {=INDEX('User data'!E:E, MATCH(E55, 'User data'!B:B, 0))} | D55: {=INDEX('User data'!F:F, MATCH(C55, 'User data'!E:E, 0))} -> #N/A | E55: Football 039 | J55: medium | K55: INBOUND | L55: FALSE | M55: https://www.gowid.com | N55: 69674a7f26cfe3d4eb0e | T55: native | W55: initial | Y55: waiting | AA55: FALSE | AB55: FALSE | AC55: FALSE | AD55: FALSE | AE55: TRUE | AJ55: 46072.135 | AK55: 46073.441 | AM55: 46072.135 | AN55: 46072.135 | CQ55: 1.6 | CR55: https://desk.channel.io/gowid/user-chats/6996016789d5f7b91f1d
A56: 6995e33fdcead327a338 | B56: 46072.046 | C56: {=INDEX('User data'!E:E, MATCH(E56, 'User data'!B:B, 0))} | D56: {=INDEX('User data'!F:F, MATCH(C56, 'User data'!E:E, 0))} -> #N/A | E56: 지니 217 | J56: medium | K56: INBOUND | L56: FALSE | M56: https://www.gowid.com | N56: 6995e3139d837d45c49f | T56: native | W56: initial | Y56: waiting | AA56: FALSE | AB56: FALSE | AC56: FALSE | AD56: FALSE | AE56: TRUE | AJ56: 46072.045 | AK56: 46073.427 | AM56: 46072.046 | AN56: 46072.046 | CQ56: 2 | CR56: https://desk.channel.io/gowid/user-chats/6995e33fdcead327a338
A57: 6995e1d1bb4103aa1859 | B57: 46072.041 | C57: {=INDEX('User data'!E:E, MATCH(E57, 'User data'!B:B, 0))} | D57: {=INDEX('User data'!F:F, MATCH(C57, 'User data'!E:E, 0))} -> #N/A | E57: 리본 189 | J57: medium | K57: INBOUND | L57: FALSE | M57: https://www.gowid.com | N57: 6995e08982e1b89fde86 | T57: native | W57: initial | Y57: waiting | AA57: FALSE | AB57: FALSE | AC57: FALSE | AD57: FALSE | AE57: TRUE | AJ57: 46072.041 | AK57: 46073.428 | AM57: 46072.041 | AN57: 46072.041 | CQ57: 3.6 | CR57: https://desk.channel.io/gowid/user-chats/6995e1d1bb4103aa1859
A58: 6995c7e9c170f3de46d7 | B58: 46071.964 | C58: {=INDEX('User data'!E:E, MATCH(E58, 'User data'!B:B, 0))} -> (주)리아온 | D58: {=INDEX('User data'!F:F, MATCH(C58, 'User data'!E:E, 0))} -> 425-88-02525 | E58: 이아현 | J58: medium | K58: INBOUND | L58: FALSE | M58: https://www.gowid.com | N58: 6995c7d5b5ed25c85e8b | T58: native | W58: initial | Y58: waiting | AA58: FALSE | AB58: FALSE | AC58: FALSE | AD58: FALSE | AE58: TRUE | AJ58: 46071.964 | AK58: 46073.384 | AM58: 46071.964 | AN58: 46071.964 | CQ58: 3.4 | CR58: https://desk.channel.io/gowid/user-chats/6995c7e9c170f3de46d7
A59: 6995888bb1831788c49f | B59: 46071.777 | C59: {=INDEX('User data'!E:E, MATCH(E59, 'User data'!B:B, 0))} | D59: {=INDEX('User data'!F:F, MATCH(C59, 'User data'!E:E, 0))} -> #N/A | E59: 쿠키 302 | J59: medium | K59: INBOUND | L59: FALSE | M59: https://www.gowid.com | N59: 6995856f0600cf579084 | T59: native | W59: initial | Y59: waiting | AA59: FALSE | AB59: FALSE | AC59: FALSE | AD59: FALSE | AE59: TRUE | AJ59: 46071.777 | AK59: 46072.854 | AM59: 46071.777 | AN59: 46071.777 | CQ59: 4.8 | CR59: https://desk.channel.io/gowid/user-chats/6995888bb1831788c49f
A60: 6995729789a153a92af6 | B60: 46071.712 | C60: {=INDEX('User data'!E:E, MATCH(E60, 'User data'!B:B, 0))} -> 주식회사 퍼슬리 | D60: {=INDEX('User data'!F:F, MATCH(C60, 'User data'!E:E, 0))} -> 241-81-03586 | E60: 오상준 | J60: medium | K60: INBOUND | L60: FALSE | M60: https://www.gowid.com | N60: 68578b40595408f06d9b | T60: native | W60: initial | Y60: waiting | AA60: FALSE | AB60: FALSE | AC60: FALSE | AD60: FALSE | AE60: TRUE | AJ60: 46071.712 | AK60: 46072.712 | AM60: 46071.712 | AN60: 46071.712 | CQ60: 5 | CR60: https://desk.channel.io/gowid/user-chats/6995729789a153a92af6
A61: 699520c5dfe6d5ce53af | B61: 46071.469 | C61: {=INDEX('User data'!E:E, MATCH(E61, 'User data'!B:B, 0))} -> (주)매시브다이나믹 | D61: {=INDEX('User data'!F:F, MATCH(C61, 'User data'!E:E, 0))} -> 130-86-94026 | E61: 최윤제 | J61: medium | K61: INBOUND | L61: FALSE | M61: https://www.gowid.com | N61: 699520ad2e55224f9f11 | T61: native | W61: initial | Y61: waiting | AA61: FALSE | AB61: FALSE | AC61: FALSE | AD61: FALSE | AE61: TRUE | AJ61: 46071.469 | AK61: 46072.469 | AM61: 46071.469 | AN61: 46071.469 | CQ61: 3.4 | CR61: https://desk.channel.io/gowid/user-chats/699520c5dfe6d5ce53af
A62: 69945c7069e2d06bf27e | B62: 46070.888 | C62: {=INDEX('User data'!E:E, MATCH(E62, 'User data'!B:B, 0))} | D62: {=INDEX('User data'!F:F, MATCH(C62, 'User data'!E:E, 0))} -> #N/A | E62: 다트 540 | J62: medium | K62: INBOUND | L62: FALSE | M62: https://www.gowid.com | N62: 69945ac2784498e93d8f | T62: native | W62: initial | Y62: waiting | AA62: FALSE | AB62: FALSE | AC62: FALSE | AD62: FALSE | AE62: TRUE | AJ62: 46070.887 | AK62: 46071.888 | AM62: 46070.888 | AN62: 46070.888 | CQ62: 5 | CR62: https://desk.channel.io/gowid/user-chats/69945c7069e2d06bf27e
A63: 6994491f3fb324d173b0 | B63: 46070.83 | C63: {=INDEX('User data'!E:E, MATCH(E63, 'User data'!B:B, 0))} | D63: {=INDEX('User data'!F:F, MATCH(C63, 'User data'!E:E, 0))} -> #N/A | E63: 구름 851 | J63: medium | K63: INBOUND | L63: FALSE | M63: https://www.gowid.com | N63: 699448427327e42794b5 | T63: native | W63: initial | Y63: waiting | AA63: FALSE | AB63: FALSE | AC63: FALSE | AD63: FALSE | AE63: TRUE | AJ63: 46070.83 | AK63: 46071.83 | AM63: 46070.83 | AN63: 46070.83 | CQ63: 3.6 | CR63: https://desk.channel.io/gowid/user-chats/6994491f3fb324d173b0
A64: 699410fbd9cfa3c0f5e8 | B64: 46070.664 | C64: {=INDEX('User data'!E:E, MATCH(E64, 'User data'!B:B, 0))} | D64: {=INDEX('User data'!F:F, MATCH(C64, 'User data'!E:E, 0))} -> #N/A | E64: 무지개 726 | J64: medium | K64: INBOUND | L64: FALSE | M64: https://www.gowid.com | N64: 699410e025f48d8b37ed | T64: native | W64: initial | Y64: waiting | AA64: FALSE | AB64: FALSE | AC64: FALSE | AD64: FALSE | AE64: TRUE | AJ64: 46070.664 | AK64: 46071.664 | AM64: 46070.664 | AN64: 46070.664 | CQ64: 4.4 | CR64: https://desk.channel.io/gowid/user-chats/699410fbd9cfa3c0f5e8
A65: 6993edba454444025c3f | B65: 46070.56 | C65: {=INDEX('User data'!E:E, MATCH(E65, 'User data'!B:B, 0))} | D65: {=INDEX('User data'!F:F, MATCH(C65, 'User data'!E:E, 0))} -> #N/A | E65: 케이크 543 | J65: medium | K65: INBOUND | L65: FALSE | M65: https://www.gowid.com | N65: 6993ed968779dded9c3a | T65: native | W65: initial | Y65: waiting | AA65: FALSE | AB65: FALSE | AC65: FALSE | AD65: FALSE | AE65: TRUE | AJ65: 46070.559 | AK65: 46071.56 | AM65: 46070.56 | AN65: 46070.56 | CQ65: 3.4 | CR65: https://desk.channel.io/gowid/user-chats/6993edba454444025c3f
A66: 6993d3183f9e8345c738 | B66: 46070.481 | C66: {=INDEX('User data'!E:E, MATCH(E66, 'User data'!B:B, 0))} | D66: {=INDEX('User data'!F:F, MATCH(C66, 'User data'!E:E, 0))} -> #N/A | E66: 허니 196 | J66: medium | K66: INBOUND | L66: FALSE | M66: https://docs.channel.io/gowid-guide/ko/articles/고위드-지출관리-서비스-활용하기-2edfad43 | N66: 69881f07e981a440cc4e | T66: native | W66: initial | Y66: waiting | AA66: FALSE | AB66: FALSE | AC66: FALSE | AD66: FALSE | AE66: TRUE | AJ66: 46070.48 | AK66: 46071.49 | AM66: 46070.481 | AN66: 46070.481 | CQ66: 4 | CR66: https://desk.channel.io/gowid/user-chats/6993d3183f9e8345c738
... A92: 698eab6711a2100bb7c9 | B92: 46066.57 | C92: {=INDEX('User data'!E:E, MATCH(E92, 'User data'!B:B, 0))} -> 블링커스 주식회사 | D92: {=INDEX('User data'!F:F, MATCH(C92, 'User data'!E:E, 0))} -> 247-81-02402 | E92: 박상욱 | J92: medium | K92: INBOUND | L92: FALSE | M92: https://www.gowid.com | N92: 66cbd213ba9575c1b13a | T92: native | W92: initial | Y92: waiting | AA92: FALSE | AB92: FALSE | AC92: FALSE | AD92: FALSE | AE92: TRUE | AJ92: 46066.57 | AK92: 46067.573 | AM92: 46066.57 | AN92: 46066.57 | CQ92: 3.2 | CR92: https://desk.channel.io/gowid/user-chats/698eab6711a2100bb7c9
A93: 698ea5e149c230cf78b3 | B93: 46066.554 | C93: {=INDEX('User data'!E:E, MATCH(E93, 'User data'!B:B, 0))} -> 주식회사 그래비티벤처스 | D93: {=INDEX('User data'!F:F, MATCH(C93, 'User data'!E:E, 0))} -> 170-88-02251 | E93: Jessy Kim | H93: [상담요약] - 고객사: 비씨카드 - 문의요약: 롯데카드 및 신한카드 추가 신청 가능 여부 - 문의유형: 카드 발급 문의 - impact: L2 - 처리내용: 롯데카드와 신한카드 추가 신청 가능 안내 - 결과: 롯데카드와 신한카드 신청 절차 설명 - 후속조치: 추가 문의 시 도움 제공 | J93: medium | K93: INBOUND | L93: FALSE | M93: https://www.gowid.com | N93: 68635e72b3630294ce73 | O93: 574085 | P93: 574085 | Q93: 574085 | R93: 574085, 607950 | S93: 13285 | T93: native | W93: closed | Y93: waiting | AA93: TRUE | AB93: FALSE | AC93: FALSE | AD93: TRUE | AE93: TRUE | AF93: 1 | AJ93: 46066.554 | AK93: 46073.569 | AL93: 46066.555 | AM93: 46066.554 | AN93: 46066.554 | AO93: 46066.555 | AP93: 46066.555 | AQ93: 46066.555 | AS93: 46066.555 | AT93: 46066.555 | AU93: 46073.542 | AX93: 46066.555 | AY93: 46066.555 | AZ93: 46066.695 | BA93: 46066.695 | BB93: 46072.567 | BC93: 46073.569 | BD93: 46073.569 | BE93: 12097 | BG93: 12097 | BI93: 329503 | BJ93: 30686 | BK93: 1 | BL93: 0 | BM93: 120 | BN93: 0 | BO93: 12216 | BP93: 11490 | BQ93: 12216 | BR93: 11490 | BS93: 12095 | BT93: 11490 | BU93: 12095 | BV93: 11490 | BW93: 12097 | BX93: 11490 | BY93: 606074 | BZ93: 108548 | CA93: 606074 | CB93: 108548 | CC93: 606074 | CD93: 108548 | CE93: 605954 | CF93: 108548 | CG93: 605953 | CH93: 108548 | CI93: 605955 | CJ93: 108548 | CK93: 276450 | CL93: 77861 | CM93: 276450 | CN93: 77861 | CO93: 2 | CP93: 119 | CR93: https://desk.channel.io/gowid/user-chats/698ea5e149c230cf78b3
A94: 698ea42af0ecd7780afa | B94: 46066.549 | C94: {=INDEX('User data'!E:E, MATCH(E94, 'User data'!B:B, 0))} | D94: {=INDEX('User data'!F:F, MATCH(C94, 'User data'!E:E, 0))} -> #N/A | E94: 김윤미 | H94: 문의 내용이 15글자 미만입니다. 요약할 내용이 없습니다. | I94: 카드/한도상하향 | J94: medium | K94: INBOUND | L94: FALSE | M94: https://gowid.channel.io | N94: 6969aca0931c24a457c0 | O94: 574085 | P94: 574085 | Q94: 574085 | R94: 574085, 607950 | S94: 13285 | T94: native | W94: closed | Y94: none | AA94: TRUE | AB94: FALSE | AC94: FALSE | AD94: TRUE | AE94: TRUE | AF94: 3 | AG94: 1 | AJ94: 46066.549 | AK94: 46073.574 | AL94: 46066.555 | AM94: 46066.549 | AN94: 46066.549 | AO94: 46066.554 | AP94: 46066.555 | AQ94: 46066.555 | AS94: 46066.555 | AT94: 46066.555 | AU94: 46073.542 | AX94: 46066.555 | AY94: 46066.555 | AZ94: 46066.573 | BA94: 46073.571 | BB94: 46072.567 | BC94: 46073.574 | BD94: 46073.574 | BE94: 6476 | BF94: 2401 | BG94: 2158 | BH94: 2401 | BI94: 323848 | BJ94: 30219 | BK94: 0 | BL94: 0 | BM94: 491 | BN94: 0 | BO94: 2045 | BP94: 881 | BQ94: 2045 | BR94: 881 | BS94: 1553 | BT94: 881 | BU94: 1553 | BV94: 881 | BW94: 1554 | BX94: 881 | BY94: 606990 | BZ94: 109026 | CA94: 606990 | CB94: 109026 | CC94: 606990 | CD94: 109026 | CE94: 606498 | CF94: 109026 | CG94: 606498 | CH94: 109026 | CI94: 606499 | CJ94: 109026 | CK94: 282649 | CL94: 78807 | CM94: 282649 | CN94: 78807 | CO94: 2 | CP94: 471 | CR94: https://desk.channel.io/gowid/user-chats/698ea42af0ecd7780afa
A95: 698ea42b0f3f3a1f6f63 | B95: 46066.549 | C95: {=INDEX('User data'!E:E, MATCH(E95, 'User data'!B:B, 0))} -> 주식회사 카닥 | D95: {=INDEX('User data'!F:F, MATCH(C95, 'User data'!E:E, 0))} -> 144-81-21245 | E95: 김송아 | I95: 카드/한도상하향 | J95: medium | K95: INBOUND | L95: FALSE | M95: https://docs.channel.io/gowid-guide/ko/articles/한도-유지상향을-위한-공동인증서-관리-835de607 | N95: 6847c819273b8e1e2e08 | O95: 574085 | P95: 574085 | Q95: 574085 | R95: 574085, 607950 | S95: 13285 | T95: native | W95: closed | Y95: none | AA95: TRUE | AB95: FALSE | AC95: FALSE | AD95: TRUE | AE95: TRUE | AF95: 1 | AJ95: 46066.549 | AK95: 46066.745 | AL95: 46066.553 | AM95: 46066.549 | AN95: 46066.549 | AO95: 46066.553 | AP95: 46066.553 | AQ95: 46066.553 | AS95: 46066.553 | AT95: 46066.553 | AU95: 46066.553 | AX95: 46066.553 | AY95: 46066.553 | AZ95: 46066.573 | BA95: 46066.573 | BC95: 46066.703 | BD95: 46066.703 | BE95: 1690 | BG95: 1690 | BK95: 0 | BL95: 0 | BM95: 361 | BN95: 0 | BO95: 2051 | BP95: 878 | BQ95: 2051 | BR95: 878 | BS95: 1689 | BT95: 878 | BU95: 1689 | BV95: 878 | BW95: 1690 | BX95: 878 | BY95: 13297 | BZ95: 12124 | CA95: 13297 | CB95: 12124 | CC95: 13297 | CD95: 12124 | CE95: 12935 | CF95: 12124 | CG95: 12935 | CH95: 12124 | CI95: 12936 | CJ95: 12124 | CK95: 12935 | CL95: 12124 | CM95: 12935 | CN95: 12124 | CO95: 2 | CP95: 341 | CR95: https://desk.channel.io/gowid/user-chats/698ea42b0f3f3a1f6f63
A96: 698e9cf308aafb0fd1d6 | B96: 46066.528 | C96: {=INDEX('User data'!E:E, MATCH(E96, 'User data'!B:B, 0))} -> 주식회사 유어유니콘 | D96: {=INDEX('User data'!F:F, MATCH(C96, 'User data'!E:E, 0))} -> 889-88-03238 | E96: 김용우 | J96: medium | K96: INBOUND | L96: FALSE | M96: https://www.gowid.com | N96: 690f1f8a59e49ac09a14 | T96: native | W96: initial | Y96: waiting | AA96: FALSE | AB96: FALSE | AC96: FALSE | AD96: FALSE | AE96: TRUE | AJ96: 46066.527 | AK96: 46067.589 | AM96: 46066.528 | AN96: 46066.528 | CQ96: 3.4 | CR96: https://desk.channel.io/gowid/user-chats/698e9cf308aafb0fd1d6
A97: 698e9a97ba6e6070345b | B97: 46066.521 | C97: {=INDEX('User data'!E:E, MATCH(E97, 'User data'!B:B, 0))} -> 주식회사 이십사점오(24.5 Corp.) | D97: {=INDEX('User data'!F:F, MATCH(C97, 'User data'!E:E, 0))} -> 889-87-01572 | E97: 김신우 | J97: medium | K97: INBOUND | L97: FALSE | M97: https://www.gowid.com | N97: 656eb93d0f351a64eb79 | T97: native | W97: initial | Y97: waiting | AA97: FALSE | AB97: FALSE | AC97: FALSE | AD97: FALSE | AE97: TRUE | AJ97: 46066.52 | AK97: 46067.521 | AM97: 46066.521 | AN97: 46066.521 | CQ97: 5 | CR97: https://desk.channel.io/gowid/user-chats/698e9a97ba6e6070345b
A98: 698e9a665d87683de89f | B98: 46066.52 | C98: {=INDEX('User data'!E:E, MATCH(E98, 'User data'!B:B, 0))} -> 주식회사 이십사점오(24.5 Corp.) | D98: {=INDEX('User data'!F:F, MATCH(C98, 'User data'!E:E, 0))} -> 889-87-01572 | E98: 김신우 | J98: medium | K98: INBOUND | L98: FALSE | M98: https://www.gowid.com | N98: 656eb93d0f351a64eb79 | T98: native | W98: initial | Y98: waiting | AA98: FALSE | AB98: FALSE | AC98: FALSE | AD98: FALSE | AE98: TRUE | AJ98: 46066.52 | AK98: 46067.52 | AM98: 46066.52 | AN98: 46066.52 | CQ98: 3.2 | CR98: https://desk.channel.io/gowid/user-chats/698e9a665d87683de89f
A99: 698e99b836ddecf547a7 | B99: 46066.518 | C99: {=INDEX('User data'!E:E, MATCH(E99, 'User data'!B:B, 0))} | D99: {=INDEX('User data'!F:F, MATCH(C99, 'User data'!E:E, 0))} -> #N/A | E99: 선인장 102 | J99: medium | K99: INBOUND | L99: FALSE | M99: https://www.gowid.com | N99: 698e99aec971dee8ce99 | T99: native | W99: initial | Y99: waiting | AA99: FALSE | AB99: FALSE | AC99: FALSE | AD99: FALSE | AE99: TRUE | AJ99: 46066.518 | AK99: 46067.518 | AM99: 46066.518 | AN99: 46066.518 | CQ99: 1.8 | CR99: https://desk.channel.io/gowid/user-chats/698e99b836ddecf547a7
A100: 698e98b40c93c41c04e1 | B100: 46066.515 | C100: {=INDEX('User data'!E:E, MATCH(E100, 'User data'!B:B, 0))} -> 주식회사 올세일코퍼레이션 (ALLSALE Corp.) | D100: {=INDEX('User data'!F:F, MATCH(C100, 'User data'!E:E, 0))} -> 251-81-03375 | E100: 김한결(Rex) | J100: medium | K100: INBOUND | L100: FALSE | M100: https://docs.channel.io/gowid-guide/ko/categories/자주-묻는-질문-FAQ-b08261e0 | N100: 692d6e627b9d1da1d963 | T100: native | W100: initial | Y100: waiting | AA100: FALSE | AB100: FALSE | AC100: FALSE | AD100: FALSE | AE100: TRUE | AJ100: 46066.515 | AK100: 46067.515 | AM100: 46066.515 | AN100: 46066.515 | CQ100: 3.6 | CR100: https://desk.channel.io/gowid/user-chats/698e98b40c93c41c04e1
A101: 698e98247cabc24f5904 | B101: 46066.513 | C101: {=INDEX('User data'!E:E, MATCH(E101, 'User data'!B:B, 0))} -> 주식회사 올세일코퍼레이션 (ALLSALE Corp.) | D101: {=INDEX('User data'!F:F, MATCH(C101, 'User data'!E:E, 0))} -> 251-81-03375 | E101: 김한결(Rex) | J101: medium | K101: INBOUND | L101: FALSE | M101: https://www.gowid.com | N101: 692d6e627b9d1da1d963 | T101: native | W101: initial | Y101: waiting | AA101: FALSE | AB101: FALSE | AC101: FALSE | AD101: FALSE | AE101: TRUE | AJ101: 46066.513 | AK101: 46067.513 | AM101: 46066.513 | AN101: 46066.513 | CQ101: 3.8 | CR101: https://desk.channel.io/gowid/user-chats/698e98247cabc24f5904
A102: 698e9464a8364b5ff83b | B102: 46066.502 | C102: {=INDEX('User data'!E:E, MATCH(E102, 'User data'!B:B, 0))} -> 주식회사 리프라이즈 | D102: {=INDEX('User data'!F:F, MATCH(C102, 'User data'!E:E, 0))} -> 421-87-03001 | E102: 박종호 | J102: medium | K102: INBOUND | L102: FALSE | M102: https://www.gowid.com | N102: 6927b0b8dc3cfc3fb32c | T102: native | W102: initial | Y102: waiting | AA102: FALSE | AB102: FALSE | AC102: FALSE | AD102: FALSE | AE102: TRUE | AJ102: 46066.502 | AK102: 46067.502 | AM102: 46066.502 | AN102: 46066.502 | CQ102: 5 | CR102: https://desk.channel.io/gowid/user-chats/698e9464a8364b5ff83b
A103: 698e9128c702bec703ac | B103: 46066.493 | C103: {=INDEX('User data'!E:E, MATCH(E103, 'User data'!B:B, 0))} -> 주식회사 바닐라브릿지 | D103: {=INDEX('User data'!F:F, MATCH(C103, 'User data'!E:E, 0))} -> 165-86-00709 | E103: 최성만 | J103: medium | K103: INBOUND | L103: FALSE | M103: https://www.gowid.com | N103: 6971bb6bde685cd74326 | T103: native | W103: initial | Y103: waiting | AA103: FALSE | AB103: FALSE | AC103: FALSE | AD103: FALSE | AE103: TRUE | AJ103: 46066.493 | AK103: 46067.601 | AM103: 46066.493 | AN103: 46066.493 | CQ103: 5 | CR103: https://desk.channel.io/gowid/user-chats/698e9128c702bec703ac
A104: 698e8d9a1576c3b66f85 | B104: 46066.482 | C104: {=INDEX('User data'!E:E, MATCH(E104, 'User data'!B:B, 0))} -> 주식회사 라디우스랩 | D104: {=INDEX('User data'!F:F, MATCH(C104, 'User data'!E:E, 0))} -> 567-87-02875 | E104: 한종빈 | I104: 구독/GWS | J104: medium | K104: INBOUND | L104: FALSE | M104: https://www.gowid.com | N104: 6971d94bc3ded889e1b9 | O104: 594863 | P104: 607950 | Q104: 594863 | R104: 594863, 607950 | S104: 13288 | T104: native | W104: closed | Y104: none | AA104: TRUE | AB104: FALSE | AC104: FALSE | AD104: TRUE | AE104: TRUE | AF104: 1 | AG104: 1 | AJ104: 46066.482 | AK104: 46066.557 | AL104: 46066.492 | AM104: 46066.482 | AN104: 46066.482 | AO104: 46066.491 | AP104: 46066.492 | AQ104: 46066.491 | AS104: 46066.491 | AT104: 46066.491 | AU104: 46066.491 | AX104: 46066.491 | AY104: 46066.491 | AZ104: 46066.491 | BA104: 46066.501 | BC104: 46066.515 | BD104: 46066.515 | BE104: 834 | BF104: 834 | BG104: 834 | BH104: 834 | BK104: 0 | BL104: 0 | BM104: 805 | BN104: 805 | BO104: 811 | BP104: 811 | BQ104: 811 | BR104: 811 | BS104: 6 | BT104: 6 | BW104: 0 | BY104: 2876 | BZ104: 2876 | CA104: 2876 | CB104: 2876 | CC104: 2876 | CD104: 2876 | CE104: 2071 | CF104: 2071 | CG104: 2064 | CH104: 2064 | CI104: 2064 | CJ104: 2064 | CK104: 2064 | CL104: 2064 | CM104: 2064 | CN104: 2064 | CO104: 3 | CP104: 811 | CR104: https://desk.channel.io/gowid/user-chats/698e8d9a1576c3b66f85
A105: 698e89f639b32e20c888 | B105: 46066.471 | C105: {=INDEX('User data'!E:E, MATCH(E105, 'User data'!B:B, 0))} -> (주）TGWP | D105: {=INDEX('User data'!F:F, MATCH(C105, 'User data'!E:E, 0))} -> 211-88-10839 | E105: 서림세무법인 | J105: medium | K105: INBOUND | L105: FALSE | M105: https://www.gowid.com | N105: 698e79e9a6f1bb51438c | T105: native | W105: initial | Y105: waiting | AA105: FALSE | AB105: FALSE | AC105: FALSE | AD105: FALSE | AE105: TRUE | AJ105: 46066.471 | AK105: 46067.471 | AM105: 46066.471 | AN105: 46066.471 | CQ105: 5 | CR105: https://desk.channel.io/gowid/user-chats/698e89f639b32e20c888
A106: 698e88755865529660a6 | B106: 46066.467 | C106: {=INDEX('User data'!E:E, MATCH(E106, 'User data'!B:B, 0))} -> 주식회사 리펀디 | D106: {=INDEX('User data'!F:F, MATCH(C106, 'User data'!E:E, 0))} -> 294-87-03409 | E106: 김재겸 | I106: 카드/한도상하향 | J106: medium | K106: INBOUND | L106: FALSE | M106: https://www.gowid.com | N106: 67651d71c66d19c0496b | O106: 607950 | P106: 607950 | Q106: 607950 | R106: 607950 | T106: native | W106: closed | Y106: none | AA106: TRUE | AB106: FALSE | AC106: FALSE | AD106: TRUE | AE106: TRUE | AF106: 1 | AG106: 1 | AJ106: 46066.467 | AK106: 46066.615 | AL106: 46066.573 | AM106: 46066.467 | AN106: 46066.467 | AO106: 46066.496 | AT106: 46066.496 | AU106: 46066.496 | AX106: 46066.496 | AY106: 46066.496 | AZ106: 46066.496 | BA106: 46066.497 | BC106: 46066.573 | BD106: 46066.573 | BE106: 55 | BF106: 55 | BG106: 55 | BH106: 55 | BM106: 2513 | BN106: 2513 | BO106: 2515 | BP106: 2515 | BQ106: 2515 | BR106: 2515 | BS106: 2 | BT106: 2 | BW106: 0 | BY106: 9163 | BZ106: 5563 | CA106: 9163 | CB106: 5563 | CC106: 9163 | CD106: 5563 | CE106: 6650 | CF106: 3050 | CG106: 6648 | CH106: 3048 | CI106: 6648 | CJ106: 3048 | CK106: 6648 | CL106: 3048 | CM106: 6648 | CN106: 3048 | CP106: 2515 | CR106: https://desk.channel.io/gowid/user-chats/698e88755865529660a6
A107: 698e86448891294cc9c5 | B107: 46066.46 | C107: {=INDEX('User data'!E:E, MATCH(E107, 'User data'!B:B, 0))} -> 주식회사 지투지바이오 | D107: {=INDEX('User data'!F:F, MATCH(C107, 'User data'!E:E, 0))} -> 195-88-00664 | E107: 지투지바이오 | H107: [상담요약] - 고객사: 롯데카드 - 문의요약: 카드 한도 상향 신청 후 5영업일 경과 - 문의유형: 심사 진행 확인 요청 - impact: L2 - 처리내용: 심사 진행 상황 확인 - 결과: 금일 오후 중으로 연락 예정 - 후속조치: 심사 결과 안내 | I107: 카드/한도상하향 | J107: medium | K107: INBOUND | L107: FALSE | M107: https://www.gowid.com | N107: 684f6cc36ba131999906 | O107: 574085 | P107: 574085 | Q107: 574085 | R107: 574085, 607950 | S107: 13285 | T107: native | W107: closed | Y107: waiting | AA107: TRUE | AB107: FALSE | AC107: FALSE | AD107: TRUE | AE107: TRUE | AF107: 1 | AG107: 1 | AJ107: 46066.46 | AK107: 46073.569 | AL107: 46066.463 | AM107: 46066.46 | AN107: 46066.46 | AO107: 46066.462 | AP107: 46066.463 | AQ107: 46066.462 | AS107: 46066.462 | AT107: 46066.462 | AU107: 46073.542 | AX107: 46066.462 | AY107: 46066.462 | AZ107: 46066.481 | BA107: 46066.481 | BB107: 46072.567 | BC107: 46073.569 | BD107: 46073.569 | BE107: 1621 | BF107: 1621 | BG107: 1621 | BH107: 1621 | BI107: 338248 | BJ107: 41018 | BK107: 1 | BL107: 1 | BM107: 177 | BN107: 177 | BO107: 1797 | BP107: 1797 | BQ107: 1797 | BR107: 1797 | BS107: 1619 | BT107: 1619 | BU107: 1619 | BV107: 1619 | BW107: 1621 | BX107: 1621 | BY107: 614158 | BZ107: 113758 | CA107: 614158 | CB107: 113758 | CC107: 614158 | CD107: 113758 | CE107: 613980 | CF107: 113580 | CG107: 613980 | CH107: 113580 | CI107: 613982 | CJ107: 113582 | CK107: 275732 | CL107: 72562 | CM107: 275732 | CN107: 72562 | CO107: 3 | CP107: 176 | CR107: https://desk.channel.io/gowid/user-chats/698e86448891294cc9c5
A108: 698e82251914167cf121 | B108: 46066.448 | C108: {=INDEX('User data'!E:E, MATCH(E108, 'User data'!B:B, 0))} -> 주식회사 바닐라브릿지 | D108: {=INDEX('User data'!F:F, MATCH(C108, 'User data'!E:E, 0))} -> 165-86-00709 | E108: 최성만 | I108: 카드/도입신청서·회원가입 | J108: medium | K108: INBOUND | L108: FALSE | M108: https://www.gowid.com | N108: 6971bb6bde685cd74326 | O108: 574085 | P108: 574085 | Q108: 574085 | R108: 574085 | T108: native | W108: closed | Y108: none | AA108: TRUE | AB108: FALSE | AC108: FALSE | AD108: TRUE | AE108: TRUE | AF108: 3 | AG108: 3 | AJ108: 46066.448 | AK108: 46066.494 | AL108: 46066.452 | AM108: 46066.448 | AN108: 46066.448 | AO108: 46066.449 | AP108: 46066.452 | AT108: 46066.449 | AU108: 46066.449 | AX108: 46066.449 | AY108: 46066.449 | AZ108: 46066.449 | BA108: 46066.452 | BC108: 46066.452 | BD108: 46066.452 | BE108: 160 | BF108: 160 | BG108: 53 | BH108: 53 | BM108: 81 | BN108: 81 | BO108: 105 | BP108: 105 | BQ108: 105 | BR108: 105 | BS108: 23 | BT108: 23 | BU108: 32 | BV108: 32 | BW108: 32 | BX108: 32 | BY108: 357 | BZ108: 357 | CA108: 357 | CB108: 357 | CC108: 357 | CD108: 357 | CE108: 275 | CF108: 275 | CG108: 283 | CH108: 283 | CI108: 283 | CJ108: 283 | CK108: 283 | CL108: 283 | CM108: 283 | CN108: 283 | CO108: 16 | CP108: 54 | CR108: https://desk.channel.io/gowid/user-chats/698e82251914167cf121 | CS108: 5
A109: 698e8124219a0d6dc8e5 | B109: 46066.445 | C109: {=INDEX('User data'!E:E, MATCH(E109, 'User data'!B:B, 0))} -> 주식회사 지투지바이오 | D109: {=INDEX('User data'!F:F, MATCH(C109, 'User data'!E:E, 0))} -> 195-88-00664 | E109: 지투지바이오 | J109: medium | K109: INBOUND | L109: FALSE | M109: https://www.gowid.com | N109: 684f6cc36ba131999906 | T109: native | W109: initial | Y109: waiting | AA109: FALSE | AB109: FALSE | AC109: FALSE | AD109: FALSE | AE109: TRUE | AJ109: 46066.445 | AK109: 46067.45 | AM109: 46066.445 | AN109: 46066.445 | CQ109: 5 | CR109: https://desk.channel.io/gowid/user-chats/698e8124219a0d6dc8e5
A110: 698e8108bb8305e0104c | B110: 46066.445 | C110: {=INDEX('User data'!E:E, MATCH(E110, 'User data'!B:B, 0))} -> 주식회사 지투지바이오 | D110: {=INDEX('User data'!F:F, MATCH(C110, 'User data'!E:E, 0))} -> 195-88-00664 | E110: 지투지바이오 | J110: medium | K110: INBOUND | L110: FALSE | M110: https://www.gowid.com | N110: 684f6cc36ba131999906 | T110: native | W110: initial | Y110: waiting | AA110: FALSE | AB110: FALSE | AC110: FALSE | AD110: FALSE | AE110: TRUE | AJ110: 46066.445 | AK110: 46067.445 | AM110: 46066.445 | AN110: 46066.445 | CQ110: 5 | CR110: https://desk.channel.io/gowid/user-chats/698e8108bb8305e0104c
A111: 698e7ce08bba387b5b14 | B111: 46066.433 | C111: {=INDEX('User data'!E:E, MATCH(E111, 'User data'!B:B, 0))} -> 주식회사 더라스트 | D111: {=INDEX('User data'!F:F, MATCH(C111, 'User data'!E:E, 0))} -> 101-86-92452 | E111: 최미정 | J111: medium | K111: INBOUND | L111: FALSE | M111: https://www.gowid.com | N111: 6747c4f36154e97c3cde | T111: native | W111: initial | Y111: waiting | AA111: FALSE | AB111: FALSE | AC111: FALSE | AD111: FALSE | AE111: TRUE | AJ111: 46066.432 | AK111: 46067.433 | AM111: 46066.433 | AN111: 46066.433 | CQ111: 1.8 | CR111: https://desk.channel.io/gowid/user-chats/698e7ce08bba387b5b14
A112: 698e75cd6fcaea0e8a45 | B112: 46066.412 | C112: {=INDEX('User data'!E:E, MATCH(E112, 'User data'!B:B, 0))} -> 로지스핏 주식회사 | D112: {=INDEX('User data'!F:F, MATCH(C112, 'User data'!E:E, 0))} -> 186-88-02334 | E112: 윤미영 | H112: 문의요약: 공동인증서 기간 만료 예정, 범용 가능성 문의 문의유형: 인증서 관련 impact: L2 처리내용: 범용인증서 사용 가능성 안내 결과: 추가 정보 제공 예정 후속조치: 고객에게 후속 연락 예정 | J112: medium | K112: INBOUND | L112: FALSE | M112: https://www.gowid.com | N112: 67ee034a1f87b57df5b2 | T112: native | W112: closed | Y112: waiting | AA112: FALSE | AB112: FALSE | AC112: FALSE | AD112: FALSE | AE112: TRUE | AJ112: 46066.411 | AK112: 46067.412 | AM112: 46066.412 | AN112: 46066.412 | BC112: 46066.413 | BD112: 46066.413 | BY112: 122 | BZ112: 0 | CA112: 122 | CB112: 0 | CC112: 122 | CD112: 0 | CQ112: 5 | CR112: https://desk.channel.io/gowid/user-chats/698e75cd6fcaea0e8a45
A113: 698e6a51df4789be1fb8 | B113: 46066.378 | C113: {=INDEX('User data'!E:E, MATCH(E113, 'User data'!B:B, 0))} -> 주식회사 위밋모빌리티 | D113: {=INDEX('User data'!F:F, MATCH(C113, 'User data'!E:E, 0))} -> 806-87-00694 | E113: 박경애 | J113: medium | K113: INBOUND | L113: FALSE | M113: https://docs.channel.io/gowid-guide/ko | N113: 682417fee9c940b1272b | T113: native | W113: initial | Y113: waiting | AA113: FALSE | AB113: FALSE | AC113: FALSE | AD113: FALSE | AE113: TRUE | AJ113: 46066.377 | AK113: 46067.382 | AM113: 46066.378 | AN113: 46066.378 | CQ113: 5 | CR113: https://desk.channel.io/gowid/user-chats/698e6a51df4789be1fb8
A114: 698e6a2772e0bc0e3d76 | B114: 46066.377 | C114: {=INDEX('User data'!E:E, MATCH(E114, 'User data'!B:B, 0))} -> 주식회사 위밋모빌리티 | D114: {=INDEX('User data'!F:F, MATCH(C114, 'User data'!E:E, 0))} -> 806-87-00694 | E114: 박경애 | J114: medium | K114: INBOUND | L114: FALSE | M114: https://www.gowid.com | N114: 682417fee9c940b1272b | T114: native | W114: initial | Y114: waiting | AA114: FALSE | AB114: FALSE | AC114: FALSE | AD114: FALSE | AE114: TRUE | AJ114: 46066.377 | AK114: 46067.377 | AM114: 46066.377 | AN114: 46066.377 | CQ114: 5 | CR114: https://desk.channel.io/gowid/user-chats/698e6a2772e0bc0e3d76
A115: 698e5ef9166e4e950f0d | B115: 46066.345 | C115: {=INDEX('User data'!E:E, MATCH(E115, 'User data'!B:B, 0))} -> 주식회사 어글리랩 | D115: {=INDEX('User data'!F:F, MATCH(C115, 'User data'!E:E, 0))} -> 524-86-02323 | E115: 전혜림 | J115: medium | K115: INBOUND | L115: FALSE | M115: https://www.gowid.com | N115: 6704c9ffda4cc452af14 | T115: native | W115: initial | Y115: waiting | AA115: FALSE | AB115: FALSE | AC115: FALSE | AD115: FALSE | AE115: TRUE | AJ115: 46066.344 | AK115: 46067.345 | AM115: 46066.345 | AN115: 46066.345 | CQ115: 3.4 | CR115: https://desk.channel.io/gowid/user-chats/698e5ef9166e4e950f0d
A116: 698da53927fe09b35856 | B116: 46065.793 | C116: {=INDEX('User data'!E:E, MATCH(E116, 'User data'!B:B, 0))} -> 주식회사 고위드(GOWID Inc) | D116: {=INDEX('User data'!F:F, MATCH(C116, 'User data'!E:E, 0))} -> 261-81-25793 | E116: 고위드 컨택트 | J116: medium | K116: INBOUND | L116: FALSE | M116: https://www.gowid.com | N116: 639bced9e0073c30c4fe | T116: native | W116: initial | Y116: waiting | AA116: FALSE | AB116: FALSE | AC116: FALSE | AD116: FALSE | AE116: TRUE | AJ116: 46065.793 | AK116: 46066.794 | AM116: 46065.793 | AN116: 46065.793 | CQ116: 3.6 | CR116: https://desk.channel.io/gowid/user-chats/698da53927fe09b35856
A117: 698d99d1b730d5d0e4be | B117: 46065.76 | C117: {=INDEX('User data'!E:E, MATCH(E117, 'User data'!B:B, 0))} -> 주식회사 언엑스 | D117: {=INDEX('User data'!F:F, MATCH(C117, 'User data'!E:E, 0))} -> 118-88-03591 | E117: 김광민 | J117: medium | K117: INBOUND | L117: FALSE | M117: https://www.gowid.com | N117: 6982c546a76828f130b5 | T117: native | W117: initial | Y117: waiting | AA117: FALSE | AB117: FALSE | AC117: FALSE | AD117: FALSE | AE117: TRUE | AJ117: 46065.76 | AK117: 46066.76 | AM117: 46065.76 | AN117: 46065.76 | CQ117: 3.4 | CR117: https://desk.channel.io/gowid/user-chats/698d99d1b730d5d0e4be
A118: 698d8f6a12f30d4c1d21 | B118: 46065.731 | C118: {=INDEX('User data'!E:E, MATCH(E118, 'User data'!B:B, 0))} -> 주식회사 보살핌 | D118: {=INDEX('User data'!F:F, MATCH(C118, 'User data'!E:E, 0))} -> 440-88-02179 | E118: 배민혜 | H118: [상담요약] - 고객사: 보살핌 - 문의요약: 카드 한도 상향 조건 확인 - 문의유형: 한도 상향 - impact: L2 - 처리내용: 현금 유지 조건 확인 요청 - 결과: 정보 제공 필요 - 후속조치: 현금 자산 내역 확인 후 안내 | J118: medium | K118: OUTBOUND | L118: FALSE | N118: 697021be3bbba76c08d0 | O118: 574085 | P118: 574085 | Q118: 574085 | R118: 574085 | T118: email | U118: email | W118: closed | Y118: waiting | AA118: TRUE | AB118: FALSE | AC118: FALSE | AD118: FALSE | AE118: FALSE | AJ118: 46065.729 | AK118: 46073.569 | AM118: 46065.731 | AT118: 46065.731 | AU118: 46073.542 | AX118: 46065.729 | AY118: 46065.731 | BB118: 46072.567 | BC118: 46073.569 | BD118: 46073.569 | BI118: 411577 | BJ118: 51819 | BY118: 677171 | BZ118: 117529 | CA118: 677171 | CB118: 117529 | CC118: 677171 | CD118: 117529 | CE118: 677359 | CF118: 117529 | CG118: 677171 | CH118: 117529 | CI118: 677171 | CJ118: 117529 | CK118: 265593 | CL118: 65710 | CM118: 265593 | CN118: 65710 | CR118: https://desk.channel.io/gowid/user-chats/698d8f6a12f30d4c1d21
A119: 698d8cd18c43e0ec9e50 | B119: 46065.721 | C119: {=INDEX('User data'!E:E, MATCH(E119, 'User data'!B:B, 0))} | D119: {=INDEX('User data'!F:F, MATCH(C119, 'User data'!E:E, 0))} -> #N/A | E119: 나비 423 | J119: medium | K119: INBOUND | L119: FALSE | M119: https://www.gowid.com | N119: 698d8c5976cc928d33b7 | T119: native | W119: initial | Y119: waiting | AA119: FALSE | AB119: FALSE | AC119: FALSE | AD119: FALSE | AE119: TRUE | AJ119: 46065.721 | AK119: 46066.722 | AM119: 46065.721 | AN119: 46065.721 | CQ119: 5 | CR119: https://desk.channel.io/gowid/user-chats/698d8cd18c43e0ec9e50
A120: 698d8aa8aae60544b3c6 | B120: 46065.715 | C120: {=INDEX('User data'!E:E, MATCH(E120, 'User data'!B:B, 0))} -> 주식회사 용감한컴퍼니 | D120: {=INDEX('User data'!F:F, MATCH(C120, 'User data'!E:E, 0))} -> 114-86-92856 | E120: ellia | J120: medium | K120: INBOUND | L120: FALSE | M120: https://www.gowid.com | N120: 6888b58140a9649b8e61 | T120: native | W120: initial | Y120: waiting | AA120: FALSE | AB120: FALSE | AC120: FALSE | AD120: FALSE | AE120: TRUE | AJ120: 46065.715 | AK120: 46066.715 | AM120: 46065.715 | AN120: 46065.715 | CQ120: 5 | CR120: https://desk.channel.io/gowid/user-chats/698d8aa8aae60544b3c6
A121: 698d8a894c3e8194b163 | B121: 46065.714 | C121: {=INDEX('User data'!E:E, MATCH(E121, 'User data'!B:B, 0))} -> 주식회사 스펙터 | D121: {=INDEX('User data'!F:F, MATCH(C121, 'User data'!E:E, 0))} -> 449-88-01707 | E121: Admin | J121: medium | K121: INBOUND | L121: FALSE | M121: https://www.gowid.com | N121: 672dab8353c1c94e58eb | T121: native | W121: initial | Y121: waiting | AA121: FALSE | AB121: FALSE | AC121: FALSE | AD121: FALSE | AE121: TRUE | AJ121: 46065.714 | AK121: 46066.715 | AM121: 46065.714 | AN121: 46065.714 | CQ121: 2 | CR121: https://desk.channel.io/gowid/user-chats/698d8a894c3e8194b163
A122: 698d875a559ad256cbb6 | B122: 46065.706 | C122: {=INDEX('User data'!E:E, MATCH(E122, 'User data'!B:B, 0))} -> 주식회사 보살핌 | D122: {=INDEX('User data'!F:F, MATCH(C122, 'User data'!E:E, 0))} -> 440-88-02179 | E122: 배민혜 | H122: 문의 내용이 15글자 이하로 요약할 내용이 없습니다. | I122: 카드/한도상하향 | J122: medium | K122: INBOUND | L122: FALSE | M122: https://www.gowid.com | N122: 697021be3bbba76c08d0 | O122: 574085 | P122: 574085 | Q122: 574085 | R122: 574085, 607950 | S122: 13285 | T122: native | W122: closed | Y122: none | AA122: TRUE | AB122: FALSE | AC122: FALSE | AD122: TRUE | AE122: TRUE | AF122: 3 | AJ122: 46065.705 | AK122: 46073.574 | AL122: 46065.707 | AM122: 46065.706 | AN122: 46065.706 | AO122: 46065.706 | AP122: 46065.707 | AQ122: 46065.706 | AS122: 46065.706 | AT122: 46065.706 | AU122: 46073.542 | AX122: 46065.706 | AY122: 46065.706 | AZ122: 46065.728 | BA122: 46073.571 | BB122: 46072.567 | BC122: 46073.574 | BD122: 46073.574 | BE122: 6161 | BG122: 2053 | BI122: 371073 | BJ122: 51819 | BK122: 0 | BL122: 0 | BM122: 42 | BN122: 42 | BO122: 1949 | BP122: 233 | BQ122: 1949 | BR122: 233 | BS122: 1907 | BT122: 191 | BU122: 1907 | BV122: 191 | BW122: 1907 | BX122: 192 | BY122: 679865 | BZ122: 118265 | CA122: 679865 | CB122: 118265 | CC122: 679865 | CD122: 118265 | CE122: 679823 | CF122: 118223 | CG122: 679823 | CH122: 118223 | CI122: 679823 | CJ122: 118223 | CK122: 308750 | CL122: 66404 | CM122: 308750 | CN122: 66404 | CO122: 3 | CP122: 41 | CR122: https://desk.channel.io/gowid/user-chats/698d875a559ad256cbb6
A123: 698d86b94f7738c54e88 | B123: 46065.703 | C123: {=INDEX('User data'!E:E, MATCH(E123, 'User data'!B:B, 0))} -> 주식회사 보살핌 | D123: {=INDEX('User data'!F:F, MATCH(C123, 'User data'!E:E, 0))} -> 440-88-02179 | E123: 배민혜 | J123: medium | K123: INBOUND | L123: FALSE | M123: https://www.gowid.com | N123: 697021be3bbba76c08d0 | T123: native | W123: closed | Y123: waiting | AA123: FALSE | AB123: FALSE | AC123: FALSE | AD123: FALSE | AE123: TRUE | AJ123: 46065.703 | AK123: 46066.705 | AM123: 46065.703 | AN123: 46065.703 | BC123: 46065.705 | BD123: 46065.705 | BY123: 156 | BZ123: 156 | CA123: 156 | CB123: 156 | CC123: 156 | CD123: 156 | CQ123: 1 | CR123: https://desk.channel.io/gowid/user-chats/698d86b94f7738c54e88
A124: 698d84132769dc49b862 | B124: 46065.695 | C124: {=INDEX('User data'!E:E, MATCH(E124, 'User data'!B:B, 0))} -> 펀치랩 주식회사 | D124: {=INDEX('User data'!F:F, MATCH(C124, 'User data'!E:E, 0))} -> 626-88-02996 | E124: 정소영 | J124: medium | K124: INBOUND | L124: FALSE | M124: https://www.gowid.com | N124: 68a2af36a7c7f5f0db08 | T124: native | W124: initial | Y124: waiting | AA124: FALSE | AB124: FALSE | AC124: FALSE | AD124: FALSE | AE124: TRUE | AJ124: 46065.695 | AK124: 46066.695 | AM124: 46065.695 | AN124: 46065.695 | CQ124: 5 | CR124: https://desk.channel.io/gowid/user-chats/698d84132769dc49b862
A125: 698d81f71b7c12401dcf | B125: 46065.69 | C125: {=INDEX('User data'!E:E, MATCH(E125, 'User data'!B:B, 0))} -> 농업회사법인 아이오크롭스 주식회사 | D125: {=INDEX('User data'!F:F, MATCH(C125, 'User data'!E:E, 0))} -> 833-81-01261 | E125: 정지예 | I125: 구독/GWS | J125: medium | K125: INBOUND | L125: FALSE | M125: https://www.gowid.com | N125: 68770b3bb053702816fc | O125: 594863 | P125: 594863 | Q125: 594863 | R125: 594863 | S125: 13288 | T125: native | W125: closed | Y125: none | AA125: TRUE | AB125: FALSE | AC125: FALSE | AD125: TRUE | AE125: TRUE | AF125: 6 | AG125: 6 | AJ125: 46065.689 | AK125: 46065.745 | AL125: 46065.692 | AM125: 46065.69 | AN125: 46065.69 | AO125: 46065.691 | AP125: 46065.692 | AQ125: 46065.691 | AS125: 46065.691 | AT125: 46065.691 | AU125: 46065.691 | AX125: 46065.691 | AY125: 46065.691 | AZ125: 46065.694 | BA125: 46065.703 | BC125: 46065.703 | BD125: 46065.703 | BE125: 668 | BF125: 668 | BG125: 111 | BH125: 111 | BK125: 0 | BL125: 0 | BM125: 90 | BN125: 90 | BO125: 311 | BP125: 311 | BQ125: 311 | BR125: 311 | BS125: 221 | BT125: 221 | BU125: 252 | BV125: 252 | BW125: 252 | BX125: 252 | BY125: 1135 | BZ125: 1135 | CA125: 1135 | CB125: 1135 | CC125: 1135 | CD125: 1135 | CE125: 1045 | CF125: 1045 | CG125: 1075 | CH125: 1075 | CI125: 1075 | CJ125: 1075 | CK125: 1075 | CL125: 1075 | CM125: 1075 | CN125: 1075 | CO125: 3 | CP125: 59 | CR125: https://desk.channel.io/gowid/user-chats/698d81f71b7c12401dcf | CS125: 5 | CT125: 친절한 안내 감사드립니다.
...

Sheet Message data
A1: chatId | B1: personType | C1: personId | D1: createdAt | E1: plainText | F1: isPrivate
A2: 69707792ccb5efbface7 | B2: user | C2: 696db3205e96892e8e31 | D2: 46051.364 | E2: 안녕하세요. 고위드 신규 가입 상담 중인 헬로스킨 인사팀 지소영입니다. 전 직장에서 고위드 사용했어서 그대로 도입하고자 합니다. 1. 저희는 자체 기장을 하고 있지 않고 세무법인을 통해 기장 중입니다. 위하고를 사용하고 있는 것으로 전달 받았는데 고위드- 위하고 간 연결이 가능한가요? 2. 구글워크스페이스 도입을 하려고 합니다. (기존은 Google Workspace Enterprise Essentials 요금제를 쓰고 있습니다. 메일 기능이 없는 드라이브 용 요금제이나 엔터프라이즈 로 분류됐어서 리셀러사 문의시 스탠다드, 플러스 요금제에서 당장 큰 할인이 없었습니다. 고위드를 통해 구글워크스페이스 업그레이드를 진행하면 안내된 금액대로 이용이 가능한지요? 3. 구글 워크스페이스 기능 등에 대한 문의시 리셀러사처럼 안내를 받을 수 있나요? | F2: FALSE
A3: 69707792ccb5efbface7 | B3: user | C3: 696db3205e96892e8e31 | D3: 46051.37 | E3: 추가로 메일 마이그레이션 지원도 여쭤봅니다 | F3: FALSE
A4: 69707792ccb5efbface7 | B4: user | C4: 696db3205e96892e8e31 | D4: 46051.399 | E4: 기존 사용 사 기준 홈페이지상 견적이 공식홈페이지와 같은데 고위드 추가 할인이 없는 걸까요? | F4: FALSE
A5: 69707792ccb5efbface7 | B5: manager | C5: 574085 | D5: 46051.401 | E5: 소영님 안녕하세요, 고위드입니다. 우선 문의 주신 내용 중 1번 문의부터 답변 드리도록 하게습니다. 고위드에서는 카드 지출 내역을 더존-위하고 양식으로 다운로드 가능한 점 안내드립니다. 구독 관련 문의에 대해서는 담당자님 확인 후 안내드릴 수 있도록 하겠습니다. 감사합니다. | F5: FALSE
A6: 69707792ccb5efbface7 | B6: manager | C6: 574085 | D6: 46051.404 | E6: @고위드 김일경 매니저 일경님 구독 문의 들어왔습니다 | F6: TRUE
A7: 69707792ccb5efbface7 | B7: manager | C7: 594863 | D7: 46051.405 | E7: 넵! | F7: TRUE
A8: 69707792ccb5efbface7 | B8: manager | C8: 594863 | D8: 46051.414 | E8: 안녕하세요 지소영님 ☺️ 고위드 구독 서비스 김일경 매니저입니다. 구독 상품 관련 안내 드립니다. :) 1. 고위드를 통해 구글워크스페이스 업그레이드를 진행하면 안내된 금액대로 이용이 가능한지요? → 네, 비즈니스 요금제로 전환 하신 후 고위드 리셀러 신청을 해주시면 고위드 사이트에서 확인하실 수 있는 견적서대로 10%할인을 받으실 수 있습니다. 다만, 비즈니스 모델 특성 상 300명이 초과되는 인원은 상품 전환이 어려운 점 참고 부탁 드립니다. 2. 구글 워크스페이스 기능 등에 대한 문의시 리셀러사처럼 안내를 받을 수 있나요? → 네, 물론입니다. 기능 문의에 대한 부분은 담당자께서 상담을 통한 안내를 드리고 있습니다. 더해서, 고위드 구글워크스페이스는 버전 변경, 라이센스 수 변경을 고위드 홈페이지 내에서 진행 하실 수 있도록 서비스를 운영하고 있습니다. 이 외에도 기존에 사용하시던 모든 기능을 구글 콘솔을 통해서도 사용이 가능합니다. :) | F8: FALSE
A9: 69707792ccb5efbface7 | B9: user | C9: 696db3205e96892e8e31 | D9: 46051.424 | E9: 안녕하세요 - | F9: FALSE
A10: 69707792ccb5efbface7 | B10: user | C10: 696db3205e96892e8e31 | D10: 46051.424 | E10: 저희가 사용했던 요금제가 메일 기능이 없기는 하다 | F10: FALSE
A11: 69707792ccb5efbface7 | B11: user | C11: 696db3205e96892e8e31 | D11: 46051.424 | E11: 엔터프라이즈 에센셜로 명칭이있어 | F11: FALSE
A12: 69707792ccb5efbface7 | B12: user | C12: 696db3205e96892e8e31 | D12: 46051.424 | E12: 스탠다드로 변경하는 경우 '다운그레이드'라 | F12: FALSE
A13: 69707792ccb5efbface7 | B13: user | C13: 696db3205e96892e8e31 | D13: 46051.424 | E13: 할인가를 당장 받을 수 없다고 다른 리셀러사에서 연락을 받았습니다. | F13: FALSE
A14: 69707792ccb5efbface7 | B14: user | C14: 696db3205e96892e8e31 | D14: 46051.424 | E14: 고위드를 통하면 문제가 확실히 없는 것일까요? | F14: FALSE
A15: 69707792ccb5efbface7 | B15: user | C15: 696db3205e96892e8e31 | D15: 46051.425 | E15: 더하여, 공식 홈페이지 견적과 가격이 같게 나와서, | F15: FALSE
A16: 69707792ccb5efbface7 | B16: user | C16: 696db3205e96892e8e31 | D16: 46051.425 | E16: 저희는 신규 구글워크스페이스 도입이 아니어서 추가 할인이 안되는 것인지요? | F16: FALSE
A17: 69707792ccb5efbface7 | B17: manager | C17: 594863 | D17: 46051.425 | E17: 해당 내용 유선 통해 자세히 안내 드리면 더욱 좋을 것 같은데요! 희망 하시면 유선 문의로 전환 도와드릴까요? 아니면 채팅 답변도 가능합니다! | F17: FALSE
A18: 69707792ccb5efbface7 | B18: user | C18: 696db3205e96892e8e31 | D18: 46051.438 | E18: 오후 1시쯤에 통화 가능할까요? | F18: FALSE
A19: 69707792ccb5efbface7 | B19: user | C19: 696db3205e96892e8e31 | D19: 46051.438 | E19: 미팅이 있어서요 | F19: FALSE
A20: 69707792ccb5efbface7 | B20: manager | C20: 594863 | D20: 46051.438 | E20: 네! :) 13시 30분 경에 유선 안내 드릴 수 있도록 하겠습니다! 감사합니다. | F20: FALSE
A21: 69707792ccb5efbface7 | B21: user | C21: 696db3205e96892e8e31 | D21: 46051.439 | E21: 네 감사합니다 | F21: FALSE
A22: 69707792ccb5efbface7 | B22: manager | C22: 594863 | D22: 46051.44 | E22: 유선 안내 예정 | F22: TRUE
A23: 69707792ccb5efbface7 | B23: manager | C23: 594863 | D23: 46051.575 | E23: 유선으로 상담 마무리 되어 이번 상담은 여기서 종료하도록 하겠습니다. 다른 문의가 있으시면 새로운 창에서 문의 부탁드립니다. 좋은 하루 되시길 바랍니다 :) | F23: FALSE
A24: 6976bcf86eb9a25e8354 | B24: user | C24: 66946e4fa6ee2b22e45e | D24: 46048.419 | E24: 안녕하세요 법인카드 상향 신청 문의 드립니다. 1월 중 진행했었는데, 심사는 완료되었는데 계속하여 오류가 발생하는 것 같습니다. (동일 화면 재송신) 관련하여 확인 부탁 드립니다. 감사합니다. - 알리콘 주식회사 / 363-88-00097 - 법인카드 상향 심사 상황 및 가능여부 | F24: FALSE
A25: 6976bcf86eb9a25e8354 | B25: manager | C25: 506375 | D25: 46048.425 | E25: 안녕하세요 지은님, 고위드입니다. 불편을 드려 죄송합니다..! 내부적으로 확인 결과, 1/15 즈음 해당시기에 한도를 부여받기 어려우심을 안내받으신 것으로 확인되시는데요, 혹 지금 만나보시는 화면이 어떻게 되실까요? 오류일 시 확인 후 응대 도와드리고자 합니다! | F25: FALSE
A26: 6976bcf86eb9a25e8354 | B26: manager | C26: 506375 | D26: 46048.425 | E26: 상세하게 안내해드리기 위해 말씀해주신 증상에 대한 전체화면 캡쳐본을 보내주시면 감사하겠습니다. | F26: FALSE
A27: 6976c63b7ff568629b43 | B27: user | C27: 6971d94bc3ded889e1b9 | D27: 46048.447 | E27: 주주명부를 왜줘야하나요-->/ | F27: FALSE
A28: 6976c63b7ff568629b43 | B28: user | C28: 6971d94bc3ded889e1b9 | D28: 46048.447 | E28: 상담사연결 | F28: FALSE
A29: 6976c63b7ff568629b43 | B29: user | C29: 6971d94bc3ded889e1b9 | D29: 46048.447 | E29: 그냥 상담사연결해주세요 | F29: FALSE
A30: 6976c63b7ff568629b43 | B30: user | C30: 6971d94bc3ded889e1b9 | D30: 46048.447 | E30: 네 맞습니다 상담사연결해주세요 | F30: FALSE
A31: 6976c63b7ff568629b43 | B31: user | C31: 6971d94bc3ded889e1b9 | D31: 46048.448 | E31: 안녕하세요. | F31: FALSE
A32: 6976c63b7ff568629b43 | B32: user | C32: 6971d94bc3ded889e1b9 | D32: 46048.449 | E32: 주주명부를 왜전달해야하는지 모르겠어서 이야기드립니다. 그리고 저희회사는 싱가폴회사가 100%지분을가지고있는데 주주 명부가 필요할까요? | F32: FALSE
A33: 6976c63b7ff568629b43 | B33: manager | C33: 574085 | D33: 46048.451 | E33: 종빈님 안녕하세요, 고위드입니다. 법인 신용 카드 입회 시 금융소비자보호법에 따라 해당 법인의 실제 소유자를 확인하는 것은 필수 사항입니다. 이는 고위드 내부 정책이 아니라 카드사 입회 시 카드사에서 요구하는 필수 서류입니다. 더욱 정확한 안내를 위하여 법인께서 입회 희망하시는 카드사(신한/롯데/비씨 중)가 어디실지 여쭙습니다. | F33: FALSE
A34: 6976c63b7ff568629b43 | B34: user | C34: 6971d94bc3ded889e1b9 | D34: 46048.452 | E34: 롯데카드입니다 | F34: FALSE
A35: 6976c63b7ff568629b43 | B35: manager | C35: 574085 | D35: 46048.459 | E35: 롯데카드의 경우 1. 법인(A)의 최대 주주가 타 법인(B)일 경우, B법인의 주주명부 또한 요구하고 있습니다. 2. 다만 해외 법인으로 주주명부 수취가 불가할 경우 A법인 명의의 공문서를 통하여 갈음이 가능합니다. 주주명부 업로드하는 단계에서 1. 주식회사 라디우스랩의 주주명부 2. 주식회사 라디우스랩의 공문서 (최대 법인 주주명부 수취 불가) 를 함께 첨부하여 주시면 됩니다! 공문서 양식을 사진 첨부하여 함께 보내드리며, 수신에는 '롯데카드' 작성 부탁드립니다. | F35: FALSE
A36: 6976c63b7ff568629b43 | B36: manager | C36: 574085 | D36: 46048.46 | E36: 작성하셔야 하는 '롯데카드 실제소유자 확인서'에는 실제소유자 구분 > 3. '2항'을 확인할 수 없는 경우, 법인 또는 단체의 대표자 중 1인에 체크하여 주시고 아래 실제 소유자 정보에는 싱가포르 법인 정보 작성 부탁드립니다. | F36: FALSE
A37: 6976c63b7ff568629b43 | B37: manager | C37: 574085 | D37: 46048.468 | E37: 답장 오면 사실상 지배자 그 내용도 안내하기 | F37: TRUE
A38: 6976c63b7ff568629b43 | B38: user | C38: 6971d94bc3ded889e1b9 | D38: 46048.5 | E38: 여기서질문이 저희는 싱가폴 회사가 모회사이고 지금 현재 카드를 신청하는회사가 자회사입니다. | F38: FALSE
A39: 6976c63b7ff568629b43 | B39: user | C39: 6971d94bc3ded889e1b9 | D39: 46048.5 | E39: 이때는 싱가폴 회사인 모회사의 주주명부를 줘야하는건가요? | F39: FALSE
A40: 6976c63b7ff568629b43 | B40: manager | C40: 574085 | D40: 46048.502 | E40: 종빈님 혹시 유선으로 안내드려도 괜찮으실까요? 주주명부 관련 내용이 복잡하고, 최대 주주가 해외 법인일 경우 작성 방법이 별도로 있어 안내드리고자 합니다. 채널톡이 더 편하실 경우 제가 여기서 그대로 안내 도와드리도록 하겠습니다./ | F40: FALSE
A41: 6976c63b7ff568629b43 | B41: user | C41: 6971d94bc3ded889e1b9 | D41: 46048.504 | E41: 네네 | F41: FALSE
A42: 6976c63b7ff568629b43 | B42: user | C42: 6971d94bc3ded889e1b9 | D42: 46048.504 | E42: 전화주시면 감사하겠습니다 | F42: FALSE
A43: 6976c63b7ff568629b43 | B43: user | C43: 6971d94bc3ded889e1b9 | D43: 46048.504 | E43: 아.. | F43: FALSE
A44: 6976c63b7ff568629b43 | B44: user | C44: 6971d94bc3ded889e1b9 | D44: 46048.504 | E44: 제가 지금 핸드폰을 집에놓고와서.. | F44: FALSE
A45: 6976c63b7ff568629b43 | B45: user | C45: 6971d94bc3ded889e1b9 | D45: 46048.504 | E45: 다른번호로 전화부탁드리겠습니다. | F45: FALSE
A46: 6976c63b7ff568629b43 | B46: manager | C46: 574085 | D46: 46048.504 | E46: 넵 유선 희망하시는 번호 남겨주시면 제가 바로 전화드리겠습니다. | F46: FALSE
A47: 6976c63b7ff568629b43 | B47: user | C47: 6971d94bc3ded889e1b9 | D47: 46048.504 | E47: 010-46840787 | F47: FALSE
A48: 6976c63b7ff568629b43 | B48: user | C48: 6971d94bc3ded889e1b9 | D48: 46048.504 | E48: 입니다 | F48: FALSE
A49: 6976c63b7ff568629b43 | B49: user | C49: 6971d94bc3ded889e1b9 | D49: 46048.505 | F49: FALSE
A50: 6976c63b7ff568629b43 | B50: user | C50: 6971d94bc3ded889e1b9 | D50: 46048.506 | F50: FALSE
A51: 6976c63b7ff568629b43 | B51: manager | C51: 574085 | D51: 46048.507 | F51: FALSE
A52: 6976c63b7ff568629b43 | B52: manager | C52: 574085 | D52: 46048.508 | F52: FALSE
A53: 6976c63b7ff568629b43 | B53: manager | C53: 574085 | D53: 46048.513 | E53: 안녕하세요 한종빈 담당자님, 유선 안내드린 고위드 권민규 매니저입니다. 추가적으로 현재 주식회사 라디우스랩의 부여받으신 한도는 내일까지 유효하시기에 금일 중 카드 신청 완료하시길 권유 드립니다. 유효 기간이 끝나면 다시 한도 산출부터 확인하셔야 하는 불편함이 있어 안내드립니다. 감사합니다. | F53: FALSE
A54: 6976c81bde9186f60b7a | B54: user | C54: 6976c76fb3e08e7ef3ed | D54: 46048.454 | E54: - 주식회사 선하다 / 301-88-01711 - 내 정보에 등록된 핸드폰번호가 퇴사자의 번호로 등록되어있어, 최초계약자 변경 요청 메일을 전송하였습니다. 1월 16일에 메일을 전송하였으나 아직 처리가 되지 않아, 변경까지 소요되는 시간을 문의드립니다. | F54: FALSE
A55: 6976c81bde9186f60b7a | B55: manager | C55: 506375 | D55: 46048.463 | E55: @망고 매니저 님! | F55: TRUE
A56: 6976c81bde9186f60b7a | B56: manager | C56: 574085 | D56: 46048.463 | E56: 나영님 안녕하세요, 고위드입니다. 우선 1월 16일에 메일 발송하시고 아직까지 회신을 받아보지 못하시고 계셔서 많이 불편하셨으리라 생각합니다. 서비스 이용에 불편을 드려 죄송합니다. 다만 1월 16일에 주식회사 선하다 로 부터 발송된 메일이 확인되지 않고 있습니다. 메일 주소 card_bizops@gowid.com 로 보내신 게 맞으실까요? 법인께서 발송하신 메일 주소도 전달 주시면 제가 다시 확인해보겠습니다! | F56: FALSE
A57: 6976c81bde9186f60b7a | B57: manager | C57: 506375 | D57: 46048.463 | E57: 최고 | F57: TRUE
A58: 6976c81bde9186f60b7a | B58: manager | C58: 574085 | D58: 46048.463 | E58: 확인해봤는데 없어요 ㅠㅠ 제가 마무리하겠슴닷! | F58: TRUE
A59: 6976c81bde9186f60b7a | B59: manager | C59: 506375 | D59: 46048.465 | E59: 호잉 ㅠㅠ | F59: TRUE
A60: 6976c81bde9186f60b7a | B60: user | C60: 6976c76fb3e08e7ef3ed | D60: 46048.481 | F60: FALSE
A61: 6976c81bde9186f60b7a | B61: user | C61: 6976c76fb3e08e7ef3ed | D61: 46048.481 | E61: 넵 해당 메일주소로 발송하였습니다. 발송일자 : 26년 1월 16일 발송 메일주소 : ny.kim@caring.co.kr 입니다 ! | F61: FALSE
A62: 6976c81bde9186f60b7a | B62: manager | C62: 574085 | D62: 46048.484 | E62: 나영님, 확인해주셔서 감사합니다. 제가 메일을 다시 확인해보았지만, 해당 계정으로 발송된 메일이 확인되지 않는 상황입니다. 괜찮으시다면 해당 채널톡으로 서류 3종 보내주시면 제가 바로 변경 도와드리도록 하겠습니다! 번거롭게 해드려 죄송합니다. | F62: FALSE
A63: 6976c81bde9186f60b7a | B63: user | C63: 6976c76fb3e08e7ef3ed | D63: 46048.485 | E63: 감사합니다. 자료 송부드립니다 ! | F63: FALSE
A64: 6976c81bde9186f60b7a | B64: user | C64: 6976c76fb3e08e7ef3ed | D64: 46048.486 | F64: FALSE
A65: 6976c81bde9186f60b7a | B65: user | C65: 6976c76fb3e08e7ef3ed | D65: 46048.486 | F65: FALSE
A66: 6976c81bde9186f60b7a | B66: user | C66: 6976c76fb3e08e7ef3ed | D66: 46048.486 | F66: FALSE
A67: 6976c81bde9186f60b7a | B67: manager | C67: 574085 | D67: 46048.489 | E67: 현재 변경 진행하시려는 이메일이 고위드 계정으로 가입되어있지 않으십니다. 법인의 멤버 중 ny.kimn@caring.co.kr 계정이 확인되지 않는데, 멤버 초대 및 가입 후 말씀 주시면 바로 변경해드리도록 하겠습니다! | F67: FALSE
A68: 6976c81bde9186f60b7a | B68: user | C68: 66b97ad2dbc638bf7456 | D68: 46048.494 | E68: 메일주소는 기존 sunhada1233@naver.com 메일주소에서 변경하지 않고, 핸드폰 번호만 변경가능할까요 ?? | F68: FALSE
A69: 6976c81bde9186f60b7a | B69: manager | C69: 574085 | D69: 46048.496 | E69: 넵 가능하십니다. 현재 법인담당자님께서 - 선하다 복지용구사업소 / 010-8375-6553 / sunhada1233@naver.com 로 되어계시는데 전화번호 변경만 도와드릴까요? | F69: FALSE
A70: 6976c81bde9186f60b7a | B70: user | C70: 66b97ad2dbc638bf7456 | D70: 46048.497 | E70: 넵 맞습니다. 핸드폰 번호만 010-8975-7263으로 변경 요청드립니다 ! | F70: FALSE
A71: 6976c81bde9186f60b7a | B71: manager | C71: 574085 | D71: 46048.499 | E71: 변경 완료했습니다. 기존 법인담당자와 동일하게 해두었으며, 전화 번호만 변경 도와드렸습니다.감사합니다. | F71: FALSE
A72: 6976c81bde9186f60b7a | B72: user | C72: 66b97ad2dbc638bf7456 | D72: 46048.5 | E72: 확인 하였습니다. 감사합니다 ~ | F72: FALSE
A73: 6976c81bde9186f60b7a | B73: manager | C73: 574085 | D73: 46048.503 | E73: 감사합니다. 이번 상담은 여기서 종료하도록 하겠습니다. 다른 문의가 있으시면 새로운 창에서 문의 부탁드립니다. 좋은 하루 되시길 바랍니다 :) | F73: FALSE
A74: 6976cc6bc562a95cafde | B74: user | C74: 6976cbfbd830f379026d | D74: 46048.538 | E74: 혹시 총 120명 되는 회사 규모에서 일부는 스탠다드, 일부는 스타터로 구독 가능합까 | F74: FALSE
A75: 6976cc6bc562a95cafde | B75: manager | C75: 594863 | D75: 46048.61 | E75: 안녕하세요 고객님 ☺️ 고위드 김일경 매니저입니다. 해당 내용 내부에서 검토가 필요한 상황인데요! 담당자님께 유선 또는 메일로 회신 드리고자 합니다. miyu@mwd.kr 로 안내 도와드릴까요? 유선 번호도 남겨 주시면 감사 드립니다! | F75: FALSE
A76: 6976cc6bc562a95cafde | B76: manager | C76: 594863 | D76: 46049.6 | E76: 메일로 전달 드려 이번 상담은 여기서 종료하도록 하겠습니다. 다른 문의가 있으시면 새로운 창에서 문의 부탁드립니다. 좋은 하루 되시길 바랍니다 :) | F76: FALSE
A77: 6976cf73cb53e553fa96 | B77: user | C77: 695ca774b479cd296de4 | D77: 46048.473 | E77: 매니저님, 계정 갯수 파악이 잘못되어서 확정하고 다시 리셀러 고위드로 진행하려고요. 사용하지 않는 계정을 파악 중입니다. 여러가지 다른 문의도 있어서 전화 한번 부탁드려도 될는지요? 01093628321 감사합니다. 김대근 드림 2026. 1. 26. 오전 11:17, 고위드 김일경 매니저 <team@gowid.mail.channel.io> 작성: 안녕하세요 김대근님 ☺️ 고위드 김일경 매니저입니다. leanonme.co.kr 도메인 전환 가능 여부 내부에서 빠르게 검토하여 안내 드리겠습니다. 관련하여, 다시 구글로 재전환을 하시는 이유가 어떻게 되시는지 알 수 있을까요? 더 많은 도움을 드리기 위해 여쭙습니다. 감사합니다. 채널톡으로 보냄 | F77: FALSE
A78: 6976cf73cb53e553fa96 | B78: manager | C78: 594863 | D78: 46048.487 | E78: 유선으로 안내 완료 1. GWS 요금제 변경 이전 철회 가능 여부를 구글에 문의하는 것으로 응대 2. 이후, 답변 받은 내용 메일로 전달 드리는 것으로 진행 | F78: TRUE
A79: 6976d18fd1ad3fad2ac6 | B79: user | C79: 66a32e6f5c2687d0a1e3 | D79: 46048.479 | F79: FALSE
A80: 6976d18fd1ad3fad2ac6 | B80: user | C80: 66a32e6f5c2687d0a1e3 | D80: 46048.479 | E80: 네 맞습니다 | F80: FALSE
A81: 6976d18fd1ad3fad2ac6 | B81: user | C81: 66a32e6f5c2687d0a1e3 | D81: 46048.481 | E81: 오류 뜹니다 비밀번호 재설정필요해요 | F81: FALSE
A82: 6976d18fd1ad3fad2ac6 | B82: manager | C82: 574085 | D82: 46048.482 | E82: 예은님 안녕하세요, 고위드입니다. 서비스 이용에 불편을 드려 죄송합니다. 비밀번호는 https://www.gowid.com/login/search2 에서 재설정 가능하십니다만, 보내주신 캡쳐 화면은 해당 링크로 접속하셨을 때 화면이실까요? | F82: FALSE
A83: 6976d18fd1ad3fad2ac6 | B83: manager | C83: 574085 | D83: 46048.485 | E83: 예은님 제가 추가적으로 확인해본 결과, 해당 메일 계정으로 고위드 가입이 안 되어 계신 것으로 확인됩니다. ye.**@wave******.live 로 고위드 계정 가입이 되어 계십니다. 해당 계정으로 비빌번호 재설정 확인 부탁드립니다! (개인정보 보호를 위하여 일부 마스킹 된 계정으로 전달 드립니다.) | F83: FALSE
A84: 6976d18fd1ad3fad2ac6 | B84: user | C84: 66a32e6f5c2687d0a1e3 | D84: 46048.486 | E84: 법인이 달라서요 | F84: FALSE
A85: 6976d18fd1ad3fad2ac6 | B85: user | C85: 66a32e6f5c2687d0a1e3 | D85: 46048.486 | E85: 웨이브로는 로그인이되는데 웨이브 법인과 | F85: FALSE
A86: 6976d18fd1ad3fad2ac6 | B86: user | C86: 66a32e6f5c2687d0a1e3 | D86: 46048.486 | E86: 주식회사 포이저로 로그인을 해야합니다. 회원가입은 되어있다고 뜨고요. cs@poiser.kr 로요 | F86: FALSE
A87: 6976d18fd1ad3fad2ac6 | B87: manager | C87: 574085 | D87: 46048.487 | E87: 아 현재 문의주시고 계시는 계정이 웨이브스튜디오라이브 주식회사 여서 제가 해당 법인으로 확인 도와드렸습니다. | F87: FALSE
A88: 6976d18fd1ad3fad2ac6 | B88: user | C88: 66a32e6f5c2687d0a1e3 | D88: 46048.487 | E88: 넵넵 | F88: FALSE
A89: 6976d18fd1ad3fad2ac6 | B89: manager | C89: 574085 | D89: 46048.487 | E89: 잠시만 기다려주시면 내부적으로도 한 번 확인을 해보겠습니다. | F89: FALSE
A90: 6976d18fd1ad3fad2ac6 | B90: user | C90: 66a32e6f5c2687d0a1e3 | D90: 46048.487 | E90: 넵 ! | F90: FALSE
A91: 6976d18fd1ad3fad2ac6 | B91: manager | C91: 574085 | D91: 46048.487 | E91: 비밀번호는 https://www.gowid.com/login/search2 에서 재설정 가능하십니다만, 보내주신 캡쳐 화면은 해당 링크로 접속하셨을 때 화면이실까요? | F91: FALSE
A92: 6976d18fd1ad3fad2ac6 | B92: user | C92: 66a32e6f5c2687d0a1e3 | D92: 46048.487 | E92: 네 맞습니다 | F92: FALSE
A93: 6976d18fd1ad3fad2ac6 | B93: user | C93: 66a32e6f5c2687d0a1e3 | D93: 46048.487 | E93: 주신링크로 해도 오류뜨네요 | F93: FALSE
A94: 6976d18fd1ad3fad2ac6 | B94: manager | C94: 574085 | D94: 46048.49 | E94: 주식회사 포이저 사업자등록번호 말씀 한 번 부탁드립니다! | F94: FALSE
A95: 6976d18fd1ad3fad2ac6 | B95: user | C95: 66a32e6f5c2687d0a1e3 | D95: 46048.497 | E95: 8858103843 | F95: FALSE
A96: 6976d18fd1ad3fad2ac6 | B96: manager | C96: 574085 | D96: 46048.5 | E96: 주식회사 포이저의 이메일은 cs@wave******.live로 확인되십니다. 해당 메일 주소로 비밀번호 재설정 확인 부탁드립니다. 감사합니다. | F96: FALSE
A97: 6976d18fd1ad3fad2ac6 | B97: user | C97: 66a32e6f5c2687d0a1e3 | D97: 46048.502 | E97: 감사합니다 !! | F97: FALSE
A98: 6976d18fd1ad3fad2ac6 | B98: manager | C98: 574085 | D98: 46048.503 | E98: 감사합니다. 이번 상담은 여기서 종료하도록 하겠습니다. 다른 문의가 있으시면 새로운 창에서 문의 부탁드립니다. 좋은 하루 되시길 바랍니다 :) | F98: FALSE
A99: 6976d61d254e45e36801 | B99: user | C99: 696dd855bbf22f70b618 | D99: 46048.493 | E99: 안녕하세요. 고위드 통하여 최초로 카드 발급하려고 합니다, 1. 법인용 법인카드로 교통카드만 하게 카드 6장 2. 법인용 법인카드 일반카드 2장 우선 저렇게 신청하려고 하는데 교통카드만 이용할 수 있는 카드를 신청할 수가 있을까요? | F99: FALSE
A100: 6976d61d254e45e36801 | B100: user | C100: 696dd855bbf22f70b618 | D100: 46048.667 | F100: FALSE
...

Sheet User data
A1: id | B1: name | C1: profile.name | D1: profile.authorities | E1: profile.companyname | F1: profile.corp_number | G1: profile.coregroup | H1: profile.profile | I1: tags | J1: profile.email | K1: profile.mobileNumber | L1: profile.landlineNumber | M1: profile.description | N1: profile.firstName | O1: profile.lastName | P1: memberId | Q1: member | R1: sessionsCount | S1: city | T1: province | U1: country | V1: timeZone | W1: createdAt | X1: hasPushToken | Y1: language | Z1: lastSeenAt | AA1: profile.회사명 | AB1: mobile.appName | AC1: mobile.appVersion | AD1: mobile.device | AE1: mobile.lastSeenAt | AF1: mobile.os | AG1: mobile.osName | AH1: mobile.sessionsCount | AI1: unsubscribeEmail | AJ1: unsubscribeTexting | AK1: updatedAt | AL1: web.browser | AM1: web.browserName | AN1: web.device | AO1: web.lastSeenAt | AP1: web.os | AQ1: web.osName | AR1: web.sessionsCount | AS1: profile.lastCheckoutCompletedAt | AT1: profile.profileuserid | AU1: profile.referrer | AV1: profile.utmCampaign | AW1: profile.utmContent | AX1: profile.utmMedium | AY1: profile.utmSource | AZ1: profile.utmTerm | BA1: profile.kakaoProfileAgree | BB1: profile.ageRange | BC1: profile.birthday | BD1: profile.gender | BE1: hasChat | BF1: profile.lastUtmSource | BG1: profile.lastUtmMedium | BH1: profile.lastUtmCampaign | BI1: profile.lastUtmContent | BJ1: profile.lastUtmTerm | BK1: profile.lastReferrer | BL1: userImportTags
A2: 66dea44d813d143c976f | B2: 정재식 | C2: 정재식 | D2: EXPENSE:일반 멤버 / SUBSCRIPTION:구독 총괄 관리자 / CARD:일반 멤버 / FUEL:일반 멤버 | E2: 모비두 주식회사 (Mobidoo) | F2: 120-88-01596 | I2: 비회원 | J2: jace@mobidoo.co.kr | P2: 2085710732 | Q2: TRUE | R2: 340 | S2: 서울시 송파구 | U2: KR | V2: Asia/Seoul | W2: 2024-09-09T07:31:25.532Z | X2: FALSE | Y2: ko | Z2: 2026-02-20T04:51:44.003Z | AB2: com.gowid.expense | AC2: 2.8.4 | AD2: Apple iPhone | AE2: 2026-02-12T05:05:21.250Z | AF2: iOS 26.2.1 | AG2: iOS | AH2: 13 | AI2: FALSE | AJ2: FALSE | AK2: 2026-02-20T04:51:44.004Z | AL2: Chrome 145 | AM2: Chrome | AN2: Desktop | AO2: 2026-02-20T04:51:44.003Z | AP2: Windows NT ?? | AQ2: Windows NT | AR2: 327 | AU2: https://gowidsub.imweb.me/ | AV2: authority-01-2026 | AW2: gowid-card-image | AX2: paid-search | AY2: google | AZ2: 법인카드 | BE2: TRUE | BF2: google | BG2: paid-search | BH2: authority-01-2026 | BI2: gowid-card-image | BJ2: 법인카드 | BK2: https://www.google.com/
A3: 67e4dbda6a1c3cbc9018 | B3: 김시하(Fia) | C3: 김시하(Fia) | D3: EXPENSE:슈퍼관리자 / SUBSCRIPTION:구독 총괄 관리자 / CARD:슈퍼관리자 | E3: 주식회사 스위트스팟 | F3: 846-86-00225 | I3: 기가입회원/관리자/기존, 핵심고객(8월), 코어그룹, 코어그룹(12월) | J3: fiakim@sweetspot.co.kr | K3: =+821095736591 -> 821095736591 | P3: 111347732 | Q3: TRUE | R3: 198 | S3: 서울시 영등포구 | U3: KR | V3: Asia/Seoul | W3: 2025-03-27T05:02:18.434Z | X3: FALSE | Y3: ko | Z3: 2026-02-15T01:16:58.867Z | AB3: com.gowid.expense | AC3: 2.8.4 | AD3: Apple iPhone | AE3: 2026-02-14T07:20:51.476Z | AF3: iOS 18.7.1 | AG3: iOS | AH3: 9 | AI3: FALSE | AJ3: FALSE | AK3: 2026-02-15T01:16:58.868Z | AL3: Edge 144 | AM3: Edge | AN3: Desktop | AO3: 2026-02-15T01:16:58.867Z | AP3: Windows >=10 | AQ3: Windows NT | AR3: 189 | AU3: https://payment-gateway.tosspayments.com/ | BE3: TRUE | BK3: https://payment-gateway.tosspayments.com/
A4: 66f527f368aa3851799c | B4: 한재희 | C4: 한재희 | D4: EXPENSE:슈퍼관리자 / CARD:슈퍼관리자 | E4: 주식회사 호아파트너스 | F4: 650-86-01021 | J4: jh.han@eatech.kr | K4: =+821026927481 -> 821026927481 | P4: 2085747850 | Q4: TRUE | R4: 59 | S4: 서울시 강서구 | U4: KR | V4: Asia/Seoul | W4: 2024-09-26T09:22:59.428Z | X4: FALSE | Y4: ko | Z4: 2026-02-13T08:09:44.046Z | AI4: FALSE | AJ4: FALSE | AK4: 2026-02-13T08:09:44.047Z | AL4: Chrome 144 | AM4: Chrome | AN4: Apple Macintosh | AO4: 2026-02-13T08:09:44.046Z | AP4: Mac OS >=10.15.7 | AQ4: Mac OS | AR4: 59 | AU4: https://www.google.com/ | BE4: TRUE | BK4: https://www.google.com/ | BL4: 2025_11_11_channcel_talk_user
A5: 697c660d7bc0033871c1 | B5: 전기범 | C5: 전기범 | D5: CARD:슈퍼관리자 | E5: 주식회사 씨앤디 | F5: 858-87-01942 | I5: 비회원 | J5: cnd3700@cnd.ai | K5: =+821058510346 -> 821058510346 | P5: 108835543 | Q5: TRUE | R5: 1 | S5: 인천시 미추홀구 | U5: KR | V5: Asia/Seoul | W5: 2026-01-30T08:04:29.506Z | X5: FALSE | Y5: ko | Z5: 2026-01-30T08:04:29.506Z | AI5: FALSE | AJ5: FALSE | AK5: 2026-01-30T08:07:38.900Z | AL5: Chrome 144 | AM5: Chrome | AN5: Desktop | AO5: 2026-01-30T08:04:29.506Z | AP5: Windows NT ?? | AQ5: Windows NT | AR5: 1 | BE5: TRUE
A6: 670f25d79ec63a60565b | B6: 김선중 | C6: 김선중 | D6: EXPENSE:슈퍼관리자 / SUBSCRIPTION:구독 총괄 관리자 / CARD:슈퍼관리자 | E6: 버킷히어로(주) | F6: 561-88-03382 | I6: 기가입회원/관리자/신규, 기가입회원/관리자/기존 | J6: kevin.kim@buckethero.net | K6: =+821055252890 -> 821055252890 | P6: 110205691 | Q6: TRUE | R6: 46 | S6: 광주시 서구 | U6: KR | V6: Asia/Seoul | W6: 2024-10-16T02:32:55.649Z | X6: FALSE | Y6: ko | Z6: 2026-02-05T01:45:18.325Z | AI6: FALSE | AJ6: FALSE | AK6: 2026-02-05T01:45:18.326Z | AL6: Chrome 144 | AM6: Chrome | AN6: Apple Macintosh | AO6: 2026-02-05T01:45:18.325Z | AP6: Mac OS >=10.15.7 | AQ6: Mac OS | AR6: 46 | AU6: https://www.google.com/ | BE6: TRUE | BK6: https://www.google.com/ | BL6: 2025_11_11_channcel_talk_user
A7: 66d5bcc2bccdaa760422 | B7: 이재훈 | C7: 이재훈 | D7: EXPENSE:슈퍼관리자 / FUEL:슈퍼관리자 / SUBSCRIPTION:구독 총괄 관리자 / CARD:슈퍼관리자 | E7: 주식회사 콘스탄트 | F7: 517-87-01809 | I7: 기가입회원/관리자/기존 | J7: jaehoon@theconst.kr | P7: 2085707427 | Q7: TRUE | R7: 109 | S7: 서울시 마포구 | U7: KR | V7: Asia/Seoul | W7: 2024-09-02T13:25:22.773Z | X7: FALSE | Y7: ko | Z7: 2026-02-12T03:25:24.519Z | AI7: FALSE | AJ7: FALSE | AK7: 2026-02-12T03:25:24.520Z | AL7: Chrome 144 | AM7: Chrome | AN7: Desktop | AO7: 2026-02-12T01:27:02.211Z | AP7: Windows NT ?? | AQ7: Windows NT | AR7: 109 | AU7: https://www.google.com/ | BE7: TRUE | BK7: https://www.google.com/
A8: 6704c9ffda4cc452af14 | B8: 전혜림 | C8: 전혜림 | D8: EXPENSE:슈퍼관리자 / SUBSCRIPTION:구독 총괄 관리자 / CARD:슈퍼관리자 | E8: 주식회사 어글리랩 | F8: 524-86-02323 | I8: 기가입회원/관리자/기존 | J8: mayj@uglee.io | K8: =+821027901704 -> 821027901704 | P8: 111104222 | Q8: TRUE | R8: 474 | S8: 서울시 강남구 | U8: KR | V8: Asia/Seoul | W8: 2024-10-08T05:58:23.893Z | X8: FALSE | Y8: ko | Z8: 2026-02-20T04:35:48.215Z | AB8: com.gowid.expense | AC8: 2.8.4 | AD8: Samsung SM-S901N | AE8: 2026-02-15T05:35:21.157Z | AF8: Android 16 | AG8: Android | AH8: 4 | AI8: FALSE | AJ8: FALSE | AK8: 2026-02-20T04:35:48.216Z | AL8: Chrome 145 | AM8: Chrome | AN8: Desktop | AO8: 2026-02-20T04:35:48.215Z | AP8: Windows NT ?? | AQ8: Windows NT | AR8: 470 | AU8: https://search.naver.com/search.naver?sm=tab_hty.top&where=nexearch&ssc=tab.nx.all&query=%EA%B3%A0%EC%9C%84%EB%93%9C&oquery=%EA%B0%9C%EC%9D%B8%EB%B2%95%EC%9D%B8%EC%B9%B4%EB%93%9C&tqi=iwg5VsqVOsVssS1mLswssssssLV-064300 | AY8: blog | BE8: TRUE | BK8: https://gowidsub.imweb.me/
A9: 659cd039610cffa631f0 | B9: 박정웅 | C9: 박정웅 | D9: EXPENSE:슈퍼관리자 / CARD:슈퍼관리자 | E9: 주식회사 엔스프링 | F9: 119-86-45571 | I9: 기가입회원/관리자/신규, 기가입회원/관리자/기존 | J9: sevocard@sorizava.co.kr | K9: =+821047669733 -> 821047669733 | P9: 2085878501 | Q9: TRUE | R9: 46 | S9: 경기도 의정부시 | U9: KR | V9: Asia/Seoul | W9: 2024-01-09T04:48:57.396Z | X9: FALSE | Y9: ko | Z9: 2026-02-20T02:17:12.553Z | AI9: FALSE | AJ9: FALSE | AK9: 2026-02-20T02:17:12.554Z | AL9: Edge 145 | AM9: Edge | AN9: Desktop | AO9: 2026-02-20T02:17:12.553Z | AP9: Windows >=10 | AQ9: Windows NT | AR9: 46 | AU9: https://timbel.hanbiro.net/ | BE9: TRUE | BK9: https://docs.channel.io/ | BL9: 2025_11_11_channcel_talk_user
A10: 6567f0cce1fd1a752da6 | B10: 김가희 | C10: 김가희 | D10: EXPENSE:카드 총괄관리자 / CARD:카드 총괄관리자 | E10: 주식회사 디카르고 | F10: 419-81-02593 | I10: 기가입회원/관리자/기존 | J10: ghkim@dkargo.io | K10: =+821022652604 -> 821022652604 | P10: 108798736 | Q10: TRUE | R10: 2187 | S10: 서울시 강남구 | U10: KR | V10: Asia/Seoul | W10: 2023-11-30T02:17:48.925Z | X10: FALSE | Y10: ko | Z10: 2026-02-20T04:48:44.194Z | AB10: com.gowid.expense | AC10: 2.8.4 | AD10: Apple iPhone | AE10: 2026-02-19T15:25:54.308Z | AF10: iOS 26.2.1 | AG10: iOS | AH10: 219 | AI10: FALSE | AJ10: FALSE | AK10: 2026-02-20T04:48:44.195Z | AL10: Chrome 144 | AM10: Chrome | AN10: Desktop | AO10: 2026-02-20T04:48:44.194Z | AP10: Windows NT ?? | AQ10: Windows NT | AR10: 1968 | AU10: https://www.google.com/ | BE10: TRUE | BK10: https://search.naver.com/
A11: 677c706e82ccffebf4fc | B11: 정승익 | C11: 정승익 | D11: EXPENSE:슈퍼관리자 / CARD:슈퍼관리자 | E11: 아티움그룹 주식회사 | F11: 677-88-02368 | J11: cole0914@naver.com | K11: =+821095622198 -> 821095622198 | P11: 109016472 | Q11: TRUE | R11: 8 | S11: 서울시 마포구 | U11: KR | V11: Asia/Seoul | W11: 2025-01-07T00:08:14.535Z | X11: FALSE | Y11: ko | Z11: 2026-02-14T01:31:21.930Z | AI11: FALSE | AJ11: FALSE | AK11: 2026-02-14T01:31:21.931Z | AL11: Chrome 145 | AM11: Chrome | AN11: Desktop | AO11: 2026-02-14T01:31:21.930Z | AP11: Windows NT ?? | AQ11: Windows NT | AR11: 8 | AU11: https://search.naver.com/search.naver?ie=UTF-8&query=%EA%B3%A0%EC%9C%84%EB%93%9C&sm=chr_hty | AV11: card-apply | AW11: PC-light-251117-NBS-V1 | AX11: paid-search | AY11: naver | AZ11: 고위드 | BE11: TRUE | BF11: naver | BG11: paid-search | BH11: card-apply | BI11: PC-light-251117-NBS-V1 | BJ11: 고위드 | BK11: https://search.naver.com/ | BL11: 2025_11_11_channcel_talk_user
A12: 6995e3139d837d45c49f | B12: 지니 217 | P12: 12f84356-4872-442f-a003-481458c6e03a | Q12: FALSE | R12: 1 | S12: 서울시 성북구 | U12: KR | V12: Asia/Seoul | W12: 2026-02-18T16:04:35.644Z | X12: FALSE | Y12: ko | Z12: 2026-02-18T16:04:35.644Z | AI12: FALSE | AJ12: FALSE | AK12: 2026-02-18T16:04:35.644Z | AL12: Chrome 145 | AM12: Chrome | AN12: Android Mobile | AO12: 2026-02-18T16:04:35.644Z | AP12: Android ?? | AQ12: Android | AR12: 1 | AU12: https://www.google.com/ | BE12: TRUE | BK12: https://www.google.com/
A13: 67ff486731e439b1d270 | B13: 김산회 | C13: 김산회 | D13: EXPENSE:슈퍼관리자 / CARD:슈퍼관리자 | E13: 주식회사 굿컨설팅그룹 | F13: 525-87-00418 | I13: 기가입회원/관리자/기존 | J13: james.kim@goodconsulting.co.kr | K13: =+821044659835 -> 821044659835 | P13: 111387286 | Q13: TRUE | R13: 144 | S13: 경기도 과천시 | U13: KR | V13: Asia/Seoul | W13: 2025-04-16T06:04:23.204Z | X13: FALSE | Y13: ko | Z13: 2026-02-12T06:04:23.151Z | AI13: FALSE | AJ13: FALSE | AK13: 2026-02-12T06:04:23.152Z | AL13: Chrome 144 | AM13: Chrome | AN13: Apple Macintosh | AO13: 2026-02-12T06:04:23.151Z | AP13: Mac OS >=10.15.7 | AQ13: Mac OS | AR13: 144 | AU13: https://www.google.com/ | AV13: authority-01-2026 | AW13: gowid-card-image | AX13: paid-search | AY13: google | AZ13: 법인카드 | BE13: TRUE | BF13: google | BG13: paid-search | BH13: authority-01-2026 | BI13: gowid-card-image | BJ13: 법인카드 | BK13: https://www.google.com/ | BL13: 2025_11_11_channcel_talk_user
A14: 697f58630b8b911f2f5a | B14: 다트 445 | P14: 73c08cab-7ff0-41c0-946d-4f102d4159dd | Q14: FALSE | R14: 4 | S14: 서울시 중구 | U14: KR | V14: Asia/Seoul | W14: 2026-02-01T13:42:59.047Z | X14: FALSE | Y14: ko | Z14: 2026-02-09T10:09:23.634Z | AI14: FALSE | AJ14: FALSE | AK14: 2026-02-09T10:09:23.635Z | AL14: Chrome 145.0.7632.41 | AM14: Chrome | AN14: Apple iPhone | AO14: 2026-02-09T10:09:23.634Z | AP14: iOS 26.2.1 | AQ14: iOS | AR14: 4 | AV14: 120242291175170606 | AW14: 120242291175200606 | AX14: paid | AY14: ig | AZ14: 120242291175180606 | BE14: TRUE | BF14: ig | BG14: social | BH14: 120242291175170606 | BI14: link_in_bio | BJ14: 120242291175180606
A15: 6971d94bc3ded889e1b9 | B15: 한종빈 | C15: 한종빈 | D15: CARD:슈퍼관리자 / SUBSCRIPTION:구독 총괄 관리자 / EXPENSE:슈퍼관리자 | E15: 주식회사 라디우스랩 | F15: 567-87-02875 | I15: 기가입회원/관리자/신규, 기가입회원/소지자 | J15: stompesi@theradius.xyz | K15: =+821041920787 -> 821041920787 | P15: 122956855 | Q15: TRUE | R15: 37 | S15: 서울시 송파구 | U15: KR | V15: Asia/Seoul | W15: 2026-01-22T08:01:15.802Z | X15: FALSE | Y15: ko | Z15: 2026-02-20T03:17:43.623Z | AB15: com.gowid.expense | AC15: 2.8.4 | AD15: Samsung SM-F966N | AE15: 2026-02-20T03:17:43.623Z | AF15: Android 16 | AG15: Android | AH15: 5 | AI15: FALSE | AJ15: FALSE | AK15: 2026-02-20T03:17:43.623Z | AL15: Chrome 144 | AM15: Chrome | AN15: Apple Macintosh | AO15: 2026-02-20T01:42:14.453Z | AP15: Mac OS >=10.15.7 | AQ15: Mac OS | AR15: 32 | AU15: https://www.google.com/ | BE15: TRUE | BK15: https://www.google.com/
A16: 67217a30884027249f64 | B16: 퍼스트캔버스 | C16: 퍼스트캔버스 | D16: EXPENSE:슈퍼관리자 / CARD:슈퍼관리자 | E16: 주식회사 디에프코퍼레이션 | F16: 808-86-00446 | I16: 기가입회원/관리자/기존, 코어그룹(12월) | J16: tax@firstcanvas.co.kr | K16: =+821023180446 -> 821023180446 | P16: 114618587 | Q16: TRUE | R16: 360 | S16: 서울시 마포구 | U16: KR | V16: Asia/Seoul | W16: 2024-10-30T00:13:36.558Z | X16: FALSE | Y16: ko | Z16: 2026-02-20T03:47:10.986Z | AB16: com.gowid.expense | AC16: 2.8.4 | AD16: Samsung SM-F766N | AE16: 2026-02-03T05:12:16.006Z | AF16: Android 16 | AG16: Android | AH16: 2 | AI16: FALSE | AJ16: FALSE | AK16: 2026-02-20T03:47:10.986Z | AL16: Edge 145 | AM16: Edge | AN16: Desktop | AO16: 2026-02-20T03:47:10.986Z | AP16: Windows >=10 | AQ16: Windows NT | AR16: 358 | AU16: https://www.google.com/ | BE16: TRUE | BK16: https://www.google.com/
A17: 670367117c4099b897f1 | B17: Jiny | C17: Jiny | D17: EXPENSE:슈퍼관리자 / CARD:슈퍼관리자 | E17: 주식회사 마크비전코리아 | F17: 490-81-01666 | I17: 기가입회원/관리자/기존 | J17: jiny.jang@marqvision.com | K17: =+821020383139 -> 821020383139 | P17: 111199985 | Q17: TRUE | R17: 364 | S17: 서울시 강남구 | U17: KR | V17: Asia/Seoul | W17: 2024-10-07T04:44:01.509Z | X17: FALSE | Y17: ko | Z17: 2026-02-13T07:20:46.746Z | AB17: com.gowid.expense | AC17: 2.8.4 | AD17: Apple iPhone | AE17: 2026-02-12T04:36:51.597Z | AF17: iOS 26.1 | AG17: iOS | AH17: 30 | AI17: FALSE | AJ17: FALSE | AK17: 2026-02-13T07:20:46.747Z | AL17: Firefox 147.0 | AM17: Firefox | AN17: Apple Macintosh | AO17: 2026-02-13T07:20:46.746Z | AP17: Mac OS >=10.15.7 | AQ17: Mac OS | AR17: 334 | BE17: TRUE
A18: 6996c313ed0bfe931579 | B18: 풋볼 754 | P18: 738f7f9b-8968-4158-a908-dd8c8c2e22a1 | Q18: FALSE | R18: 2 | S18: 서울시 강남구 | U18: KR | V18: Asia/Seoul | W18: 2026-02-19T08:00:19.971Z | X18: FALSE | Y18: ko | Z18: 2026-02-19T08:34:12.127Z | AI18: FALSE | AJ18: FALSE | AK18: 2026-02-19T08:34:12.127Z | AL18: Chrome 144 | AM18: Chrome | AN18: Desktop | AO18: 2026-02-19T08:34:12.127Z | AP18: Windows NT ?? | AQ18: Windows NT | AR18: 2 | AU18: https://www.google.com/ | BE18: TRUE | BK18: https://www.google.com/
A19: 66fd348332a7248106d9 | B19: 조윤주 | C19: 조윤주 | D19: EXPENSE:슈퍼관리자 / SUBSCRIPTION:구독 총괄 관리자 / CARD:슈퍼관리자 | E19: (주)자비스앤빌런즈 | F19: 158-86-00171 | I19: 기가입회원/관리자/기존, 핵심고객(8월), 코어그룹(12월) | J19: yunjoo@jobis.co | K19: =+821052308627 -> 821052308627 | P19: 110126994 | Q19: TRUE | R19: 986 | S19: 서울시 강남구 | U19: KR | V19: Asia/Seoul | W19: 2024-10-02T11:54:43.207Z | X19: FALSE | Y19: ko | Z19: 2026-02-19T07:12:41.571Z | AB19: com.gowid.expense | AC19: 2.8.4 | AD19: Apple iPhone | AE19: 2026-02-18T12:31:43.441Z | AF19: iOS 18.5 | AG19: iOS | AH19: 93 | AI19: TRUE | AJ19: TRUE | AK19: 2026-02-19T07:12:41.572Z | AL19: Chrome 144 | AM19: Chrome | AN19: Desktop | AO19: 2026-02-19T07:12:41.571Z | AP19: Windows NT ?? | AQ19: Windows NT | AR19: 893 | AU19: https://search.naver.com/search.naver?where=nexearch&sm=top_hty&fbm=0&ie=utf8&query=%EA%B3%A0%EC%9C%84%EB%93%9C | BE19: TRUE | BK19: https://search.naver.com/search.naver?where=nexearch&sm=top_hty&fbm=0&ie=utf8&query=%EA%B3%A0%EC%9C%84%EB%93%9C&ackey=ol7i18k7
A20: 6551dbb105b66add6f86 | B20: 임찬솔 | C20: 임찬솔 | D20: EXPENSE:슈퍼관리자 / CARD:슈퍼관리자 / SUBSCRIPTION:구독 총괄 관리자 | E20: 주식회사 열다컴퍼니 | F20: 793-87-02566 | H20: 신한 | I20: 기가입회원/관리자/기존 | J20: contact@yolda.kr | K20: =+821089585520 -> 821089585520 | P20: 116707327 | Q20: TRUE | R20: 290 | S20: 서울시 광진구 | U20: KR | V20: Asia/Seoul | W20: 2023-11-13T08:17:53.023Z | X20: FALSE | Y20: ko | Z20: 2026-02-19T14:45:54.902Z | AB20: com.gowid.expense | AC20: 2.7.3 | AD20: Samsung SM-S908N | AE20: 2026-01-28T04:00:09.635Z | AF20: Android 16 | AG20: Android | AH20: 2 | AI20: FALSE | AJ20: FALSE | AK20: 2026-02-19T14:45:54.904Z | AL20: Chrome 144 | AM20: Chrome | AN20: Apple Macintosh | AO20: 2026-02-19T14:45:54.902Z | AP20: Mac OS >=10.15.7 | AQ20: Mac OS | AR20: 288 | AU20: https://www.google.com/ | AV20: authority-01-2026 | AW20: gowid-card-image | AX20: paid-search | AY20: google | AZ20: 법인카드 | BE20: TRUE | BF20: google | BG20: paid-search | BH20: authority-01-2026 | BI20: gowid-card-image | BJ20: 법인카드 | BK20: https://www.google.com/
A21: 65921f1b05254de39656 | B21: 정민진 | C21: 정민진 | D21: EXPENSE:슈퍼관리자 / SUBSCRIPTION:구독 총괄 관리자 / CARD:슈퍼관리자 | E21: 주식회사 데이탄소프트 | F21: 326-88-01855 | I21: 기가입회원/관리자/기존, 비회원 | J21: support@datansoft.com | K21: =+821022249844 -> 821022249844 | P21: 114654591 | Q21: TRUE | R21: 177 | S21: 제주도 제주시 | U21: KR | V21: Asia/Seoul | W21: 2024-01-01T02:10:35.024Z | X21: FALSE | Y21: ko | Z21: 2026-02-19T03:03:16.975Z | AB21: com.gowid.expense | AC21: 2.8.4 | AD21: Samsung SM-S926N | AE21: 2026-02-19T03:03:16.975Z | AF21: Android 16 | AG21: Android | AH21: 50 | AI21: FALSE | AJ21: FALSE | AK21: 2026-02-19T03:03:16.976Z | AL21: Chrome 144 | AM21: Chrome | AN21: Desktop | AO21: 2026-02-09T00:33:06.203Z | AP21: Windows NT ?? | AQ21: Windows NT | AR21: 127 | AU21: https://corp.lottecard.co.kr/ | BE21: TRUE | BK21: https://www.bing.com/
A22: 67809d4aa7314954c090 | B22: young | C22: young | D22: EXPENSE:슈퍼관리자 / SUBSCRIPTION:구독 총괄 관리자 / CARD:슈퍼관리자 | E22: 주식회사 마이프랜차이즈 | F22: 584-87-01610 | I22: 기가입회원/관리자/신규, 기가입회원/관리자/기존 | J22: dayoung@myfranchise.kr | P22: 115593138 | Q22: TRUE | R22: 66 | S22: 서울시 서초구 | U22: KR | V22: Asia/Seoul | W22: 2025-01-10T04:08:42.684Z | X22: FALSE | Y22: ko | Z22: 2026-02-18T23:52:53.665Z | AB22: com.gowid.expense | AC22: 2.8.4 | AD22: Samsung SM-F956N | AE22: 2026-02-13T05:26:07.041Z | AF22: Android 16 | AG22: Android | AH22: 22 | AI22: FALSE | AJ22: FALSE | AK22: 2026-02-18T23:52:53.666Z | AL22: Chrome 145 | AM22: Chrome | AN22: Desktop | AO22: 2026-02-18T23:52:53.665Z | AP22: Windows NT ?? | AQ22: Windows NT | AR22: 44 | AU22: https://payment-gateway.tosspayments.com/ | BE22: TRUE | BK22: https://gowidsub.imweb.me/
A23: 67481f2a7b45d3666f5e | B23: 심상보 | C23: 심상보 | D23: EXPENSE:슈퍼관리자 / SUBSCRIPTION:구독 총괄 관리자 / CARD:슈퍼관리자 | E23: 주식회사 브릿센트(BRITCENT Inc.) | F23: 850-87-01711 | H23: 신한 | I23: 기가입회원/관리자/신규, 기가입회원/관리자/기존 | J23: britcent@britcent.com | K23: =+821049633616 -> 821049633616 | P23: 111202206 | Q23: TRUE | R23: 58 | S23: 서울시 중구 | U23: KR | V23: Asia/Seoul | W23: 2024-11-28T07:43:38.504Z | X23: FALSE | Y23: ko | Z23: 2026-01-31T14:09:41.263Z | AB23: com.gowid.expense | AC23: 2.8.3 | AD23: Apple iPhone | AE23: 2026-01-29T17:43:40.945Z | AF23: iOS 26.1 | AG23: iOS | AH23: 1 | AI23: FALSE | AJ23: FALSE | AK23: 2026-01-31T14:09:41.264Z | AL23: Chrome 144 | AM23: Chrome | AN23: Apple Macintosh | AO23: 2026-01-31T14:09:41.263Z | AP23: Mac OS >=10.15.7 | AQ23: Mac OS | AR23: 57 | AU23: https://www.google.com/ | AY23: blog | BE23: TRUE | BF23: blog | BK23: https://www.google.com/ | BL23: 2025_11_11_channcel_talk_user
A24: 660b9ca16bc23e2402b8 | B24: 박이훈 | C24: 박이훈 | D24: EXPENSE:슈퍼관리자 / CARD:슈퍼관리자 | E24: 주식회사 리훈 (RIHOON CO., LTD.) | F24: 489-88-01777 | I24: 기가입회원/관리자/기존 | J24: rihoon@rihoon.co.kr | K24: =+821027205104 -> 821027205104 | P24: 2085815043 | Q24: TRUE | R24: 235 | S24: 서울시 종로구 | U24: KR | V24: Asia/Seoul | W24: 2024-04-02T05:50:25.441Z | X24: FALSE | Y24: ko | Z24: 2026-02-19T08:11:39.920Z | AI24: FALSE | AJ24: FALSE | AK24: 2026-02-19T08:11:39.921Z | AL24: Chrome 144 | AM24: Chrome | AN24: Desktop | AO24: 2026-02-19T08:11:39.920Z | AP24: Windows NT ?? | AQ24: Windows NT | AR24: 235 | AU24: https://www.google.com/ | AV24: authority-01-2026 | AW24: gowid-card-image | AX24: paid-search | AY24: blog | AZ24: 법인카드 | BE24: TRUE | BF24: google | BG24: paid-search | BH24: authority-01-2026 | BI24: gowid-card-image | BJ24: 법인카드 | BK24: https://www.google.com/
A25: 67369718eee0e307df5c | B25: 이지원 | C25: 이지원 | D25: EXPENSE:슈퍼관리자 / CARD:슈퍼관리자 | E25: 주식회사 미스터아빠 | F25: 448-87-01712 | I25: 기가입회원/관리자/기존, 코어그룹(12월) | J25: jw@papamarket.kr | K25: =+821086910598 -> 821086910598 | P25: 110998233 | Q25: TRUE | R25: 221 | S25: 서울시 강남구 | U25: KR | V25: Asia/Seoul | W25: 2024-11-15T00:34:32.978Z | X25: FALSE | Y25: ko | Z25: 2026-02-04T01:20:53.236Z | AI25: FALSE | AJ25: FALSE | AK25: 2026-02-04T01:20:53.237Z | AL25: Chrome 144 | AM25: Chrome | AN25: Desktop | AO25: 2026-02-04T01:20:53.236Z | AP25: Windows NT ?? | AQ25: Windows NT | AR25: 221 | AU25: https://search.naver.com/search.naver?where=nexearch&sm=top_sug.pre&fbm=0&acr=2&acq=%EA%B3%A0%EC%9C%84%EB%93%9C&qdt=0&ie=utf8&query=%EA%B3%A0%EC%9C%84%EB%93%9C | AV25: authority-01-2026 | AW25: gowid-card-image | AX25: paid-search | AY25: google | AZ25: 법인카드 | BE25: TRUE | BF25: google | BG25: paid-search | BH25: authority-01-2026 | BI25: gowid-card-image | BJ25: 법인카드 | BK25: https://www.google.com/
A26: 66ed202b07d401938433 | B26: 이아름 | C26: 이아름 | D26: EXPENSE:카드 총괄관리자 / SUBSCRIPTION:구독 총괄 관리자 / CARD:카드 총괄관리자 | E26: 주식회사 직진코퍼레이션 | F26: 574-88-01930 | I26: 기가입회원/관리자/기존, 핵심고객(8월) | J26: lar@we-ar.kr | K26: =+821037818443 -> 821037818443 | P26: 111098673 | Q26: TRUE | R26: 117 | S26: 서울시 성동구 | U26: KR | V26: Asia/Seoul | W26: 2024-09-20T07:11:39.032Z | X26: FALSE | Y26: ko | Z26: 2026-02-13T05:50:18.347Z | AI26: FALSE | AJ26: FALSE | AK26: 2026-02-13T05:50:18.348Z | AL26: Chrome 144 | AM26: Chrome | AN26: Desktop | AO26: 2026-02-13T05:50:18.347Z | AP26: Windows NT ?? | AQ26: Windows NT | AR26: 117 | AU26: https://www.google.com/ | BE26: TRUE | BK26: https://www.google.com/
A27: 6982b190b5806a8bc906 | B27: 김규미 | C27: 김규미 | D27: CARD:슈퍼관리자 / EXPENSE:슈퍼관리자 | E27: (주）TGWP | F27: 211-88-10839 | I27: 기가입회원/관리자/신규, 비회원 | J27: kmkim@tgwp.co.kr | K27: =+821081886933 -> 821081886933 | P27: 122946000 | Q27: TRUE | R27: 21 | S27: 서울시 광진구 | U27: KR | V27: Asia/Seoul | W27: 2026-02-04T02:40:16.744Z | X27: FALSE | Y27: ko | Z27: 2026-02-20T00:07:23.083Z | AB27: com.gowid.expense | AC27: 2.8.4 | AD27: Apple iPhone | AE27: 2026-02-12T02:52:24.561Z | AF27: iOS 26.2.1 | AG27: iOS | AH27: 2 | AI27: FALSE | AJ27: FALSE | AK27: 2026-02-20T00:07:23.084Z | AL27: Chrome 145 | AM27: Chrome | AN27: Desktop | AO27: 2026-02-20T00:07:23.083Z | AP27: Windows NT ?? | AQ27: Windows NT | AR27: 19 | AU27: https://search.naver.com/ | AV27: card-apply | AW27: PC-light-251117-NBS-V1 | AX27: paid-search | AY27: naver | AZ27: 고위드 | BE27: TRUE | BF27: naver | BG27: paid-search | BH27: card-apply | BI27: PC-light-251117-NBS-V1 | BJ27: 고위드 | BK27: https://search.naver.com/
A28: 69854caf083aba6bdb0c | B28: 나비 698 | P28: 58fa77ac-0946-4d3c-be4e-9d23f38fdc57 | Q28: FALSE | R28: 7 | S28: 광주시 서구 | U28: KR | V28: Asia/Seoul | W28: 2026-02-06T02:06:39.034Z | X28: FALSE | Y28: ko | Z28: 2026-02-10T07:38:24.400Z | AI28: FALSE | AJ28: FALSE | AK28: 2026-02-10T07:38:24.400Z | AL28: Chrome 144 | AM28: Chrome | AN28: Desktop | AO28: 2026-02-10T07:38:24.400Z | AP28: Windows NT ?? | AQ28: Windows NT | AR28: 7 | AU28: https://blog.gowid.com/ | AV28: workspace-30promotion | AX28: organic-search | AY28: blog | BE28: TRUE | BF28: blog | BG28: organic-search | BH28: workspace-30promotion | BK28: https://www.google.com/
A29: 69945ac2784498e93d8f | B29: 다트 540 | P29: bd7b4b89-a046-4941-9621-cb640fcd3603 | Q29: FALSE | R29: 1 | S29: 서울시 영등포구 | U29: KR | V29: Asia/Seoul | W29: 2026-02-17T12:10:42.492Z | X29: FALSE | Y29: ko | Z29: 2026-02-17T12:10:42.492Z | AI29: FALSE | AJ29: FALSE | AK29: 2026-02-17T12:10:42.492Z | AL29: Edge 145 | AM29: Edge | AN29: Desktop | AO29: 2026-02-17T12:10:42.492Z | AP29: Windows >=10 | AQ29: Windows NT | AR29: 1 | BE29: TRUE
A30: 698e6abe35dc2af1bcf2 | B30: 오진연 | C30: 오진연 | D30: CARD:슈퍼관리자 | E30: (주)쿨스쿨 | F30: 314-86-66749 | J30: konan@coolschool.co.kr | K30: =+821023620570 -> 821023620570 | P30: 122991645 | Q30: TRUE | R30: 9 | S30: 경기도 성남시 분당구 | U30: KR | V30: Asia/Seoul | W30: 2026-02-13T00:05:18.220Z | X30: FALSE | Y30: ko | Z30: 2026-02-19T20:51:38.704Z | AI30: FALSE | AJ30: FALSE | AK30: 2026-02-19T20:51:38.705Z | AL30: Chrome 144 | AM30: Chrome | AN30: Desktop | AO30: 2026-02-19T20:51:38.704Z | AP30: Windows NT ?? | AQ30: Windows NT | AR30: 9 | AU30: https://www.google.com/ | BE30: TRUE | BK30: https://www.google.com/
A31: 679b26c501256631a6b2 | B31: 라로제 어드민 | C31: 라로제 어드민 | D31: EXPENSE:슈퍼관리자 / SUBSCRIPTION:구독 총괄 관리자 / CARD:슈퍼관리자 | E31: 주식회사 라로제코리아 | F31: 433-87-03789 | I31: 기가입회원/관리자/기존 | J31: admin@larosee.co.kr | K31: =+821059239455 -> 821059239455 | P31: 111133823 | Q31: TRUE | R31: 1032 | S31: 서울시 강남구 | U31: KR | V31: Asia/Seoul | W31: 2025-01-30T07:14:13.004Z | X31: FALSE | Y31: ko | Z31: 2026-02-20T01:30:09.939Z | AB31: com.gowid.expense | AC31: 2.8.4 | AD31: Samsung SM-F741N | AE31: 2026-02-18T10:49:14.948Z | AF31: Android 16 | AG31: Android | AH31: 58 | AI31: FALSE | AJ31: FALSE | AK31: 2026-02-20T01:30:09.940Z | AL31: Chrome 145 | AM31: Chrome | AN31: Desktop | AO31: 2026-02-20T01:30:09.939Z | AP31: Windows NT ?? | AQ31: Windows NT | AR31: 974 | AU31: https://www.google.com/ | BE31: TRUE | BK31: https://gowidsub.imweb.me/
A32: 645d7e82ca57ef469aaa | B32: 임수현 | C32: 임수현 | D32: EXPENSE:슈퍼관리자 / SUBSCRIPTION:구독 총괄 관리자 / CARD:슈퍼관리자 | E32: 주식회사 핀케치 | F32: 507-88-01605 | H32: 롯데 | I32: 기가입회원/관리자/기존 | J32: suhyun.lim@fincatch.co.kr | K32: =+821088791466 -> 821088791466 | P32: 2085963213 | Q32: TRUE | R32: 113 | S32: 서울시 영등포구 | U32: KR | V32: Asia/Seoul | W32: 2023-05-11T23:47:14.831Z | X32: FALSE | Y32: ko | Z32: 2026-02-13T03:36:37.346Z | AI32: FALSE | AJ32: FALSE | AK32: 2026-02-13T03:36:37.347Z | AL32: Chrome 144 | AM32: Chrome | AN32: Desktop | AO32: 2026-02-13T03:36:37.346Z | AP32: Windows NT ?? | AQ32: Windows NT | AR32: 113 | AU32: https://www.google.com/ | AV32: authority-01-2026 | AW32: gowid-card-image | AX32: paid-search | AY32: google | AZ32: 법인카드 | BE32: TRUE | BF32: google | BG32: paid-search | BH32: authority-01-2026 | BI32: gowid-card-image | BJ32: 법인카드 | BK32: https://www.google.com/ | BL32: 2025_11_11_channcel_talk_user
A33: 698c39fb61fec13f60b1 | B33: 케이크 828 | P33: 5a68e7c9-22f2-4451-946c-ecba4e708fa9 | Q33: FALSE | R33: 1 | S33: 경기도 시흥시 | U33: KR | V33: Asia/Seoul | W33: 2026-02-11T08:12:43.401Z | X33: FALSE | Y33: ko | Z33: 2026-02-11T08:12:43.401Z | AI33: FALSE | AJ33: FALSE | AK33: 2026-02-11T08:12:43.401Z | AL33: SamsungBrowser 29.0 | AM33: SamsungBrowser | AN33: Samsung Phone | AO33: 2026-02-11T08:12:43.401Z | AP33: Android ?? | AQ33: Android | AR33: 1 | BE33: TRUE
A34: 697b654e15262eb7872a | B34: 전기범 | C34: 전기범 | I34: 비회원 | J34: cnd3700@cnd.ai | K34: =+821058510346 -> 821058510346 | P34: 84b16523-9d4e-46b1-b325-05e90fd6f9db | Q34: FALSE | R34: 7 | S34: 서울시 강남구 | U34: KR | V34: Asia/Seoul | W34: 2026-01-29T13:49:02.086Z | X34: FALSE | Y34: ko | Z34: 2026-02-04T07:27:57.871Z | AI34: FALSE | AJ34: FALSE | AK34: 2026-02-04T07:27:57.872Z | AL34: SamsungBrowser 29.0 | AM34: SamsungBrowser | AN34: Samsung Phone | AO34: 2026-02-04T07:27:57.871Z | AP34: Android ?? | AQ34: Android | AR34: 7 | AU34: https://m.search.naver.com/ | AV34: card-apply | AW34: MO-light-251117-NBS-V1 | AX34: paid-search | AY34: naver | AZ34: 고위드 | BE34: TRUE | BF34: naver | BG34: paid-search | BH34: card-apply | BI34: MO-light-251117-NBS-V1 | BJ34: 고위드 | BK34: https://m.search.naver.com/
A35: 6985a16dc614f51202d0 | B35: 케이크 378 | P35: 05ed8fb8-5637-41ed-a607-5409694012a3 | Q35: FALSE | R35: 1 | S35: 경기도 부천시 원미구 | U35: KR | V35: Asia/Seoul | W35: 2026-02-06T08:08:13.811Z | X35: FALSE | Y35: ko | Z35: 2026-02-06T08:08:13.810Z | AI35: FALSE | AJ35: FALSE | AK35: 2026-02-06T08:08:13.811Z | AL35: Chrome 144 | AM35: Chrome | AN35: Desktop | AO35: 2026-02-06T08:08:13.810Z | AP35: Windows NT ?? | AQ35: Windows NT | AR35: 1 | AU35: https://stibee.com/ | BE35: TRUE | BK35: https://stibee.com/
A36: 677f3220e29b9eac5933 | B36: 전상아 | C36: 전상아 | D36: EXPENSE:슈퍼 관리자 / CARD:슈퍼 관리자 | E36: 주식회사 데이터라이즈 | F36: 259-87-01484 | J36: seongmoo.kim@datarize.ai | K36: =+821099056570 -> 821099056570 | P36: 2085884975 | Q36: TRUE | R36: 2 | S36: 서울시 강남구 | U36: KR | V36: Asia/Seoul | W36: 2025-01-09T02:19:12.927Z | X36: FALSE | Y36: ko | Z36: 2026-02-10T07:36:43.821Z | AI36: FALSE | AJ36: FALSE | AK36: 2026-02-10T07:36:43.822Z | AL36: Chrome 131 | AM36: Chrome | AN36: Desktop | AO36: 2025-01-09T05:39:43.161Z | AP36: Windows NT ?? | AQ36: Windows NT | AR36: 2 | AU36: https://www.google.com/ | BE36: TRUE | BK36: https://www.google.com/ | BL36: 2025_11_11_channcel_talk_user
A37: 6971bb6bde685cd74326 | B37: 최성만 | C37: 최성만 | D37: CARD:슈퍼관리자 / EXPENSE:슈퍼관리자 | E37: 주식회사 바닐라브릿지 | F37: 165-86-00709 | J37: sungman@vanillabridge.com | K37: =+821091817788 -> 821091817788 | P37: 122956858 | Q37: TRUE | R37: 8 | S37: 서울시 마포구 | U37: KR | V37: Asia/Seoul | W37: 2026-01-22T05:53:47.911Z | X37: FALSE | Y37: ko | Z37: 2026-02-19T01:10:09.709Z | AI37: FALSE | AJ37: FALSE | AK37: 2026-02-19T01:10:09.710Z | AL37: Chrome 144 | AM37: Chrome | AN37: Desktop | AO37: 2026-02-19T01:10:09.709Z | AP37: Windows NT ?? | AQ37: Windows NT | AR37: 8 | AU37: https://search.naver.com/ | AV37: card-apply | AW37: PC-light-251117-NBS-V1 | AX37: paid-search | AY37: naver | AZ37: 고위드 | BE37: TRUE | BF37: naver | BG37: paid-search | BH37: card-apply | BI37: PC-light-251117-NBS-V1 | BJ37: 고위드 | BK37: https://search.naver.com/
A38: 67fccd25e4a885744cc9 | B38: 고은별 | C38: 고은별 | D38: EXPENSE:슈퍼관리자 / SUBSCRIPTION:구독 총괄 관리자 / CARD:슈퍼관리자 | E38: 팀스파르타 주식회사 | F38: 783-86-01715 | I38: 기가입회원/관리자/기존, 코어그룹, 코어그룹(12월) | J38: eb.ko@teamsparta.co | K38: =+821032892575 -> 821032892575 | P38: 111387061 | Q38: TRUE | R38: 539 | S38: 서울시 강남구 | U38: KR | V38: Asia/Seoul | W38: 2025-04-14T08:53:57.936Z | X38: FALSE | Y38: ko | Z38: 2026-02-20T03:40:27.969Z | AB38: com.gowid.expense | AC38: 2.8.4 | AD38: Apple iPhone | AE38: 2026-02-14T03:15:22.223Z | AF38: iOS 26.2.1 | AG38: iOS | AH38: 42 | AI38: FALSE | AJ38: FALSE | AK38: 2026-02-20T03:40:27.970Z | AL38: Chrome 145 | AM38: Chrome | AN38: Desktop | AO38: 2026-02-20T03:40:27.969Z | AP38: Windows NT ?? | AQ38: Windows NT | AR38: 497 | AU38: https://www.google.com/ | BE38: TRUE | BK38: https://docs.channel.io/
A39: 67a17f639fd921689bf6 | B39: 임현이 | C39: 임현이 | D39: EXPENSE:카드 총괄관리자 / SUBSCRIPTION:일반 멤버 / CARD:카드 총괄관리자 | E39: 주식회사 에디트콜렉티브 | F39: 318-81-09139 | I39: 기가입회원/관리자/기존 | J39: he.lim@editcollective.io | P39: 111136721 | Q39: TRUE | R39: 476 | S39: 서울시 강남구 | U39: KR | V39: Asia/Seoul | W39: 2025-02-04T02:45:55.654Z | X39: FALSE | Y39: ko | Z39: 2026-02-19T09:08:49.374Z | AB39: com.gowid.expense | AC39: 2.8.4 | AD39: Samsung SM-S937N | AE39: 2026-02-19T04:08:28.827Z | AF39: Android 16 | AG39: Android | AH39: 6 | AI39: FALSE | AJ39: FALSE | AK39: 2026-02-19T09:08:49.375Z | AL39: Chrome 144 | AM39: Chrome | AN39: Desktop | AO39: 2026-02-19T09:08:49.374Z | AP39: Windows NT ?? | AQ39: Windows NT | AR39: 470 | AU39: https://gowid.com/ | BE39: TRUE | BK39: https://search.naver.com/
A40: 691ea28af0c586c99af6 | B40: 구다현 | C40: 구다현 | D40: CARD:슈퍼관리자 / EXPENSE:슈퍼관리자 | E40: (주)바스코리아 | F40: 851-81-02744 | I40: 비회원, 기가입회원/관리자/기존 | J40: amitie47088@bas-korea.com | K40: =+821073524708 -> 821073524708 | P40: 112562359 | Q40: TRUE | R40: 25 | S40: 부산시 강서구 | U40: KR | V40: Asia/Seoul | W40: 2025-11-20T05:09:30.986Z | X40: FALSE | Y40: ko | Z40: 2026-01-26T08:18:24.110Z | AI40: FALSE | AJ40: FALSE | AK40: 2026-01-26T08:18:24.111Z | AL40: Chrome 144 | AM40: Chrome | AN40: Desktop | AO40: 2026-01-26T08:18:24.110Z | AP40: Windows NT ?? | AQ40: Windows NT | AR40: 25 | AU40: https://docs.channel.io/ | BE40: TRUE | BK40: https://www.google.com/
A41: 68ec68659a8535a3b5b4 | B41: 김진희 | C41: 김진희 | D41: EXPENSE:슈퍼관리자 / SUBSCRIPTION:구독 총괄 관리자 / CARD:슈퍼관리자 | E41: 주식회사 위버케어 | F41: 336-87-00652 | I41: 기가입회원/관리자/기존 | J41: genie@weavr.care | P41: 112247633 | Q41: TRUE | R41: 189 | S41: 서울시 강남구 | U41: KR | V41: Asia/Seoul | W41: 2025-10-13T02:48:05.632Z | X41: FALSE | Y41: ko | Z41: 2026-02-20T04:21:33.887Z | AB41: com.gowid.expense | AC41: 2.8.4 | AD41: Apple iPhone | AE41: 2026-02-12T07:50:51.670Z | AF41: iOS 26.2.1 | AG41: iOS | AH41: 8 | AI41: FALSE | AJ41: FALSE | AK41: 2026-02-20T04:21:33.887Z | AL41: Chrome 145 | AM41: Chrome | AN41: Desktop | AO41: 2026-02-20T04:21:33.887Z | AP41: Windows NT ?? | AQ41: Windows NT | AR41: 181 | AU41: https://www.google.com/ | BE41: TRUE | BK41: https://corp.lottecard.co.kr/
A42: 695c656b6c1199ff0ffb | B42: 송미진 | C42: 송미진 | D42: EXPENSE:슈퍼관리자 / CARD:슈퍼관리자 / SUBSCRIPTION:구독 총괄 관리자 | E42: 주식회사 스튜디오오피큐알 | F42: 880-86-03111 | I42: 기가입회원/관리자/신규 | J42: admin@officementary.com | K42: =+821020648726 -> 821020648726 | P42: 122922814 | Q42: TRUE | R42: 45 | S42: 서울시 강남구 | U42: KR | V42: Asia/Seoul | W42: 2026-01-06T01:29:15.442Z | X42: FALSE | Y42: ko | Z42: 2026-02-19T23:51:27.165Z | AB42: com.gowid.expense | AC42: 2.8.4 | AD42: Apple iPhone | AE42: 2026-02-12T08:44:35.983Z | AF42: iOS 26.2.1 | AG42: iOS | AH42: 15 | AI42: FALSE | AJ42: FALSE | AK42: 2026-02-19T23:51:27.166Z | AL42: Chrome 145 | AM42: Chrome | AN42: Desktop | AO42: 2026-02-19T23:51:27.165Z | AP42: Windows NT ?? | AQ42: Windows NT | AR42: 30 | AU42: https://payment-gateway.tosspayments.com/ | BE42: TRUE | BK42: https://payment-gateway.tosspayments.com/
A43: 65681a85826983030494 | B43: 앤잡스 | C43: 앤잡스 | D43: EXPENSE:슈퍼관리자 / CARD:슈퍼관리자 | E43: 주식회사 팀블렌드 | F43: 154-86-01241 | H43: 신한 | I43: 기가입회원/관리자/기존 | J43: lms@biskit.co | K43: =+821031708946 -> 821031708946 | P43: 2085947233 | Q43: TRUE | R43: 413 | S43: 서울시 양천구 | U43: KR | V43: Asia/Seoul | W43: 2023-11-30T05:15:49.533Z | X43: FALSE | Y43: ko | Z43: 2026-02-20T02:30:23.595Z | AI43: FALSE | AJ43: FALSE | AK43: 2026-02-20T02:30:23.596Z | AL43: Chrome 145 | AM43: Chrome | AN43: Desktop | AO43: 2026-02-20T02:30:23.595Z | AP43: Windows NT ?? | AQ43: Windows NT | AR43: 413 | AU43: https://search.naver.com/search.naver?where=nexearch&sm=top_hty&fbm=0&ie=utf8&query=%EA%B3%A0%EC%9C%84%EB%93%9C | BE43: TRUE | BK43: https://www.gowid.com/
A44: 697970ad3d0bebd23a87 | B44: 백승찬 | C44: 백승찬 | D44: CARD:슈퍼관리자 | E44: 주식회사 파크로 | F44: 701-88-02550 | J44: parkro2022@naver.com | K44: =+821034202255 -> 821034202255 | P44: 122953435 | Q44: TRUE | R44: 11 | S44: 대구시 북구 | U44: KR | V44: Asia/Seoul | W44: 2026-01-28T02:13:01.250Z | X44: FALSE | Y44: ko | Z44: 2026-02-14T13:59:26.007Z | AI44: FALSE | AJ44: FALSE | AK44: 2026-02-14T13:59:26.008Z | AL44: Chrome 144 | AM44: Chrome | AN44: Desktop | AO44: 2026-02-14T13:59:26.007Z | AP44: Windows NT ?? | AQ44: Windows NT | AR44: 11 | AU44: https://search.naver.com/ | AV44: card-apply | AW44: PC-light-251117-NBS-V1 | AX44: paid-search | AY44: naver | AZ44: 고위드 | BE44: TRUE | BF44: naver | BG44: paid-search | BH44: card-apply | BI44: PC-light-251117-NBS-V1 | BJ44: 고위드 | BK44: https://search.naver.com/
A45: 67451fe390d088e53c52 | B45: 김민경 | C45: 김민경 | D45: EXPENSE:슈퍼관리자 / SUBSCRIPTION:구독 총괄 관리자 / CARD:슈퍼관리자 | E45: 주식회사 딥서치 (DeepSearch, Inc) | F45: 603-81-82945 | I45: 기가입회원/관리자/기존 | J45: ai@deepsearch.com | K45: =+821033983109 -> 821033983109 | P45: 111028885 | Q45: TRUE | R45: 290 | S45: 경기도 의정부시 | U45: KR | V45: Asia/Seoul | W45: 2024-11-26T01:09:55.593Z | X45: FALSE | Y45: ko | Z45: 2026-02-12T06:01:12.191Z | AB45: com.gowid.expense | AC45: 2.8.2 | AD45: Apple iPhone | AE45: 2026-01-20T04:08:41.732Z | AF45: iOS 26.2 | AG45: iOS | AH45: 3 | AI45: FALSE | AJ45: FALSE | AK45: 2026-02-12T06:01:12.192Z | AL45: Chrome 145 | AM45: Chrome | AN45: Desktop | AO45: 2026-02-12T06:01:12.191Z | AP45: Windows NT ?? | AQ45: Windows NT | AR45: 287 | AU45: https://gowid.com/ | BE45: TRUE | BK45: https://gowid.com/
A46: 6976cbfbd830f379026d | B46: miyu@mwd.kr | E46: 메이저월드 | I46: 비회원 | J46: miyu@mwd.kr | P46: e9138258-e38a-46a9-b80b-41050e0e3a40 | Q46: FALSE | R46: 3 | S46: 경기도 화성시 | U46: KR | V46: Asia/Seoul | W46: 2026-01-26T02:05:47.885Z | X46: FALSE | Y46: ko | Z46: 2026-01-26T03:46:18.937Z | AI46: FALSE | AJ46: FALSE | AK46: 2026-01-26T03:46:18.938Z | AL46: Edge 144 | AM46: Edge | AN46: Desktop | AO46: 2026-01-26T03:46:18.937Z | AP46: Windows >=10 | AQ46: Windows NT | AR46: 3 | AU46: https://www.google.com/ | AV46: card-apply | AW46: PC-light-251117-NBS-V1 | AX46: paid-search | AY46: naver | AZ46: 고위드 | BE46: TRUE | BF46: naver | BG46: paid-search | BH46: card-apply | BI46: PC-light-251117-NBS-V1 | BJ46: 고위드 | BK46: https://search.naver.com/
A47: 68413f7b2146cad1240d | B47: 우지철 | C47: 우지철 | D47: EXPENSE:슈퍼관리자 / SUBSCRIPTION:구독 총괄 관리자 / CARD:슈퍼관리자 | E47: 주식회사 데어워크 | F47: 189-86-02697 | I47: 기가입회원/관리자/기존 | J47: jimmy.woo@darewalk.com | K47: =+821029572951 -> 821029572951 | P47: 115659709 | Q47: TRUE | R47: 43 | S47: Seoul | T47: Seoul | U47: KR | V47: Asia/Seoul | W47: 2025-06-05T06:55:55.135Z | X47: FALSE | Y47: ko | Z47: 2026-02-20T00:49:40.188Z | AI47: FALSE | AJ47: FALSE | AK47: 2026-02-20T00:49:40.189Z | AL47: Chrome 144 | AM47: Chrome | AN47: Apple Macintosh | AO47: 2026-02-20T00:49:40.188Z | AP47: Mac OS >=10.15.7 | AQ47: Mac OS | AR47: 43 | AU47: https://www.google.com/ | BE47: TRUE | BK47: https://payment-gateway.tosspayments.com/
A48: 685df7e2265f514a72a2 | B48: 이수경 | C48: 이수경 | D48: EXPENSE:슈퍼관리자 / CARD:슈퍼관리자 | E48: 굿뉴스에너지 주식회사 | F48: 679-88-03344 | I48: 기가입회원/관리자/신규 | J48: sk.lee@goodnews.energy | K48: =+821021676243 -> 821021676243 | P48: 112106129 | Q48: TRUE | R48: 136 | S48: 서울시 성동구 | U48: KR | V48: Asia/Seoul | W48: 2025-06-27T01:46:10.157Z | X48: FALSE | Y48: ko | Z48: 2026-02-20T02:37:38.859Z | AI48: FALSE | AJ48: FALSE | AK48: 2026-02-20T02:37:38.860Z | AL48: Chrome 144 | AM48: Chrome | AN48: Desktop | AO48: 2026-02-20T02:37:38.859Z | AP48: Windows NT ?? | AQ48: Windows NT | AR48: 136 | AU48: https://www.google.com/ | BE48: TRUE | BK48: https://www.google.com/
A49: 673305ef506eb7326a3b | B49: 박성철 | C49: 박성철 | D49: EXPENSE:슈퍼관리자 / SUBSCRIPTION:구독 총괄 관리자 / CARD:슈퍼관리자 | E49: 모바일닥터 | F49: 211-88-95444 | I49: 기가입회원/관리자/기존 | J49: seongchul@fevercoach.net | K49: =+821064682565 -> 821064682565 | P49: 109913045 | Q49: TRUE | R49: 7 | S49: 경기도 용인시 수지구 | U49: KR | V49: Asia/Seoul | W49: 2024-11-12T07:38:23.329Z | X49: FALSE | Y49: ko | Z49: 2026-01-30T06:32:25.995Z | AI49: FALSE | AJ49: FALSE | AK49: 2026-01-30T06:32:25.996Z | AL49: Chrome 144 | AM49: Chrome | AN49: Desktop | AO49: 2026-01-30T04:55:00.825Z | AP49: Windows NT ?? | AQ49: Windows NT | AR49: 7 | AU49: https://www.google.com/ | AV49: card-apply | AW49: PC-light-251117-NBS-V1 | AX49: paid-search | AY49: naver | AZ49: 고위드 | BE49: TRUE | BF49: naver | BG49: paid-search | BH49: card-apply | BI49: PC-light-251117-NBS-V1 | BJ49: 고위드 | BK49: https://search.naver.com/ | BL49: 2025_11_11_channcel_talk_user
A50: 65671d0b07a172827ce3 | B50: 조현상 | C50: 조현상 | D50: EXPENSE:슈퍼관리자 / SUBSCRIPTION:구독 총괄 관리자 / CARD:슈퍼관리자 | E50: (주) 데이터뱅크 | F50: 725-81-01484 | H50: 신한 | I50: 기가입회원/관리자/기존 | J50: brianhscho@data-bank.ai | K50: =+821089953526 -> 821089953526 | P50: 114482224 | Q50: TRUE | R50: 129 | S50: 서울시 서초구 | U50: KR | V50: Asia/Seoul | W50: 2023-11-29T11:14:19.031Z | X50: FALSE | Y50: en | Z50: 2026-02-03T01:19:52.641Z | AI50: FALSE | AJ50: FALSE | AK50: 2026-02-03T01:19:52.642Z | AL50: Chrome 144 | AM50: Chrome | AN50: Apple Macintosh | AO50: 2026-02-01T12:20:04.066Z | AP50: Mac OS >=10.15.7 | AQ50: Mac OS | AR50: 129 | AU50: https://www.google.com/ | AV50: card-apply | AW50: main-header-bar | AX50: organic-search | AY50: blog | BE50: TRUE | BF50: blog | BG50: organic-search | BH50: card-apply | BI50: main-header-bar | BK50: https://www.google.com/
A51: 6978112adeadaadfd160 | B51: 박상현 | C51: 박상현 | D51: EXPENSE:일반 멤버 / CARD:일반 멤버 | E51: 주식회사 코코지 | F51: 274-81-02025 | I51: 기가입회원/소지자 | J51: sanghyun.park@kokozi.house | P51: 122956792 | Q51: TRUE | R51: 3 | S51: 서울시 강남구 | U51: KR | V51: Asia/Seoul | W51: 2026-01-27T01:13:14.912Z | X51: FALSE | Y51: ko | Z51: 2026-01-27T04:43:59.595Z | AB51: com.gowid.expense | AC51: 2.8.3 | AD51: Samsung SM-F741N | AE51: 2026-01-27T01:18:51.995Z | AF51: Android 16 | AG51: Android | AH51: 1 | AI51: FALSE | AJ51: FALSE | AK51: 2026-01-27T04:43:59.596Z | AL51: Chrome 144 | AM51: Chrome | AN51: Desktop | AO51: 2026-01-27T04:43:59.595Z | AP51: Windows NT ?? | AQ51: Windows NT | AR51: 2 | BE51: TRUE
A52: 69856c27e08eafb02bda | B52: 이승환 | C52: 이승환 | D52: CARD:슈퍼관리자 | E52: 주식회사 엄마의이유 | F52: 703-86-03890 | J52: jake0227@naver.com | K52: =+821090735195 -> 821090735195 | P52: 122949107 | Q52: TRUE | R52: 2 | S52: 서울시 성북구 | U52: KR | V52: Asia/Seoul | W52: 2026-02-06T04:20:55.919Z | X52: FALSE | Y52: ko | Z52: 2026-02-06T07:52:42.916Z | AI52: FALSE | AJ52: FALSE | AK52: 2026-02-06T07:52:42.917Z | AL52: Chrome 144 | AM52: Chrome | AN52: Desktop | AO52: 2026-02-06T07:52:42.916Z | AP52: Windows NT ?? | AQ52: Windows NT | AR52: 2 | BE52: TRUE
A53: 6967060043f331484f62 | B53: 허효선 | C53: 허효선 | D53: CARD:슈퍼관리자 / EXPENSE:슈퍼관리자 | E53: 크레플 주식회사(CREFLE Inc.) | F53: 823-86-01560 | I53: 기가입회원/관리자/신규 | J53: hs.heo@crefle.com | K53: =+821032261896 -> 821032261896 | P53: 122919832 | Q53: TRUE | R53: 14 | S53: 경기도 성남시 분당구 | U53: KR | V53: Asia/Seoul | W53: 2026-01-14T02:57:04.278Z | X53: FALSE | Y53: ko | Z53: 2026-02-04T07:48:28.529Z | AI53: FALSE | AJ53: FALSE | AK53: 2026-02-04T07:48:28.530Z | AL53: Chrome 144 | AM53: Chrome | AN53: Desktop | AO53: 2026-02-04T07:48:28.529Z | AP53: Windows NT ?? | AQ53: Windows NT | AR53: 14 | AU53: https://www.google.com/ | AV53: authority-01-2026 | AW53: gowid-card-image | AX53: paid-search | AY53: google | AZ53: 법인카드 | BE53: TRUE | BF53: google | BG53: paid-search | BH53: authority-01-2026 | BI53: gowid-card-image | BJ53: 법인카드 | BK53: https://www.google.com/
A54: 69856b834d2936a16319 | B54: 김지현 | C54: 김지현 | D54: CARD:슈퍼관리자 | E54: 주식회사 줄루웍스 | F54: 559-81-03774 | J54: kimhaeda@gmail.com | K54: =+821028633258 -> 821028633258 | P54: 122949109 | Q54: TRUE | R54: 12 | S54: 경기도 고양시 덕양구 | U54: KR | V54: Asia/Seoul | W54: 2026-02-06T04:18:11.316Z | X54: FALSE | Y54: ko | Z54: 2026-02-19T01:51:04.187Z | AI54: FALSE | AJ54: FALSE | AK54: 2026-02-19T01:51:04.188Z | AL54: Chrome 144 | AM54: Chrome | AN54: Apple Macintosh | AO54: 2026-02-19T01:51:04.187Z | AP54: Mac OS >=10.15.7 | AQ54: Mac OS | AR54: 12 | AU54: https://www.google.com/ | AV54: card-apply | AW54: main-header-bar | AX54: organic-search | AY54: blog | BE54: TRUE | BF54: blog | BG54: organic-search | BH54: card-apply | BI54: main-header-bar | BK54: https://www.google.com/
A55: 69969a3eada6ff84cc1d | B55: 백한열 | C55: 백한열 | D55: SUBSCRIPTION:구독 총괄 관리자 | E55: 주식회사 스튜디오크립티드 | F55: 329-86-02368 | J55: cryptid.tax@gmail.com | K55: =+821085253395 -> 821085253395 | P55: 122988382 | Q55: TRUE | R55: 1 | S55: 경기도 고양시 일산동구 | U55: KR | V55: Asia/Seoul | W55: 2026-02-19T05:06:06.711Z | X55: FALSE | Y55: ko | Z55: 2026-02-19T05:06:06.710Z | AI55: FALSE | AJ55: FALSE | AK55: 2026-02-19T05:08:37.981Z | AL55: Chrome 145 | AM55: Chrome | AN55: Desktop | AO55: 2026-02-19T05:06:06.710Z | AP55: Windows NT ?? | AQ55: Windows NT | AR55: 1 | AU55: https://search.naver.com/ | BE55: TRUE | BK55: https://search.naver.com/
A56: 69703f5e64cc24042600 | B56: 신혜림 | C56: 신혜림 | D56: CARD:슈퍼관리자 / EXPENSE:슈퍼관리자 | E56: 주식회사 클래디(Cladi Co.,Ltd) | F56: 405-81-11055 | I56: 기가입회원/관리자/신규 | J56: emmashin@cladi.me | K56: =+821083322989 -> 821083322989 | P56: 122957752 | Q56: TRUE | R56: 5 | S56: 경기도 성남시 분당구 | U56: KR | V56: Asia/Seoul | W56: 2026-01-21T02:52:14.412Z | X56: FALSE | Y56: ko | Z56: 2026-02-19T04:40:55.341Z | AI56: FALSE | AJ56: FALSE | AK56: 2026-02-19T04:40:55.342Z | AL56: Safari 26.2 | AM56: Safari | AN56: Apple Macintosh | AO56: 2026-02-19T04:40:55.341Z | AP56: Mac OS >=10.15.7 | AQ56: Mac OS | AR56: 5 | AU56: https://www.google.com/ | BE56: TRUE | BK56: https://www.google.com/
A57: 68a675c456dd07c0cca6 | B57: 윤시원 | C57: 윤시원 | D57: EXPENSE:슈퍼관리자 / CARD:슈퍼관리자 | E57: （주）한백자동차정비 | F57: 410-81-95552 | J57: yunc1@kakao.com | K57: =+821066031905 -> 821066031905 | P57: 110094590 | Q57: TRUE | R57: 27 | S57: 서울시 강남구 | U57: KR | V57: Asia/Seoul | W57: 2025-08-21T01:26:28.356Z | X57: FALSE | Y57: ko | Z57: 2026-02-06T02:24:47.461Z | AB57: com.gowid.expense | AC57: 2.8.4 | AD57: Samsung SM-S921N | AE57: 2026-02-06T02:24:47.461Z | AF57: Android 16 | AG57: Android | AH57: 22 | AI57: FALSE | AJ57: FALSE | AK57: 2026-02-06T02:24:47.462Z | AL57: Chrome 144 | AM57: Chrome | AN57: Desktop | AO57: 2026-02-06T01:01:14.290Z | AP57: Windows NT ?? | AQ57: Windows NT | AR57: 5 | AU57: https://docs.channel.io/ | BE57: TRUE | BK57: https://docs.channel.io/ | BL57: 2025_11_11_channcel_talk_user
A58: 664a9aa8f1c757f1ac45 | B58: 박지운 | C58: 박지운 | D58: EXPENSE:슈퍼관리자 / CARD:슈퍼관리자 | E58: 주식회사 샐러리파이 (Salarify Corp.) | F58: 144-86-02597 | I58: 기가입회원/관리자/기존 | J58: jioon.park@salarify.kr | K58: =+821031777932 -> 821031777932 | P58: 114616178 | Q58: TRUE | R58: 80 | S58: 경기도 파주시 | U58: KR | V58: Asia/Seoul | W58: 2024-05-20T00:34:48.994Z | X58: FALSE | Y58: ko | Z58: 2026-02-10T07:42:45.260Z | AI58: FALSE | AJ58: FALSE | AK58: 2026-02-10T07:42:45.262Z | AL58: Chrome 145 | AM58: Chrome | AN58: Apple Macintosh | AO58: 2026-02-10T01:33:55.323Z | AP58: Mac OS >=10.15.7 | AQ58: Mac OS | AR58: 80 | AU58: https://www.google.com/ | AV58: Linkedin_main_page | AX58: page | AY58: Linkedin_main | BE58: TRUE | BF58: Linkedin_main | BG58: page | BH58: Linkedin_main_page | BK58: https://www.google.com/
A59: 66b97ad2dbc638bf7456 | B59: 선하다 복지용구사업소 | C59: 선하다 복지용구사업소 | D59: EXPENSE:슈퍼관리자 / CARD:슈퍼관리자 | E59: 주식회사 선하다 | F59: 301-88-01711 | I59: 기가입회원/관리자/기존, 기가입회원 | J59: sunhada1233@naver.com | K59: =+821089757263 -> 821089757263 | P59: 108842299 | Q59: TRUE | R59: 156 | S59: 서울시 서초구 | U59: KR | V59: Asia/Seoul | W59: 2024-08-12T03:00:34.899Z | X59: FALSE | Y59: ko | Z59: 2026-02-20T01:33:44.080Z | AI59: FALSE | AJ59: FALSE | AK59: 2026-02-20T01:33:44.081Z | AL59: Chrome 145 | AM59: Chrome | AN59: Desktop | AO59: 2026-02-20T01:33:44.080Z | AP59: Windows NT ?? | AQ59: Windows NT | AR59: 156 | AU59: https://search.naver.com/search.naver?where=nexearch&sm=top_hty&fbm=0&ie=utf8&query=%EA%B3%A0%EC%9C%84%EB%93%9C | BE59: TRUE | BK59: https://docs.channel.io/
A60: 698c3ed95f3dc7144173 | B60: 지니 127 | P60: 87af4d19-5163-4924-80e7-01982c0b4b3d | Q60: FALSE | R60: 2 | S60: 서울시 성동구 | U60: KR | V60: Asia/Seoul | W60: 2026-02-11T08:33:29.390Z | X60: FALSE | Y60: ko | Z60: 2026-02-11T08:42:16.655Z | AI60: FALSE | AJ60: FALSE | AK60: 2026-02-11T08:42:16.655Z | AL60: Edge 144 | AM60: Edge | AN60: Desktop | AO60: 2026-02-11T08:42:16.655Z | AP60: Windows >=10 | AQ60: Windows NT | AR60: 2 | AU60: https://www.bing.com/ | BE60: TRUE | BK60: https://www.bing.com/
A61: 65b7495a9b170d51382d | B61: 최유은 | C61: 최유은 | D61: EXPENSE:카드 총괄관리자 / SUBSCRIPTION:구독 총괄 관리자 / CARD:카드 총괄관리자 | E61: (주)와이오엘오 | F61: 610-86-34204 | H61: 신한 | I61: 기가입회원/관리자/기존, 핵심고객(8월), 코어그룹, 코어그룹(12월) | J61: choiye@yolocorp.kr | K61: =+821023571092 -> 821023571092 | P61: 109813780 | Q61: TRUE | R61: 473 | S61: 경기도 성남시 분당구 | U61: KR | V61: Asia/Seoul | W61: 2024-01-29T06:44:42.635Z | X61: FALSE | Y61: ko | Z61: 2026-02-20T02:14:10.622Z | AB61: com.gowid.expense | AC61: 2.8.4 | AD61: Apple iPhone | AE61: 2026-02-02T10:30:47.251Z | AF61: iOS 26.2.1 | AG61: iOS | AH61: 2 | AI61: FALSE | AJ61: FALSE | AK61: 2026-02-20T02:14:10.623Z | AL61: Chrome 145 | AM61: Chrome | AN61: Desktop | AO61: 2026-02-20T02:14:10.622Z | AP61: Windows NT ?? | AQ61: Windows NT | AR61: 471 | AU61: https://www.google.com/ | BE61: TRUE | BK61: https://payment-gateway.tosspayments.com/
A62: 697312002b281d37c090 | B62: 강영화 | C62: 강영화 | D62: CARD:슈퍼관리자 / EXPENSE:슈퍼관리자 | E62: 엘스랩스 주식회사 | F62: 494-87-04027 | I62: 기가입회원/관리자/신규 | J62: young@else.so | K62: =+821095880891 -> 821095880891 | P62: 122956635 | Q62: TRUE | R62: 11 | S62: 서울시 강남구 | U62: KR | V62: Asia/Seoul | W62: 2026-01-23T06:15:28.177Z | X62: FALSE | Y62: en | Z62: 2026-02-20T02:30:34.404Z | AI62: FALSE | AJ62: FALSE | AK62: 2026-02-20T02:30:34.406Z | AL62: Chrome 144 | AM62: Chrome | AN62: Apple Macintosh | AO62: 2026-02-20T02:30:34.404Z | AP62: Mac OS >=10.15.7 | AQ62: Mac OS | AR62: 11 | AU62: https://www.google.com/ | BE62: TRUE | BK62: https://www.google.com/
A63: 671f045361fe17c2baca | B63: 박클레어 | C63: 박클레어 | D63: EXPENSE:슈퍼관리자 / SUBSCRIPTION:구독 총괄 관리자 / CARD:슈퍼관리자 | E63: 주식회사 지투시그마 (Z to Sigma Inc.) | F63: 893-81-01579 | I63: 기가입회원/관리자/기존, 일반/나머지고객 | J63: claire@paywork.io | K63: =+821091387238 -> 821091387238 | P63: 2085743365 | Q63: TRUE | R63: 373 | S63: 서울시 중구 | U63: KR | V63: Asia/Seoul | W63: 2024-10-28T03:26:11.400Z | X63: FALSE | Y63: ko | Z63: 2026-02-19T02:41:51.481Z | AB63: com.gowid.expense | AC63: 2.8.4 | AD63: Apple iPhone | AE63: 2026-02-18T06:58:21.752Z | AF63: iOS 26.2.1 | AG63: iOS | AH63: 9 | AI63: FALSE | AJ63: FALSE | AK63: 2026-02-19T02:41:51.482Z | AL63: Chrome 144 | AM63: Chrome | AN63: Apple Macintosh | AO63: 2026-02-19T02:41:51.481Z | AP63: Mac OS >=10.15.7 | AQ63: Mac OS | AR63: 364 | AU63: https://blog.gowid.com/ | BE63: TRUE | BK63: https://www.google.com/
A64: 698544ea4610683b182a | B64: 초콜릿 444 | P64: c70481e4-4f57-4a92-a9b7-266065eb6412 | Q64: FALSE | R64: 2 | S64: 서울시 구로구 | U64: KR | V64: Asia/Seoul | W64: 2026-02-06T01:33:30.287Z | X64: FALSE | Y64: ko | Z64: 2026-02-06T02:13:12.905Z | AI64: FALSE | AJ64: FALSE | AK64: 2026-02-06T02:13:12.905Z | AL64: Chrome 144 | AM64: Chrome | AN64: Desktop | AO64: 2026-02-06T02:13:12.905Z | AP64: Windows NT ?? | AQ64: Windows NT | AR64: 2 | AU64: https://search.naver.com/ | BE64: TRUE | BK64: https://search.naver.com/
A65: 68685d73f166cc034502 | B65: 박지연 | C65: 박지연 | D65: EXPENSE:슈퍼관리자 / CARD:슈퍼관리자 | E65: 주식회사 쟈스민 | F65: 411-81-93504 | I65: 기가입회원/관리자/기존 | J65: jasmine.kcom@gmail.com | K65: =+821089083333 -> 821089083333 | P65: 109918207 | Q65: TRUE | R65: 16 | S65: 서울시 강남구 | U65: KR | V65: Asia/Seoul | W65: 2025-07-04T23:02:11.989Z | X65: FALSE | Y65: ko | Z65: 2026-02-10T03:53:13.017Z | AB65: com.gowid.expense | AC65: 2.8.4 | AD65: Samsung SM-S931N | AE65: 2026-02-10T01:51:09.816Z | AF65: Android 16 | AG65: Android | AH65: 11 | AI65: FALSE | AJ65: FALSE | AK65: 2026-02-10T03:53:13.018Z | AL65: Edge 144 | AM65: Edge | AN65: Desktop | AO65: 2026-02-10T03:53:13.017Z | AP65: Windows >=10 | AQ65: Windows NT | AR65: 5 | AU65: https://www.google.com/ | AV65: card-apply | AW65: PC-light-251117-NBS-V1 | AX65: paid-search | AY65: naver | AZ65: 고위드법인카드 | BE65: TRUE | BF65: naver | BG65: paid-search | BH65: card-apply | BI65: PC-light-251117-NBS-V1 | BJ65: 고위드법인카드 | BK65: https://search.naver.com/ | BL65: 2025_11_11_channcel_talk_user
A66: 679f227e32e8a1ee76a1 | B66: 지형근 | C66: 지형근 | D66: EXPENSE:슈퍼관리자 / CARD:슈퍼관리자 | E66: 주식회사 부쉬맨(BUSHMAN Co., Ltd.) | F66: 538-87-02289 | J66: bushmankorea@gmail.com | K66: =+821028785127 -> 821028785127 | P66: 111131518 | Q66: TRUE | R66: 5 | S66: 경기도 성남시 분당구 | U66: KR | V66: Asia/Seoul | W66: 2025-02-02T07:45:02.208Z | X66: FALSE | Y66: ko | Z66: 2026-02-10T07:39:09.293Z | AI66: FALSE | AJ66: FALSE | AK66: 2026-02-10T07:39:09.294Z | AL66: Chrome 138 | AM66: Chrome | AN66: Desktop | AO66: 2025-12-02T08:21:17.809Z | AP66: Windows NT ?? | AQ66: Windows NT | AR66: 5 | AU66: https://search.naver.com/search.naver?sm=tab_hty.top&where=nexearch&ssc=tab.nx.all&query=%EA%B3%A0%EC%9C%84%EB%93%9C&oquery=%EC%98%A4%EB%A0%8C%EC%A7%80%ED%94%8C%EB%9E%98%EB%8B%9B&tqi=iH8h3sqVN8CssD%2B%2Fit4ssssstVo-232041 | BE66: TRUE | BK66: https://www.google.com/ | BL66: 2025_11_11_channcel_talk_user
A67: 698444e9680bdac3cd46 | B67: 유채림 | C67: 유채림 | D67: CARD:슈퍼관리자 | E67: 하이퍼브레인 주식회사(HYPERBRAIN Co., Ltd.) | F67: 453-81-03495 | J67: cl_yu@hyperbrain.co.kr | K67: =+821045877298 -> 821045877298 | P67: 122949247 | Q67: TRUE | R67: 4 | S67: 전북도 군산시 | U67: KR | V67: Asia/Seoul | W67: 2026-02-05T07:21:13.426Z | X67: FALSE | Y67: ko | Z67: 2026-02-09T09:58:27.967Z | AI67: FALSE | AJ67: FALSE | AK67: 2026-02-09T09:58:27.968Z | AL67: Chrome 144 | AM67: Chrome | AN67: Desktop | AO67: 2026-02-09T09:58:27.967Z | AP67: Windows NT ?? | AQ67: Windows NT | AR67: 4 | AU67: https://www.google.com/ | BE67: TRUE | BK67: https://www.google.com/
A68: 696db3205e96892e8e31 | B68: 지소영 | C68: 지소영 | D68: CARD:슈퍼관리자 / EXPENSE:슈퍼관리자 | E68: 헬로스킨 주식회사(HELLO SKIN Co.,Ltd.) | F68: 888-88-00596 | I68: 비회원 | J68: jsy@jumiso.co.kr | K68: =+821068525584 -> 821068525584 | P68: 122953658 | Q68: TRUE | R68: 25 | S68: 서울시 강남구 | U68: KR | V68: Asia/Seoul | W68: 2026-01-19T04:29:20.387Z | X68: FALSE | Y68: ko | Z68: 2026-02-19T02:30:05.729Z | AI68: FALSE | AJ68: FALSE | AK68: 2026-02-19T02:30:05.730Z | AL68: Chrome 144 | AM68: Chrome | AN68: Desktop | AO68: 2026-02-19T02:30:05.729Z | AP68: Windows NT ?? | AQ68: Windows NT | AR68: 25 | AU68: https://www.google.com/ | AV68: authority-01-2026 | AW68: gowid-card-image | AX68: paid-search | AY68: google | AZ68: 법인카드 | BE68: TRUE | BF68: google | BG68: paid-search | BH68: authority-01-2026 | BI68: gowid-card-image | BJ68: 법인카드 | BK68: https://www.google.com/
A69: 698bef47d107fbbec4ca | B69: 김희선 | C69: 김희선 | D69: EXPENSE:슈퍼관리자 / CARD:슈퍼관리자 | E69: 주식회사 시프트 | F69: 764-81-00613 | J69: spiderman@xhiftcorp.com | K69: =+821087550064 -> 821087550064 | P69: 2085882658 | Q69: TRUE | R69: 1 | S69: 경기도 고양시 덕양구 | U69: KR | V69: Asia/Seoul | W69: 2026-02-11T02:53:59.855Z | X69: FALSE | Y69: ko | Z69: 2026-02-11T02:53:59.855Z | AI69: FALSE | AJ69: FALSE | AK69: 2026-02-11T02:54:10.312Z | AL69: Chrome 144 | AM69: Chrome | AN69: Desktop | AO69: 2026-02-11T02:53:59.855Z | AP69: Windows NT ?? | AQ69: Windows NT | AR69: 1 | BE69: TRUE
A70: 698936d1bc94ae7dbf8f | B70: 유승완 | C70: 유승완 | D70: CARD:슈퍼관리자 | E70: 주식회사 크리에이즈컴퍼니 | F70: 475-86-03530 | J70: ysweada@naver.com | K70: =+821032031114 -> 821032031114 | P70: 122992733 | Q70: TRUE | R70: 7 | S70: 경남 양산시 | U70: KR | V70: Asia/Seoul | W70: 2026-02-09T01:22:25.772Z | X70: FALSE | Y70: ko | Z70: 2026-02-11T02:45:40.552Z | AI70: FALSE | AJ70: FALSE | AK70: 2026-02-11T02:45:40.552Z | AL70: Chrome 144 | AM70: Chrome | AN70: Desktop | AO70: 2026-02-11T02:45:40.552Z | AP70: Windows NT ?? | AQ70: Windows NT | AR70: 7 | AU70: https://www.google.com/ | BE70: TRUE | BK70: https://www.google.com/
A71: 65f4010755b1a0eb957f | B71: 원소현 | C71: 원소현 | D71: EXPENSE:슈퍼관리자 / CARD:슈퍼관리자 | E71: 주식회사 리우 | F71: 257-81-01545 | H71: 신한 | I71: 기가입회원/관리자/기존 | J71: wmy0102@riupack.com | K71: =+821033608415 -> 821033608415 | P71: 109950739 | Q71: TRUE | R71: 941 | S71: 경북 포항시 남구 | U71: KR | V71: Asia/Seoul | W71: 2024-03-15T08:04:23.351Z | X71: FALSE | Y71: ko | Z71: 2026-02-20T03:46:35.785Z | AI71: FALSE | AJ71: FALSE | AK71: 2026-02-20T03:46:35.786Z | AL71: Edge 145 | AM71: Edge | AN71: Desktop | AO71: 2026-02-20T03:46:35.785Z | AP71: Windows >=10 | AQ71: Windows NT | AR71: 941 | AU71: https://www.riupack.com/ | BE71: TRUE
A72: 67049b48d2f96f870032 | B72: 장한솔 | C72: 장한솔 | D72: EXPENSE:슈퍼관리자 / SUBSCRIPTION:구독 총괄 관리자 / CARD:슈퍼관리자 | E72: 주식회사 보살핌 | F72: 440-88-02179 | J72: hansol.jang@bosalpim.co.kr | K72: =+821051119300 -> 821051119300 | P72: 2085807619 | Q72: TRUE | R72: 49 | S72: 서울시 강남구 | U72: KR | V72: Asia/Seoul | W72: 2024-10-08T02:39:04.864Z | X72: FALSE | Y72: ko | Z72: 2026-02-19T10:41:49.265Z | AB72: com.gowid.expense | AC72: 2.8.4 | AD72: Samsung SM-S931N | AE72: 2026-02-19T09:17:37.316Z | AF72: Android 16 | AG72: Android | AH72: 1 | AI72: FALSE | AJ72: FALSE | AK72: 2026-02-19T10:41:49.266Z | AL72: Chrome 145 | AM72: Chrome | AN72: Apple Macintosh | AO72: 2026-02-19T10:41:49.265Z | AP72: Mac OS >=10.15.7 | AQ72: Mac OS | AR72: 48 | AU72: https://www.google.com/ | BE72: TRUE | BK72: https://www.google.com/
A73: 66f53171f11755c05d8c | B73: 안서현 | C73: 안서현 | D73: EXPENSE:슈퍼관리자 / SUBSCRIPTION:구독 총괄 관리자 / CARD:슈퍼관리자 | E73: 주식회사 이오스튜디오 | F73: 501-87-01653 | I73: 기가입회원/관리자/기존, 핵심고객(8월) | J73: ash@eoeoeo.net | K73: =+821053822553 -> 821053822553 | P73: 2085877440 | Q73: TRUE | R73: 353 | S73: Seattle | T73: Washington | U73: US | V73: America/Los_Angeles | W73: 2024-09-26T10:03:29.987Z | X73: FALSE | Y73: ko | Z73: 2026-02-19T04:49:39.288Z | AB73: com.gowid.expense | AC73: 2.8.4 | AD73: Apple iPhone | AE73: 2026-02-09T10:58:51.697Z | AF73: iOS 26.2.1 | AG73: iOS | AH73: 21 | AI73: FALSE | AJ73: FALSE | AK73: 2026-02-19T04:49:39.289Z | AL73: Chrome 144 | AM73: Chrome | AN73: Desktop | AO73: 2026-02-19T04:49:39.288Z | AP73: Windows NT ?? | AQ73: Windows NT | AR73: 332 | AU73: https://www.google.com/ | AV73: authority-01-2026 | AW73: gowid-card-image | AX73: paid-search | AY73: google | AZ73: 스타트업법인카드 | BE73: TRUE | BF73: google | BG73: paid-search | BH73: authority-01-2026 | BI73: gowid-card-image | BJ73: 스타트업법인카드 | BK73: https://www.google.com/
A74: 67201a42c50c9890b794 | B74: 재무팀 | C74: 재무팀 | D74: EXPENSE:슈퍼관리자 / CARD:슈퍼관리자 | E74: 주식회사 마티니 아이오 | F74: 111-81-35910 | I74: 기가입회원/관리자/기존, 비회원 | J74: eunyoung@aimed.xyz | K74: =+821045866282 -> 821045866282 | P74: 117020724 | Q74: TRUE | R74: 744 | S74: 서울시 서초구 | U74: KR | V74: Asia/Seoul | W74: 2024-10-28T23:12:02.807Z | X74: FALSE | Y74: ko | Z74: 2026-02-20T04:57:53.039Z | AI74: FALSE | AJ74: FALSE | AK74: 2026-02-20T04:57:53.040Z | AL74: Edge 145 | AM74: Edge | AN74: Desktop | AO74: 2026-02-20T04:57:53.039Z | AP74: Windows >=10 | AQ74: Windows NT | AR74: 744 | AU74: https://ntp.msn.com/ | AV74: card-apply | AW74: PC-light-251117-NBS-V1 | AX74: paid-search | AY74: naver | AZ74: 고위드 | BE74: TRUE | BF74: naver | BG74: paid-search | BH74: card-apply | BI74: PC-light-251117-NBS-V1 | BJ74: 고위드 | BK74: https://search.naver.com/
A75: 697c74946feec1d864d9 | B75: 수박 252 | I75: 비회원 | P75: e5bc6139-ebb1-4ed1-83a0-8a161a4615f7 | Q75: FALSE | R75: 2 | S75: Seoul | T75: Seoul | U75: KR | V75: Asia/Seoul | W75: 2026-01-30T09:06:28.458Z | X75: FALSE | Y75: ko | Z75: 2026-02-02T05:58:58.493Z | AI75: FALSE | AJ75: FALSE | AK75: 2026-02-02T06:01:12.589Z | AL75: Chrome 144 | AM75: Chrome | AN75: Apple Macintosh | AO75: 2026-02-02T05:58:58.493Z | AP75: Mac OS >=10.15.7 | AQ75: Mac OS | AR75: 2 | AV75: authority-lead-form-01-2026 | AW75: stibee-email-sequence-step2 | AX75: paid-social | AY75: facebook | BE75: TRUE | BF75: facebook | BG75: paid-social | BH75: authority-lead-form-01-2026 | BI75: stibee-email-sequence-step2
A76: 696dcc593b530b6d530b | B76: 박형석 | C76: 박형석 | D76: CARD:슈퍼관리자 / EXPENSE:슈퍼관리자 | E76: 프레시오리진 주식회사 농업회사법인 | F76: 566-88-03446 | I76: 기가입회원/관리자/신규, 비회원 | J76: freshorigin@naver.com | K76: =+821092713359 -> 821092713359 | P76: 122954552 | Q76: TRUE | R76: 7 | S76: 부산시 동구 | U76: KR | V76: Asia/Seoul | W76: 2026-01-19T06:16:57.242Z | X76: FALSE | Y76: ko | Z76: 2026-02-10T04:27:41.632Z | AI76: FALSE | AJ76: FALSE | AK76: 2026-02-10T04:27:41.634Z | AL76: Chrome 144 | AM76: Chrome | AN76: Desktop | AO76: 2026-02-10T04:27:41.632Z | AP76: Windows NT ?? | AQ76: Windows NT | AR76: 7 | AU76: https://search.naver.com/ | AV76: card-apply | AW76: PC-light-251117-NBS-V1 | AX76: paid-search | AY76: naver | AZ76: 고위드 | BE76: TRUE | BF76: naver | BG76: paid-search | BH76: card-apply | BI76: PC-light-251117-NBS-V1 | BJ76: 고위드 | BK76: https://search.naver.com/
A77: 698e99aec971dee8ce99 | B77: 선인장 102 | P77: a6cdead3-a011-42dd-af5b-fa2f408e1255 | Q77: FALSE | R77: 2 | S77: 서울시 관악구 | U77: KR | V77: Asia/Seoul | W77: 2026-02-13T03:25:34.825Z | X77: FALSE | Y77: ko | Z77: 2026-02-14T10:32:38.005Z | AI77: FALSE | AJ77: FALSE | AK77: 2026-02-14T10:32:38.006Z | AL77: Chrome Webview 145.0.7632.49 | AM77: Chrome Webview | AN77: Samsung SM-F966N | AO77: 2026-02-14T10:32:38.005Z | AP77: Android 16 | AQ77: Android | AR77: 2 | AU77: http://instagram.com/ | AV77: commerce-card-02-2026 | AW77: commerce-card-1080x1080-v2 | AX77: paid-social | AY77: facebook | AZ77: 120242817850330606 | BE77: TRUE | BF77: facebook | BG77: paid-social | BH77: commerce-card-02-2026 | BI77: commerce-card-1080x1080-v3 | BJ77: 120242817850330606 | BK77: http://instagram.com/
A78: 67185266092739e1507a | B78: 김수연 | C78: 김수연 | D78: EXPENSE:슈퍼관리자 / SUBSCRIPTION:구독 총괄 관리자 / CARD:슈퍼관리자 | E78: 신스타프리젠츠 주식회사(Shin Starr Presents Corp.) | F78: 780-86-01695 | I78: 기가입회원/관리자/신규, 기가입회원/관리자/기존 | J78: sy.kim@shinstarr.com | P78: 110990003 | Q78: TRUE | R78: 54 | S78: 서울시 영등포구 | U78: KR | V78: Asia/Seoul | W78: 2024-10-23T01:33:26.037Z | X78: FALSE | Y78: ko | Z78: 2026-02-11T05:24:20.383Z | AI78: FALSE | AJ78: FALSE | AK78: 2026-02-11T05:24:20.384Z | AL78: Chrome 144 | AM78: Chrome | AN78: Desktop | AO78: 2026-02-11T05:24:20.383Z | AP78: Windows NT ?? | AQ78: Windows NT | AR78: 54 | AU78: https://search.yahoo.com/ | BE78: TRUE | BK78: https://payment-gateway.tosspayments.com/ | BL78: 2025_11_11_channcel_talk_user
A79: 68578b40595408f06d9b | B79: 오상준 | C79: 오상준 | D79: EXPENSE:슈퍼관리자 / CARD:슈퍼관리자 | E79: 주식회사 퍼슬리 | F79: 241-81-03586 | I79: 기가입회원/소지자, 기가입회원/관리자/기존 | J79: sangjun.oh@perslyai.com | K79: =+821043011619 -> 821043011619 | P79: 112291958 | Q79: TRUE | R79: 20 | S79: 서울시 서초구 | U79: KR | V79: Asia/Seoul | W79: 2025-06-22T04:49:04.365Z | X79: FALSE | Y79: ko | Z79: 2026-02-19T07:38:16.781Z | AI79: FALSE | AJ79: FALSE | AK79: 2026-02-19T07:38:16.782Z | AL79: Whale 4.35.351.16 | AM79: Whale | AN79: Desktop | AO79: 2026-02-19T07:38:16.781Z | AP79: Windows NT ?? | AQ79: Windows NT | AR79: 20 | AU79: https://www.google.com/ | BE79: TRUE | BK79: https://www.google.com/ | BL79: 2025_11_11_channcel_talk_user
A80: 69847351c6e41bd16e9c | B80: 치즈 272 | P80: 78dd17fd-672c-4492-8096-d44dd0a29d2c | Q80: FALSE | R80: 2 | S80: 서울시 강남구 | U80: KR | V80: Asia/Seoul | W80: 2026-02-05T10:39:13.814Z | X80: FALSE | Y80: ko | Z80: 2026-02-06T01:22:08.561Z | AI80: FALSE | AJ80: FALSE | AK80: 2026-02-06T01:25:02.637Z | AL80: Chrome 144 | AM80: Chrome | AN80: Desktop | AO80: 2026-02-06T01:22:08.561Z | AP80: Windows NT ?? | AQ80: Windows NT | AR80: 2 | AU80: https://search.naver.com/ | AV80: card-apply | AW80: PC-light-251117-NBS-V1 | AX80: paid-search | AY80: naver | AZ80: 고위드 | BE80: TRUE | BF80: naver | BG80: paid-search | BH80: card-apply | BI80: PC-light-251117-NBS-V1 | BJ80: 고위드 | BK80: https://www.google.com/
A81: 65dff0fa1cc4317ffbed | B81: 심재한 | C81: 심재한 | D81: EXPENSE:슈퍼관리자 / CARD:슈퍼관리자 | E81: 주식회사 라이넨스 | F81: 175-86-02816 | H81: 신한 | J81: jhshim@lynens.kr | K81: =+821084869597 -> 821084869597 | P81: 117312350 | Q81: TRUE | R81: 34 | S81: 서울시 마포구 | U81: KR | V81: Asia/Seoul | W81: 2024-02-29T02:50:34.122Z | X81: FALSE | Y81: ko | Z81: 2026-02-13T08:25:17.698Z | AI81: FALSE | AJ81: FALSE | AK81: 2026-02-13T08:25:17.699Z | AL81: Safari 18.3 | AM81: Safari | AN81: Apple Macintosh | AO81: 2026-02-13T08:25:17.698Z | AP81: Mac OS >=10.15.7 | AQ81: Mac OS | AR81: 34 | AU81: https://blog.gowid.com/ | AV81: authority-01-2026 | AW81: gowid-card-image | AX81: paid-search | AY81: blog | AZ81: 법인카드 | BE81: TRUE | BF81: google | BG81: paid-search | BH81: authority-01-2026 | BI81: gowid-card-image | BJ81: 법인카드 | BK81: https://search.naver.com/search.naver?where=nexearch&sm=top_sug.pre&fbm=0&acr=1&acq=%EA%B3%A0%EC%9C%84%EB%93%9C&qdt=0&ie=utf8&query=%EA%B3%A0%EC%9C%84%EB%93%9C&ackey=z0pbdupz | BL81: 2025_11_11_channcel_talk_user
A82: 697c7ab241a7ede35164 | B82: 신현덕 | C82: 신현덕 | D82: EXPENSE:일반 멤버 / SUBSCRIPTION:일반 멤버 / CARD:일반 멤버 | E82: 주식회사 고위드(GOWID Inc) | F82: 261-81-25793 | I82: 기가입회원/소지자 | J82: gyejrdl12@gowid.com | P82: 122953535 | Q82: TRUE | R82: 20 | S82: 서울시 송파구 | U82: KR | V82: Asia/Seoul | W82: 2026-01-30T09:32:34.269Z | X82: FALSE | Y82: ko | Z82: 2026-02-19T08:32:44.632Z | AB82: com.gowid.expense | AC82: 2.8.4 | AD82: Samsung SM-F956N | AE82: 2026-02-19T08:32:44.632Z | AF82: Android 16 | AG82: Android | AH82: 16 | AI82: FALSE | AJ82: FALSE | AK82: 2026-02-19T08:32:44.633Z | AL82: Safari 26.2 | AM82: Safari | AN82: Apple Macintosh | AO82: 2026-02-08T23:28:26.710Z | AP82: Mac OS >=10.15.7 | AQ82: Mac OS | AR82: 4 | AV82: authority-lead-form-01-2026 | AW82: stibee-email-sequence-step1 | AX82: paid-social | AY82: facebook | BE82: TRUE | BF82: facebook | BG82: paid-social | BH82: authority-lead-form-01-2026 | BI82: stibee-email-sequence-step1
A83: 667964bea6e7980d7cf2 | B83: 박진홍 | C83: 박진홍 | D83: EXPENSE:슈퍼관리자 / SUBSCRIPTION:구독 총괄 관리자 / CARD:슈퍼관리자 | E83: 주식회사 밀크코퍼레이션 (Milk Corporation Corp.) | F83: 755-81-02029 | H83: 롯데 | I83: 기가입회원/관리자/기존 | J83: jacob.park@milkcorp.kr | K83: =+821025353229 -> 821025353229 | P83: 109917336 | Q83: TRUE | R83: 479 | S83: 서울시 중랑구 | U83: KR | V83: Asia/Seoul | W83: 2024-06-24T12:21:18.683Z | X83: FALSE | Y83: ko | Z83: 2026-02-19T10:08:45.075Z | AI83: FALSE | AJ83: FALSE | AK83: 2026-02-19T10:08:45.076Z | AL83: Chrome 144 | AM83: Chrome | AN83: Apple Macintosh | AO83: 2026-02-19T10:08:45.075Z | AP83: Mac OS >=10.15.7 | AQ83: Mac OS | AR83: 479 | AU83: https://corp.lottecard.co.kr/ | BE83: TRUE | BK83: https://payment-gateway.tosspayments.com/
A84: 693a59971cbe69deb891 | B84: 임휘랑 | C84: 임휘랑 | D84: EXPENSE:슈퍼관리자 / FUEL:슈퍼관리자 / SUBSCRIPTION:구독 총괄 관리자 / CARD:슈퍼관리자 | E84: 주식회사 의식주컴퍼니 | F84: 561-87-00957 | I84: 코어그룹(12월) | J84: hrlim@lifegoeson.kr | P84: 112569023 | Q84: TRUE | R84: 13 | S84: 경기도 군포시 | U84: KR | V84: Asia/Seoul | W84: 2025-12-11T05:41:43.118Z | X84: FALSE | Y84: ko | Z84: 2026-02-10T04:45:25.749Z | AI84: FALSE | AJ84: FALSE | AK84: 2026-02-10T04:45:25.750Z | AL84: Chrome 144 | AM84: Chrome | AN84: Desktop | AO84: 2026-02-10T04:45:25.749Z | AP84: Windows NT ?? | AQ84: Windows NT | AR84: 13 | BE84: TRUE
A85: 68a28785a4a14663c90e | B85: 안지준 | C85: 안지준 | D85: EXPENSE:카드 총괄관리자 / SUBSCRIPTION:구독 총괄 관리자 / CARD:카드 총괄관리자 | E85: 주식회사 테라퓨젠바이오 | F85: 629-86-03025 | I85: 코어그룹, 코어그룹(12월) | J85: joon.ahn@terafugen.com | P85: 112319642 | Q85: TRUE | R85: 180 | S85: 서울시 구로구 | U85: KR | V85: Asia/Seoul | W85: 2025-08-18T01:53:09.673Z | X85: FALSE | Y85: ko | Z85: 2026-02-11T04:08:01.637Z | AB85: com.gowid.expense | AC85: 2.8.4 | AD85: Samsung SM-N986N | AE85: 2026-01-31T02:50:06.496Z | AF85: Android 13 | AG85: Android | AH85: 9 | AI85: FALSE | AJ85: FALSE | AK85: 2026-02-11T04:08:01.638Z | AL85: Chrome 144 | AM85: Chrome | AN85: Desktop | AO85: 2026-02-11T04:08:01.637Z | AP85: Windows NT ?? | AQ85: Windows NT | AR85: 171 | AU85: https://www.google.com/ | BE85: TRUE | BK85: https://flow.team/
A86: 697718155ce787a56670 | B86: 조성률 | C86: 조성률 | D86: CARD:슈퍼관리자 / EXPENSE:슈퍼관리자 | E86: 캔디드 유한회사 | F86: 717-87-02844 | I86: 기가입회원/관리자/신규, 비회원 | J86: sj@teamcandid.kr | K86: =+821084625224 -> 821084625224 | P86: 122959856 | Q86: TRUE | R86: 30 | S86: 서울시 강남구 | U86: KR | V86: Asia/Seoul | W86: 2026-01-26T07:30:29.380Z | X86: FALSE | Y86: ko | Z86: 2026-02-20T00:06:55.976Z | AI86: FALSE | AJ86: FALSE | AK86: 2026-02-20T00:06:55.977Z | AL86: Chrome 144 | AM86: Chrome | AN86: Apple Macintosh | AO86: 2026-02-20T00:06:55.976Z | AP86: Mac OS >=10.15.7 | AQ86: Mac OS | AR86: 30 | AU86: https://outline.teamcandid.kr/ | BE86: TRUE | BK86: https://www.google.com/
A87: 6996a69cd3ca03317e6e | B87: 팔레트 582 | P87: 3e7120df-801d-43b6-938a-f38d6a3b5b1e | Q87: FALSE | R87: 3 | S87: 서울시 강남구 | U87: KR | V87: Asia/Seoul | W87: 2026-02-19T05:58:52.868Z | X87: FALSE | Y87: ko | Z87: 2026-02-19T07:24:41.488Z | AI87: FALSE | AJ87: FALSE | AK87: 2026-02-19T07:24:41.489Z | AL87: Chrome 144 | AM87: Chrome | AN87: Apple Macintosh | AO87: 2026-02-19T07:24:41.488Z | AP87: Mac OS >=10.15.7 | AQ87: Mac OS | AR87: 3 | AU87: https://www.google.com/ | BE87: TRUE | BK87: https://www.google.com/
A88: 65693bb77842d481d244 | B88: 정현강 | C88: 정현강 | D88: EXPENSE:슈퍼관리자 / SUBSCRIPTION:구독 총괄 관리자 / CARD:슈퍼관리자 | E88: 내이루리 주식회사 | F88: 109-86-56649 | H88: 신한 | I88: 기가입회원/관리자/기존 | J88: ceo@naeyil.com | K88: =+821095688892 -> 821095688892 | P88: 108735580 | Q88: TRUE | R88: 130 | S88: 서울시 광진구 | U88: KR | V88: Asia/Seoul | W88: 2023-12-01T01:49:43.496Z | X88: FALSE | Y88: ko | Z88: 2026-02-12T22:08:52.381Z | AB88: com.gowid.expense | AC88: 2.8.4 | AD88: Samsung SM-S908N | AE88: 2026-02-12T22:08:52.381Z | AF88: Android 14 | AG88: Android | AH88: 58 | AI88: FALSE | AJ88: FALSE | AK88: 2026-02-12T22:08:52.382Z | AL88: Chrome 144 | AM88: Chrome | AN88: Desktop | AO88: 2026-02-04T05:12:28.877Z | AP88: Windows NT ?? | AQ88: Windows NT | AR88: 72 | AU88: https://www.google.com/ | BE88: TRUE | BK88: https://www.google.com/ | BL88: 2025_11_11_channcel_talk_user
A89: 6995c7d5b5ed25c85e8b | B89: 이아현 | C89: 이아현 | D89: CARD:슈퍼관리자 | E89: (주)리아온 | F89: 425-88-02525 | J89: ceo@leaon.kr | K89: =+821021562103 -> 821021562103 | P89: 122988413 | Q89: TRUE | R89: 7 | S89: 서울시 강서구 | U89: KR | V89: Asia/Seoul | W89: 2026-02-18T14:08:21.745Z | X89: FALSE | Y89: ko | Z89: 2026-02-19T18:16:06.353Z | AI89: FALSE | AJ89: FALSE | AK89: 2026-02-19T18:16:06.354Z | AL89: Chrome 144 | AM89: Chrome | AN89: Desktop | AO89: 2026-02-19T18:16:06.353Z | AP89: Windows NT ?? | AQ89: Windows NT | AR89: 7 | AU89: https://www.google.com/ | BE89: TRUE | BK89: https://www.google.com/
A90: 67fcdcbb363f51322030 | B90: 이효진 | C90: 이효진 | D90: EXPENSE:슈퍼관리자 / CARD:슈퍼관리자 | E90: 주식회사 아이엔지로보틱스 | F90: 199-88-02553 | J90: hjlee7713@ingrobotics.com | K90: =+821037227713 -> 821037227713 | P90: 111384063 | Q90: TRUE | R90: 28 | S90: 경기도 안양시 동안구 | U90: KR | V90: Asia/Seoul | W90: 2025-04-14T10:00:27.222Z | X90: FALSE | Y90: ko | Z90: 2026-02-11T06:13:27.251Z | AI90: FALSE | AJ90: FALSE | AK90: 2026-02-11T06:13:27.252Z | AL90: Edge 144 | AM90: Edge | AN90: Desktop | AO90: 2026-02-11T06:13:27.251Z | AP90: Windows >=10 | AQ90: Windows NT | AR90: 28 | AU90: https://wmail.ecount.com/ | BE90: TRUE | BK90: https://search.naver.com/
A91: 695c9837cb14ff9fd3b6 | B91: 조명광 | C91: 조명광 | D91: CARD:슈퍼관리자 / EXPENSE:슈퍼관리자 | E91: 주식회사 코네이스 | F91: 857-81-02868 | J91: mike@conace.co.kr | K91: =+821089300982 -> 821089300982 | P91: 122924091 | Q91: TRUE | R91: 10 | S91: 서울시 마포구 | U91: KR | V91: Asia/Seoul | W91: 2026-01-06T05:05:59.832Z | X91: FALSE | Y91: ko | Z91: 2026-02-19T02:46:14.967Z | AI91: FALSE | AJ91: FALSE | AK91: 2026-02-19T02:46:14.968Z | AL91: Chrome 144 | AM91: Chrome | AN91: Desktop | AO91: 2026-02-19T02:46:14.967Z | AP91: Windows NT ?? | AQ91: Windows NT | AR91: 10 | AU91: https://corp.lottecard.co.kr/ | AV91: card-apply | AW91: PC-light-251117-NBS-V1 | AX91: paid-search | AY91: naver | AZ91: 고위드 | BE91: TRUE | BF91: naver | BG91: paid-search | BH91: card-apply | BI91: PC-light-251117-NBS-V1 | BJ91: 고위드 | BK91: https://www.google.com/
A92: 697990a46bb55e715bf8 | B92: 강미덥 | C92: 강미덥 | D92: CARD:슈퍼관리자 / EXPENSE:슈퍼관리자 | E92: 주식회사 벤치링크 | F92: 323-87-02784 | I92: 기가입회원/관리자/신규, 비회원 | J92: eric@benchlink.io | K92: =+821077632682 -> 821077632682 | P92: 122953587 | Q92: TRUE | R92: 11 | S92: 서울시 영등포구 | U92: KR | V92: Asia/Seoul | W92: 2026-01-28T04:29:24.441Z | X92: FALSE | Y92: ko | Z92: 2026-02-20T02:02:27.565Z | AI92: FALSE | AJ92: FALSE | AK92: 2026-02-20T02:02:27.566Z | AL92: Chrome 144 | AM92: Chrome | AN92: Desktop | AO92: 2026-02-20T02:02:27.565Z | AP92: Windows NT ?? | AQ92: Windows NT | AR92: 11 | AU92: https://www.google.com/ | BE92: TRUE | BK92: https://www.google.com/
A93: 6969aca0931c24a457c0 | B93: 김윤미 | C93: 김윤미 | J93: hoihoi0615@printpac.co.kr | K93: =+821031815243 -> 821031815243 | P93: 5c1324ad-985e-4638-96c5-054671b06399 | Q93: FALSE | R93: 4 | S93: 경기도 화성시 | U93: KR | V93: Asia/Seoul | W93: 2026-01-16T03:12:32.602Z | X93: FALSE | Y93: ko | Z93: 2026-02-13T07:02:28.493Z | AI93: FALSE | AJ93: FALSE | AK93: 2026-02-13T07:02:28.494Z | AL93: Edge 144 | AM93: Edge | AN93: Desktop | AO93: 2026-02-13T07:02:28.493Z | AP93: Windows >=10 | AQ93: Windows NT | AR93: 4 | BE93: TRUE
A94: 695362248196dfe3dc5f | B94: 이소현 | C94: 이소현 | D94: EXPENSE:슈퍼관리자 / CARD:슈퍼관리자 | E94: (주)싸이어스 | F94: 367-81-02555 | I94: 기가입회원/관리자/신규, 기가입회원/관리자/기존 | J94: sohyun0823@cyers.co.kr | K94: =+821096492080 -> 821096492080 | P94: 112559158 | Q94: TRUE | R94: 103 | S94: 경기도 안양시 동안구 | U94: KR | V94: Asia/Seoul | W94: 2025-12-30T05:24:52.530Z | X94: FALSE | Y94: ko | Z94: 2026-02-11T07:31:46.589Z | AB94: com.gowid.expense | AC94: 2.8.4 | AD94: Samsung SM-S931N | AE94: 2026-02-11T06:39:15.346Z | AF94: Android 16 | AG94: Android | AH94: 46 | AI94: FALSE | AJ94: FALSE | AK94: 2026-02-11T07:31:46.590Z | AL94: Chrome 144 | AM94: Chrome | AN94: Desktop | AO94: 2026-02-11T07:31:46.589Z | AP94: Windows NT ?? | AQ94: Windows NT | AR94: 57 | AU94: https://www.bing.com/ | BE94: TRUE | BK94: https://docs.channel.io/
A95: 698adac9d13b25e3a10b | B95: 송현규 | C95: 송현규 | D95: CARD:슈퍼관리자 / SUBSCRIPTION:구독 총괄 관리자 | E95: 주식회사 프라이스잇(priceit. Co.,Ltd.) | F95: 431-86-03466 | J95: hg.song@priceit.kr | K95: =+821028833743 -> 821028833743 | P95: 122993780 | Q95: TRUE | R95: 8 | S95: 서울시 강남구 | U95: KR | V95: Asia/Seoul | W95: 2026-02-10T07:14:17.857Z | X95: FALSE | Y95: ko | Z95: 2026-02-19T00:00:46.732Z | AI95: FALSE | AJ95: FALSE | AK95: 2026-02-19T00:24:24.108Z | AL95: Chrome 145 | AM95: Chrome | AN95: Desktop | AO95: 2026-02-19T00:00:46.732Z | AP95: Windows NT ?? | AQ95: Windows NT | AR95: 8 | AU95: https://www.google.com/ | BE95: TRUE | BK95: https://payment-gateway.tosspayments.com/
A96: 69444ec552e0036a094c | B96: Bob | C96: Bob | D96: EXPENSE:일반 멤버 / CARD:일반 멤버 | E96: 주식회사 뤼튼테크놀로지스 | F96: 202-81-67042 | I96: 기가입회원/소지자 | J96: bob@wrtn.io | P96: 109948695 | Q96: TRUE | R96: 33 | S96: 서울시 강서구 | U96: KR | V96: Asia/Seoul | W96: 2025-12-18T18:58:13.339Z | X96: FALSE | Y96: ko | Z96: 2026-02-20T00:24:50.942Z | AB96: com.gowid.expense | AC96: 2.8.4 | AD96: Samsung SM-S916N | AE96: 2026-02-20T00:24:50.942Z | AF96: Android 16 | AG96: Android | AH96: 33 | AI96: FALSE | AJ96: FALSE | AK96: 2026-02-20T00:24:50.943Z | BE96: TRUE
A97: 670f10549d5d9ce2643b | B97: Lara Park (박민희) | C97: Lara Park (박민희) | D97: EXPENSE:슈퍼관리자 / SUBSCRIPTION:구독 총괄 관리자 / CARD:슈퍼관리자 | E97: 주식회사 나니아랩스 | F97: 191-88-02340 | I97: 기가입회원/관리자/기존, 비회원 | J97: lara.park@narnia.ai | K97: =+821091308746 -> 821091308746 | P97: 111107325 | Q97: TRUE | R97: 679 | S97: 서울시 용산구 | U97: KR | V97: Asia/Seoul | W97: 2024-10-16T01:01:08.644Z | X97: FALSE | Y97: ko | Z97: 2026-02-18T01:43:15.218Z | AB97: com.gowid.expense | AC97: 2.8.4 | AD97: Samsung SM-S911N | AE97: 2026-02-15T10:46:49.209Z | AF97: Android 16 | AG97: Android | AH97: 137 | AI97: FALSE | AJ97: FALSE | AK97: 2026-02-18T01:43:15.219Z | AL97: Chrome 144 | AM97: Chrome | AN97: Desktop | AO97: 2026-02-18T01:43:15.218Z | AP97: Windows NT ?? | AQ97: Windows NT | AR97: 542 | AU97: https://search.naver.com/search.naver?where=nexearch&sm=top_hty&fbm=0&ie=utf8&query=%EA%B3%A0%EC%9C%84%EB%93%9C | BE97: TRUE | BK97: https://payment-gateway.tosspayments.com/
A98: 688b815dcc8379f5698f | B98: 방정훈 | C98: 방정훈 | D98: EXPENSE:슈퍼관리자 / CARD:슈퍼관리자 | E98: 주식회사 시그 | F98: 727-87-02292 | H98: 신한 | I98: 기가입회원/관리자/기존 | J98: bang@sigcrew.com | K98: =+821027486163 -> 821027486163 | P98: 117023859 | Q98: TRUE | R98: 14 | S98: 서울시 영등포구 | U98: KR | V98: Asia/Seoul | W98: 2025-07-31T14:44:45.838Z | X98: FALSE | Y98: ko | Z98: 2026-02-10T12:09:34.107Z | AI98: FALSE | AJ98: FALSE | AK98: 2026-02-10T12:09:34.108Z | AL98: Chrome 144 | AM98: Chrome | AN98: Apple Macintosh | AO98: 2026-02-10T12:09:34.107Z | AP98: Mac OS >=10.15.7 | AQ98: Mac OS | AR98: 14 | AU98: https://www.google.com/ | BE98: TRUE | BK98: https://www.google.com/
A99: 696652e08c7a12256ccc | B99: 국경민 | C99: 국경민 | D99: CARD:슈퍼관리자 / SUBSCRIPTION:구독 총괄 관리자 | E99: 주식회사 웰케어스테이션 | F99: 788-81-03300 | I99: 기가입회원/관리자/신규 | J99: brian@wellcarestation.com | K99: =+821027992713 -> 821027992713 | P99: 122954680 | Q99: TRUE | R99: 17 | S99: 서울시 강남구 | U99: KR | V99: Asia/Seoul | W99: 2026-01-13T14:12:48.575Z | X99: FALSE | Y99: ko | Z99: 2026-01-29T07:15:34.017Z | AI99: FALSE | AJ99: FALSE | AK99: 2026-01-29T07:15:34.018Z | AL99: Safari 18.4 | AM99: Safari | AN99: Apple Macintosh | AO99: 2026-01-29T02:31:24.066Z | AP99: Mac OS >=10.15.7 | AQ99: Mac OS | AR99: 17 | AU99: https://www.google.com/ | AV99: authority-01-2026 | AW99: gowid-card-image | AX99: paid-search | AY99: google | AZ99: 법인카드 | BE99: TRUE | BF99: google | BG99: paid-search | BH99: authority-01-2026 | BI99: gowid-card-image | BJ99: 법인카드 | BK99: https://www.google.com/
A100: 698ab8f337bc8195640a | B100: 지니 792 | P100: 429cd200-d885-4269-a451-43ea456428fa | Q100: FALSE | R100: 1 | S100: 서울시 강북구 | U100: KR | V100: Asia/Seoul | W100: 2026-02-10T04:49:55.228Z | X100: FALSE | Y100: ko | Z100: 2026-02-10T04:49:55.227Z | AI100: FALSE | AJ100: FALSE | AK100: 2026-02-10T04:49:55.228Z | AL100: Whale 4.35.351.16 | AM100: Whale | AN100: Desktop | AO100: 2026-02-10T04:49:55.227Z | AP100: Windows NT ?? | AQ100: Windows NT | AR100: 1 | AU100: https://search.naver.com/ | BE100: TRUE | BK100: https://search.naver.com/
...
